Workbook

Sheet CIERRE CAJA ENE26
B1: BODEGA 3
B2: CIERRE DE CAJA DIARIO
B3: INGRESOS: | D3: TASA: | E3: 86 | F3: =SUM(F5:F35) -> 2657 | G3: =SUM(G5:G35) -> 0 | H3: =SUM(H5:H35) -> #DIV/0! | I3: =TODAY() -> 46177 | K3: INGRESOS | N3: FORMAS DE PAGO:
A4: ITEM | B4: FECHA | C4: DESCRIPCION | D4: EFECTIVO | E4: PAGO MOVIL | F4: CASH $ | G4: ZELLE | H4: %ING/GAN | I4: TOTAL | K4: DESCRIPCION | L4: MONTO | M4: % | N4: INGRESOS: | O4: $ | P4: Bs
A5: =IF(B5="","",1) -> 1 | B5: 46027 | C5: INGRESO POR VENTAS DESDE EL 01 HASTA EL 03 DE ENERO | F5: 885 | H5: =IF(B5="","",F5/$L$9) -> 0.33308242 | I5: =IF(C5="","",(SUM(D5:E5)/$E$3)+SUM(F5:G5)) -> 885 | J5: =MID(C5,1,8) -> INGRESO | K5: {=UNIQUE($J$5:$J$35,0,0)} -> INGRESO | L5: =SUMIFS($I$5:$I$35,$J$5:$J$35,K5) -> 2657 | M5: =IF(L5=0,"",L5/$L$9) -> 1 | N5: {=TRANSPOSE(D4:G4)} -> EFECTIVO | O5: =D36/$E$3 -> 0 | P5: =D36 -> 0
A6: =IF(B6="","",A5+1) -> 2 | B6: 46034 | C6: INGRESO POR VENTAS DESDE EL 04 HASTA EL 07 DE ENERO | F6: 625 | H6: =IF(B6="","",F6/$L$7) -> #DIV/0! | I6: =IF(C6="","",(SUM(D6:E6)/$E$3)+SUM(F6:G6)) -> 625 | J6: =MID(C6,1,8) -> INGRESO | K6: GANANCIA | L6: =SUMIFS($I$5:$I$35,$J$5:$J$35,K6) -> 0 | M6: =IF(L6=0,"",L6/$L$9) | N6: PAGO MOVIL | O6: =E36/$E$3 -> 0 | P6: =E36 -> 0
A7: =IF(B7="","",A6+1) -> 3 | B7: 46028 | C7: GANANCIA POR TASA CAMBIARIA INVERSIONES DOBLE PICA | H7: =IF(B7="","",F7/$L$7) -> #DIV/0! | I7: =IF(C7="","",(SUM(D7:E7)/$E$3)+SUM(F7:G7)) -> 0 | J7: =MID(C7,1,8) -> GANANCIA | L7: =SUMIFS($I$5:$I$35,$J$5:$J$35,K7) -> 0 | M7: =IF(L7=0,"",L7/$L$9) | N7: CASH $ | O7: =F36 -> 2657
A8: =IF(B8="","",A7+1) | H8: =IF(B8="","",F8/$L$7) | I8: =IF(C8="","",(SUM(D8:E8)/$E$3)+SUM(F8:G8)) | J8: =MID(C8,1,8) | N8: ZELLE | O8: =G36 -> 0
A9: =IF(B9="","",A8+1) | H9: =IF(B9="","",F9/$L$7) | I9: =IF(C9="","",(SUM(D9:E9)/$E$3)+SUM(F9:G9)) | J9: =MID(C9,1,8) | K9: TOTALES: | L9: =SUM(L5:L6) -> 2657 | M9: =SUM(M5:M6) -> 1
A10: =IF(B10="","",A9+1) | H10: =IF(B10="","",F10/$L$7) | I10: =IF(C10="","",(SUM(D10:E10)/$E$3)+SUM(F10:G10)) | J10: =MID(C10,1,8) | O10: =SUM(O5:O9) -> 2657 | P10: =SUM(P5:P9) -> 0
A11: =IF(B11="","",A10+1) -> 1 | B11: 46037 | C11: INGRESO POR VENTAS DESDE EL 08 AL 14 DE ENERO | F11: 1147 | H11: =IF(B11="","",F11/$L$7) -> #DIV/0! | I11: =IF(C11="","",(SUM(D11:E11)/$E$3)+SUM(F11:G11)) -> 1147 | J11: =MID(C11,1,8) -> INGRESO | N11: EGRESOS: | O11: $ | P11: Bs
A12: =IF(B12="","",A11+1) | H12: =IF(B12="","",F12/$L$7) | I12: =IF(C12="","",(SUM(D12:E12)/$E$3)+SUM(F12:G12)) | J12: =MID(C12,1,8) | N12: {=TRANSPOSE(D4:G4)} -> EFECTIVO | O12: =D66/$E$3 -> 0 | P12: =D66 -> 0
A13: =IF(B13="","",A12+1) | H13: =IF(B13="","",F13/$L$7) | I13: =IF(C13="","",(SUM(D13:E13)/$E$3)+SUM(F13:G13)) | J13: =MID(C13,1,8) | N13: PAGO MOVIL | O13: =E66/$E$3 -> 0 | P13: =E66 -> 0
A14: =IF(B14="","",A13+1) | H14: =IF(B14="","",F14/$L$7) | I14: =IF(C14="","",(SUM(D14:E14)/$E$3)+SUM(F14:G14)) | J14: =MID(C14,1,8) | N14: CASH $ | O14: =F66 -> 1003.4
A15: =IF(B15="","",A14+1) | H15: =IF(B15="","",F15/$L$7) | I15: =IF(C15="","",(SUM(D15:E15)/$E$3)+SUM(F15:G15)) | J15: =MID(C15,1,8) | N15: ZELLE | O15: =G66 -> 0
A16: =IF(B16="","",A15+1) | H16: =IF(B16="","",F16/$L$7) | I16: =IF(C16="","",(SUM(D16:E16)/$E$3)+SUM(F16:G16)) | J16: =MID(C16,1,8)
A17: =IF(B17="","",A16+1) | H17: =IF(B17="","",F17/$L$7) | I17: =IF(C17="","",(SUM(D17:E17)/$E$3)+SUM(F17:G17)) | J17: =MID(C17,1,8) | O17: =SUM(O12:O16) -> 1003.4 | P17: =SUM(P12:P16) -> 0
A18: =IF(B18="","",A17+1) | H18: =IF(B18="","",F18/$L$7) | I18: =IF(C18="","",(SUM(D18:E18)/$E$3)+SUM(F18:G18)) | J18: =MID(C18,1,8)
A19: =IF(B19="","",A18+1) | H19: =IF(B19="","",F19/$L$7) | I19: =IF(C19="","",(SUM(D19:E19)/$E$3)+SUM(F19:G19)) | J19: =MID(C19,1,8)
A20: =IF(B20="","",A19+1) | I20: =IF(C20="","",(SUM(D20:E20)/$E$3)+SUM(F20:H20)) | J20: =MID(C20,1,8)
A21: =IF(B21="","",A20+1) | H21: =IF(B21="","",F21/$L$7) | I21: =IF(C21="","",(SUM(D21:E21)/$E$3)+SUM(F21:G21)) | J21: =MID(C21,1,8) | N21: SALDOS AL CIERRE DE CAJA: | Q21: DISTRIBUCION DEL CASH
A22: =IF(B22="","",A21+1) | H22: =IF(B22="","",F22/$L$7) | I22: =IF(C22="","",(SUM(D22:E22)/$E$3)+SUM(F22:G22)) | J22: =MID(C22,1,8) | N22: SDO ANTERIOR: | O22: 0 | R22: 100 | S22: =Q22*R22 -> 0
A23: =IF(B23="","",A22+1) | H23: =IF(B23="","",F23/$L$7) | I23: =IF(C23="","",(SUM(D23:E23)/$E$3)+SUM(F23:G23)) | J23: =MID(C23,1,8) | N23: EFECTIVO | O23: =O5-O12 -> 0 | R23: 50 | S23: =Q23*R23 -> 0
A24: =IF(B24="","",A23+1) | H24: =IF(B24="","",F24/$L$7) | I24: =IF(C24="","",(SUM(D24:E24)/$E$3)+SUM(F24:G24)) | J24: =MID(C24,1,8) | N24: PAGO MOVIL | O24: =O6-O13 -> 0 | R24: 20 | S24: =Q24*R24 -> 0
A25: =IF(B25="","",A24+1) | H25: =IF(B25="","",F25/$L$7) | I25: =IF(C25="","",(SUM(D25:E25)/$E$3)+SUM(F25:G25)) | J25: =MID(C25,1,8) | N25: CASH $ | O25: =O7-O14 -> 1653.6 | R25: 10 | S25: =Q25*R25 -> 0
A26: =IF(B26="","",A25+1) | H26: =IF(B26="","",F26/$L$7) | I26: =IF(C26="","",(SUM(D26:E26)/$E$3)+SUM(F26:G26)) | J26: =MID(C26,1,8) | N26: ZELLE | O26: =O8-O15 -> 0 | R26: 5 | S26: =Q26*R26 -> 0
A27: =IF(B27="","",A26+1) | H27: =IF(B27="","",F27/$L$7) | I27: =IF(C27="","",(SUM(D27:E27)/$E$3)+SUM(F27:G27)) | J27: =MID(C27,1,8) | N27: ORO | O27: =O9-O16 -> 0 | R27: 1 | S27: =Q27*R27 -> 0
A28: =IF(B28="","",A27+1) | H28: =IF(B28="","",F28/$L$7) | I28: =IF(C28="","",(SUM(D28:E28)/$E$3)+SUM(F28:G28)) | J28: =MID(C28,1,8) | N28: TOTAL: | O28: =SUM(O22:O27) -> 1653.6 | Q28: TOTAL: | S28: =SUM(S22:S27) -> 0
A29: =IF(B29="","",A28+1) | H29: =IF(B29="","",F29/$L$7) | I29: =IF(C29="","",(SUM(D29:E29)/$E$3)+SUM(F29:G29)) | J29: =MID(C29,1,8) | Q29: DIFERENCIA: | S29: =S28-O25 -> -1653.6
A30: =IF(B30="","",A29+1) | H30: =IF(B30="","",F30/$L$7) | I30: =IF(C30="","",(SUM(D30:E30)/$E$3)+SUM(F30:G30)) | J30: =MID(C30,1,8)
A31: =IF(B31="","",A30+1) | H31: =IF(B31="","",F31/$L$7) | I31: =IF(C31="","",(SUM(D31:E31)/$E$3)+SUM(F31:G31)) | J31: =MID(C31,1,8)
A32: =IF(B32="","",A31+1) | H32: =IF(B32="","",F32/$L$7) | I32: =IF(C32="","",(SUM(D32:E32)/$E$3)+SUM(F32:G32)) | J32: =MID(C32,1,8)
A33: =IF(B33="","",A32+1) | H33: =IF(B33="","",F33/$L$7) | I33: =IF(C33="","",(SUM(D33:E33)/$E$3)+SUM(F33:G33)) | J33: =MID(C33,1,8)
A34: =IF(B34="","",A33+1) | H34: =IF(B34="","",F34/$L$7) | I34: =IF(C34="","",(SUM(D34:E34)/$E$3)+SUM(F34:G34)) | J34: =MID(C34,1,8)
A35: =IF(B35="","",A34+1) | H35: =IF(B35="","",F35/$L$7) | I35: =IF(C35="","",(SUM(D35:E35)/$E$3)+SUM(F35:G35)) | J35: =MID(C35,1,8)
B36: TOTAL INGRESOS: | D36: =SUM(D5:D35) -> 0 | E36: =SUM(E5:E35) -> 0 | F36: =SUM(F5:F35) -> 2657 | G36: =SUM(G5:G35) -> 0 | H36: =SUM(H5:H35) -> #DIV/0! | I36: =SUM(I5:I35) -> 2657
B37: EGRESOS:
B38: FECHA | C38: DESCRIPCION | D38: EFECTIVO | E38: PAGO MOVIL | F38: CASH $ | G38: ZELLE | H38: ORO | I38: TOTAL
A39: =IF(B39="","",1) -> 1 | B39: 46028 | C39: COMPRA INVERSIONES DOBLE PICA | F39: 753.4 | I39: =F39 -> 753.4 | J39: 19,53*
A40: =IF(B40="","",A39+1) | I40: =F40 | J40: *
A41: =IF(B41="","",A40+1) | I41: =F41 | J41: *
A42: =IF(B42="","",A41+1) | I42: =F42 | J42: *
A43: =IF(B43="","",A42+1) | I43: =F43 | J43: *
A44: =IF(B44="","",A43+1) -> 1 | B44: 46037 | C44: NOMINA 1RA QUINCENA ENCARDAO CANAIMA | F44: 200 | I44: =F44 -> 200 | J44: *
A45: =IF(B45="","",A44+1) -> 2 | B45: 46037 | C45: NOMINA 1RA QUINCENA ADMINISTRADORA | F45: 50 | I45: =F45 -> 50 | J45: *
A46: =IF(B46="","",A45+1) | I46: =F46 | J46: *
A47: =IF(B47="","",A46+1) | I47: =F47
A48: =IF(B48="","",A47+1) | I48: =F48 | J48: *
A49: =IF(B49="","",A48+1) | I49: =F49 | J49: *
A50: =IF(B50="","",A49+1) | I50: =F50 | J50: *
A51: =IF(B51="","",A50+1) | I51: =F51 | J51: *
A52: =IF(B52="","",A51+1) | I52: =F52
A53: =IF(B53="","",A52+1) | I53: =F53
A54: =IF(B54="","",A53+1) | I54: =F54
A55: =IF(B55="","",A54+1) | I55: =F55
A56: =IF(B56="","",A55+1) | I56: =F56
A57: =IF(B57="","",A56+1) | I57: =F57
A58: =IF(B58="","",A57+1) | I58: =F58
A59: =IF(B59="","",A58+1) | I59: =F59
A60: =IF(B60="","",A59+1) | I60: =F60
A61: =IF(B61="","",A60+1) | I61: =F61
A62: =IF(B62="","",A61+1) | I62: =F62
A63: =IF(B63="","",A62+1) | I63: =F63
... A65: =IF(B65="","",A64+1) | I65: =F65
B66: TOTAL EGRESOS: | D66: =SUM(D39:D65) -> 0 | E66: =SUM(E39:E65) -> 0 | F66: =SUM(F39:F65) -> 1003.4 | G66: =SUM(G39:G65) -> 0 | H66: =SUM(H39:H65) -> 0 | I66: =SUM(I39:I65) -> 1003.4
A67: =IF(B67="","",A66+1) | G67: SALDO | I67: =I36-I66 -> 1653.6

Sheet CAMBIO DIVISAS
A1: FECHA | B1: DESCRIPCION | C1: PROVEEDOR | D1: MONTO BS | E1: BCV | F1: MONTO | G1: TASA | H1: CAMBIO | I1: GANANCIA | J1: ESTATUS DEL CAMBIO
A2: 45992 | B2: INVERSIONES DOBLE PICA | C2: EXTERNO | D2: 82276.71 | E2: 247.3 | F2: =D2/E2 -> 332.7 | G2: 370 | H2: =D2/G2 -> 222.36949 | I2: =F2-H2 -> 110.33051 | J2: PAGADO
A3: 45992 | B3: TODO ALIMENTOS ORIENTE | C3: EXTERNO | D3: 230235.39 | E3: 247.4 | F3: =D3/E3 -> 930.62001 | G3: 370 | H3: =D3/G3 -> 622.25781 | I3: =F3-H3 -> 308.3622 | J3: PAGADO
A4: 45993 | B4: STARLINK | C4: BERKANA | D4: 0 | E4: 0 | F4: 0 | H4: 150 | I4: 0 | J4: PAGADO
A5: 45995 | B5: HUEVOS Y QUESO | C5: EXTERNO | D5: 66776 | E5: 257.93 | F5: =D5/E5 -> 258.89195 | G5: 411 | H5: 161 | I5: =F5-H5 -> 97.891947 | J5: PAGADO
A6: 45995 | B6: HALLACAS | C6: BERKANA CALLAO | D6: 16824 | E6: 254.92 | F6: =D6/E6 -> 65.997176 | G6: 390 | H6: =D6/G6 -> 43.138462 | I6: =F6-H6 -> 22.858714 | J6: PAGADO
A7: 45999 | B7: REFRESCOS | C7: BERKANA | D7: 5313.16 | E7: 257.92 | F7: =D7/E7 -> 20.600031 | G7: 390 | H7: =D7/G7 -> 13.623487 | I7: =F7-H7 -> 6.9765438 | J7: PAGADO
A8: 45999 | B8: PAN DE JAMON | C8: BERKANA | D8: 16765.5 | E8: 257.92 | F8: =D8/E8 -> 65.002714 | G8: 390 | H8: =D8/G8 -> 42.988462 | I8: =F8-H8 -> 22.014252 | J8: PAGADO
A9: 46001 | B9: HALLACAS | C9: BERKANA CALLAO | D9: 34600 | E9: 262.1 | F9: =D9/E9 -> 132.01068 | G9: 420 | H9: =D9/G9 -> 82.380952 | I9: =F9-H9 -> 49.629731 | J9: PAGADO
A10: 46003 | B10: INVERSIONES DOBLE PICA | C10: EXTERNO | D10: 135197.69 | E10: 267.75 | F10: =D10/E10 -> 504.94002 | G10: 400 | H10: =D10/G10 -> 337.99422 | I10: =F10-H10 -> 166.94579 | J10: PAGADO
A11: 46006 | B11: HALLACAS | C11: BERKANA CALLAO | D11: 18254.28 | E11: 276.58 | F11: =D11/E11 -> 66 | G11: 420 | H11: =D11/G11 -> 43.462571 | I11: =F11-H11 -> 22.537429 | J11: PAGADO
A12: 46009 | B12: HUEVOS | C12: OMAR | D12: 36342.8 | E12: 279.56 | F12: =D12/E12 -> 130 | G12: 420 | H12: =D12/G12 -> 86.530476 | I12: =F12-H12 -> 43.469524 | J12: PAGADO
A13: 46009 | B13: PAN DE JAMON | C13: BERKANA | D13: 17977.7 | E13: 276.58 | F13: =D13/E13 -> 65 | G13: 420 | H13: =D13/G13 -> 42.804048 | I13: =F13-H13 -> 22.195952 | J13: PAGADO
A14: 46013 | B14: HALLACAS | C14: BERKANA | D14: 18265.85 | E14: 285.4 | F14: =D14/E14 -> 64.000876 | G14: 450 | H14: =D14/G14 -> 40.590778 | I14: =F14-H14 -> 23.410098 | J14: PAGADO
A15: 46014 | B15: CESTA | C15: BERKANA | D15: 2307.6 | E15: 288.45 | F15: =D15/E15 -> 8 | G15: 450 | H15: =D15/G15 -> 5.128 | I15: =F15-H15 -> 2.872 | J15: PAGADO
A16: 46014 | B16: BARAKI | C16: EXTERNO | D16: 19107.333 | E16: 288.45 | F16: =D16/E16 -> 66.241405 | G16: 450 | H16: =D16/G16 -> 42.460741 | I16: =F16-H16 -> 23.780664 | J16: PAGADO
A17: 46014 | B17: LA BODEGA | C17: BERKANA | D17: 4182.53 | E17: 288.45 | F17: =D17/E17 -> 14.500017 | G17: 450 | H17: =D17/G17 -> 9.2945111 | I17: =F17-H17 -> 5.2055062 | J17: PAGADO
A18: 46014 | B18: PAPELERIA | C18: BERKANA | D18: 447 | E18: 288.45 | F18: =D18/E18 -> 1.549662 | G18: 450 | H18: =D18/G18 -> 0.99333333 | I18: =F18-H18 -> 0.55632865 | J18: PAGADO
A19: 46015 | B19: POLLO | C19: JONATHAN | F19: 135 | H19: 0 | I19: 0 | J19: PAGADO
A20: 46015 | B20: HUEVOS | C20: OMAR | D20: 37875.5 | E20: 291.35 | F20: =D20/E20 -> 130 | G20: 450 | H20: =D20/G20 -> 84.167778 | I20: =F20-H20 -> 45.832222 | J20: PAGADO
A21: 46017 | B21: DOBLE PICA | C21: DANIEL | D21: 257949.38 | E21: 291.35 | F21: =D21/E21 -> 885.35912 | G21: 470 | H21: =D21/G21 -> 548.82847 | I21: =F21-H21 -> 336.53065 | J21: PAGADO
A22: 46017 | B22: INV. UNARE 3 | C22: DANIEL | D22: =11263.59+16641.92 -> 27905.51 | E22: 291.35 | F22: =D22/E22 -> 95.780024 | G22: 470 | H22: =D22/G22 -> 59.373426 | I22: =F22-H22 -> 36.406598 | J22: PAGADO
A23: 46020 | B23: HALLACAS | C23: BERKANA | D23: 28317.84 | E23: 294.963 | F23: =D23/E23 -> 96.004719 | G23: 485 | H23: =D23/G23 -> 58.387299 | I23: =F23-H23 -> 37.61742 | J23: PAGADO
A24: 46386 | B24: HALLACAS | C24: EXTERNO | D24: 29814.3 | E24: 298.14 | F24: =D24/E24 -> 100.00101 | G24: 505 | H24: =D24/G24 -> 59.038218 | I24: =F24-H24 -> 40.962788 | J24: PAGADO
A25: 46386 | B25: PAN DE JAMON | C25: EXTERNO | D25: 29497 | E25: 294.969 | F25: =D25/E25 -> 100.00034 | G25: 500 | H25: =D25/G25 -> 58.994 | I25: =F25-H25 -> 41.006339 | J25: PAGADO
A26: 46028 | B26: DOBLE PICA | C26: EXTERNO | D26: 232160.89 | E26: 308.15 | F26: =D26/E26 -> 753.40221 | G26: 550 | H26: =D26/G26 -> 422.11071 | I26: =F26-H26 -> 331.2915 | J26: PAGADO
A27: 46028 | B27: INV. UNARE 3 | C27: EXTERNO | D27: 13537.03 | E27: 308.15 | F27: =D27/E27 -> 43.930002 | G27: 550 | H27: =D27/G27 -> 24.612782 | I27: =F27-H27 -> 19.31722 | J27: PAGADO
A28: 46035 | B28: DOBLE PICA | C28: BERKANA | D28: 190252.62 | E28: 330.38 | F28: =D28/E28 -> 575.85998 | G28: 520 | H28: =D28/G28 -> 365.87042 | I28: =F28-H28 -> 209.98956 | J28: PENDIENTE
A29: 46035 | B29: FARMACIA EL FORTIN | C29: EXTERNO | D29: 61570.26 | E29: 330.38 | F29: =D29/E29 -> 186.36195 | G29: 520 | H29: =D29/G29 -> 118.40435 | I29: =F29-H29 -> 67.957601 | J29: PENDIENTE
A30: 46035 | B30: COMERCIAL ALBAVEN | C30: EXTERNO | D30: 9795.77 | E30: 330.38 | F30: =D30/E30 -> 29.650009 | G30: 520 | H30: =D30/G30 -> 18.838019 | I30: =F30-H30 -> 10.81199 | J30: PENDIENTE
F31: =D31/E31 -> #DIV/0! | H31: =D31/G31 -> #DIV/0! | I31: =F31-H31 -> #DIV/0!
F32: =D32/E32 -> #DIV/0! | H32: =D32/G32 -> #DIV/0! | I32: =F32-H32 -> #DIV/0!
F33: =D33/E33 -> #DIV/0! | H33: =D33/G33 -> #DIV/0! | I33: =F33-H33 -> #DIV/0!
F34: =D34/E34 -> #DIV/0! | H34: =D34/G34 -> #DIV/0! | I34: =F34-H34 -> #DIV/0!
F35: =D35/E35 -> #DIV/0! | H35: =D35/G35 -> #DIV/0! | I35: =F35-H35 -> #DIV/0!
F36: =D36/E36 -> #DIV/0! | H36: =D36/G36 -> #DIV/0! | I36: =F36-H36 -> #DIV/0!
F37: =D37/E37 -> #DIV/0! | H37: =D37/G37 -> #DIV/0! | I37: =F37-H37 -> #DIV/0!
F38: =D38/E38 -> #DIV/0! | H38: =D38/G38 -> #DIV/0! | I38: =F38-H38 -> #DIV/0!

Sheet VENTAS
B1: BODEGA3 | O1: BODEGA3
F2: VENTAS $ | I2: VENTAS Bs. | L2: TOTAL $ | S2: TOTALES
F3: =SUM(F5:F14000) -> 2485.1 | H3: =SUM(H5:H14000) -> 3066.2374 | K3: =SUM(K5:K14000) -> 0 | L3: =SUM(L5:L14000) -> 3066.2374 | O3: 46024 | S3: =SUM(S5:S14000) -> 237.85 | U3: =SUM(U5:U14000) -> 361.4987
B4: FECHA | C4: CLIENTE | D4: PRODUCTO | E4: COD/PROD | F4: CANT | G4: PRECIO/UNIT $ | H4: MONTO/TOTAL | I4: PRECIO UNIT Bs | J4: TASA | K4: TOTAL Bs | L4: MONTO TOTAL $ | O4: FECHA | P4: CLIENTE | Q4: PRODUCTO | R4: COD/PROD | S4: CANT | T4: PRECIO/UNIT | U4: MONTO/TOTAL
B5: 46023 | C5: CONSUMIDOR FINAL | D5: Belmont | E5: {=IF(D5="","",XLOOKUP(D5,DATOS!$D$6:D14000,DATOS!$C$6:C14000,0,0,1))} -> BELM | F5: 8 | G5: 0.25 | H5: =IF(F5="","",(F5*G5)) -> 2 | K5: =IF(I5="","",(F5*I5)) | L5: =IF(I5="",H5,H5+(K5/J5)) -> 2 | O5: =IFERROR(__xludf.DUMMYFUNCTION("FILTER(B5:J14000,B5:B14000=O3)"),46024.0) -> 46024 | P5: =IFERROR(__xludf.DUMMYFUNCTION("""COMPUTED_VALUE"""),"CONSUMIDOR FINAL") -> CONSUMIDOR FINAL | Q5: =IFERROR(__xludf.DUMMYFUNCTION("""COMPUTED_VALUE"""),"Huevo") -> Huevo | R5: =IFERROR(__xludf.DUMMYFUNCTION("""COMPUTED_VALUE"""),"HUEVO") -> HUEVO | S5: =IFERROR(__xludf.DUMMYFUNCTION("""COMPUTED_VALUE"""),15.0) -> 15 | T5: =IFERROR(__xludf.DUMMYFUNCTION("""COMPUTED_VALUE"""),0.3333) -> 0.3333 | U5: =IFERROR(__xludf.DUMMYFUNCTION("""COMPUTED_VALUE"""),4.999499999999999) -> 4.9995
B6: 46023 | C6: CONSUMIDOR FINAL | D6: HALLACAS | E6: {=IF(D6="","",XLOOKUP(D6,DATOS!$D$6:D14000,DATOS!$C$6:C14000,0,0,1))} -> 00050 | F6: 2 | G6: 4.5 | H6: =IF(F6="","",(F6*G6)) -> 9 | K6: =IF(I6="","",(F6*I6)) | L6: =IF(I6="",H6,H6+(K6/J6)) -> 9 | O6: =IFERROR(__xludf.DUMMYFUNCTION("""COMPUTED_VALUE"""),46024.0) -> 46024 | P6: =IFERROR(__xludf.DUMMYFUNCTION("""COMPUTED_VALUE"""),"CONSUMIDOR FINAL") -> CONSUMIDOR FINAL | Q6: =IFERROR(__xludf.DUMMYFUNCTION("""COMPUTED_VALUE"""),"Caramelos Bianchi") -> Caramelos Bianchi | R6: =IFERROR(__xludf.DUMMYFUNCTION("""COMPUTED_VALUE"""),"CARM2") -> CARM2 | S6: =IFERROR(__xludf.DUMMYFUNCTION("""COMPUTED_VALUE"""),5.0) -> 5 | T6: =IFERROR(__xludf.DUMMYFUNCTION("""COMPUTED_VALUE"""),0.1) -> 0.1 | U6: =IFERROR(__xludf.DUMMYFUNCTION("""COMPUTED_VALUE"""),0.5) -> 0.5
B7: 46023 | C7: CONSUMIDOR FINAL | D7: Refrescos 1lt | E7: {=IF(D7="","",XLOOKUP(D7,DATOS!$D$6:D14000,DATOS!$C$6:C14000,0,0,1))} -> REF3 | F7: 1 | G7: 3 | H7: =IF(F7="","",(F7*G7)) -> 3 | K7: =IF(I7="","",(F7*I7)) | L7: =IF(I7="",H7,H7+(K7/J7)) -> 3 | O7: =IFERROR(__xludf.DUMMYFUNCTION("""COMPUTED_VALUE"""),46024.0) -> 46024 | P7: =IFERROR(__xludf.DUMMYFUNCTION("""COMPUTED_VALUE"""),"CONSUMIDOR FINAL") -> CONSUMIDOR FINAL | Q7: =IFERROR(__xludf.DUMMYFUNCTION("""COMPUTED_VALUE"""),"CARAMELOS FRUTICAS 100UND") -> CARAMELOS FRUTICAS 100UND | R7: =IFERROR(__xludf.DUMMYFUNCTION("""COMPUTED_VALUE"""),"CARM005") -> CARM005 | S7: =IFERROR(__xludf.DUMMYFUNCTION("""COMPUTED_VALUE"""),5.0) -> 5 | T7: =IFERROR(__xludf.DUMMYFUNCTION("""COMPUTED_VALUE"""),0.1) -> 0.1 | U7: =IFERROR(__xludf.DUMMYFUNCTION("""COMPUTED_VALUE"""),0.5) -> 0.5
B8: 46023 | C8: CONSUMIDOR FINAL | D8: galleta marilu chocolate | E8: {=IF(D8="","",XLOOKUP(D8,DATOS!$D$6:D14000,DATOS!$C$6:C14000,0,0,1))} -> 00017 | F8: 2 | G8: 0.5 | H8: =IF(F8="","",(F8*G8)) -> 1 | K8: =IF(I8="","",(F8*I8)) | L8: =IF(I8="",H8,H8+(K8/J8)) -> 1 | O8: =IFERROR(__xludf.DUMMYFUNCTION("""COMPUTED_VALUE"""),46024.0) -> 46024 | P8: =IFERROR(__xludf.DUMMYFUNCTION("""COMPUTED_VALUE"""),"CONSUMIDOR FINAL") -> CONSUMIDOR FINAL | Q8: =IFERROR(__xludf.DUMMYFUNCTION("""COMPUTED_VALUE"""),"Huevo") -> Huevo | R8: =IFERROR(__xludf.DUMMYFUNCTION("""COMPUTED_VALUE"""),"HUEVO") -> HUEVO | S8: =IFERROR(__xludf.DUMMYFUNCTION("""COMPUTED_VALUE"""),12.0) -> 12 | T8: =IFERROR(__xludf.DUMMYFUNCTION("""COMPUTED_VALUE"""),0.3333) -> 0.3333 | U8: =IFERROR(__xludf.DUMMYFUNCTION("""COMPUTED_VALUE"""),3.9996) -> 3.9996
B9: 46023 | C9: CONSUMIDOR FINAL | D9: Pollo 1kg | E9: {=IF(D9="","",XLOOKUP(D9,DATOS!$D$6:D14000,DATOS!$C$6:C14000,0,0,1))} -> POLLO | F9: 3.25 | G9: 5 | H9: =IF(F9="","",(F9*G9)) -> 16.25 | K9: =IF(I9="","",(F9*I9)) | L9: =IF(I9="",H9,H9+(K9/J9)) -> 16.25 | O9: =IFERROR(__xludf.DUMMYFUNCTION("""COMPUTED_VALUE"""),46024.0) -> 46024 | P9: =IFERROR(__xludf.DUMMYFUNCTION("""COMPUTED_VALUE"""),"CONSUMIDOR FINAL") -> CONSUMIDOR FINAL | Q9: =IFERROR(__xludf.DUMMYFUNCTION("""COMPUTED_VALUE"""),"GALLETA MARILU CHOCOVAINILLA") -> GALLETA MARILU CHOCOVAINILLA | R9: =IFERROR(__xludf.DUMMYFUNCTION("""COMPUTED_VALUE"""),"GALL024") -> GALL024 | S9: =IFERROR(__xludf.DUMMYFUNCTION("""COMPUTED_VALUE"""),2.0) -> 2 | T9: =IFERROR(__xludf.DUMMYFUNCTION("""COMPUTED_VALUE"""),0.5) -> 0.5 | U9: =IFERROR(__xludf.DUMMYFUNCTION("""COMPUTED_VALUE"""),1.0) -> 1
B10: 46023 | C10: CONSUMIDOR FINAL | D10: BIG BOG SABORES VARIADOS | E10: {=IF(D10="","",XLOOKUP(D10,DATOS!$D$6:D14000,DATOS!$C$6:C14000,0,0,1))} -> 00081 | F10: 2 | G10: 0.5 | H10: =IF(F10="","",(F10*G10)) -> 1 | K10: =IF(I10="","",(F10*I10)) | L10: =IF(I10="",H10,H10+(K10/J10)) -> 1 | O10: =IFERROR(__xludf.DUMMYFUNCTION("""COMPUTED_VALUE"""),46024.0) -> 46024 | P10: =IFERROR(__xludf.DUMMYFUNCTION("""COMPUTED_VALUE"""),"CONSUMIDOR FINAL") -> CONSUMIDOR FINAL | Q10: =IFERROR(__xludf.DUMMYFUNCTION("""COMPUTED_VALUE"""),"Huevo") -> Huevo | R10: =IFERROR(__xludf.DUMMYFUNCTION("""COMPUTED_VALUE"""),"HUEVO") -> HUEVO | S10: =IFERROR(__xludf.DUMMYFUNCTION("""COMPUTED_VALUE"""),6.0) -> 6 | T10: =IFERROR(__xludf.DUMMYFUNCTION("""COMPUTED_VALUE"""),0.333333) -> 0.333333 | U10: =IFERROR(__xludf.DUMMYFUNCTION("""COMPUTED_VALUE"""),1.999998) -> 1.999998
B11: 46023 | C11: CONSUMIDOR FINAL | D11: CARAMELOS FRUTICAS 100UND | E11: {=IF(D11="","",XLOOKUP(D11,DATOS!$D$6:D14000,DATOS!$C$6:C14000,0,0,1))} -> CARM005 | F11: 10 | G11: 0.1 | H11: =IF(F11="","",(F11*G11)) -> 1 | K11: =IF(I11="","",(F11*I11)) | L11: =IF(I11="",H11,H11+(K11/J11)) -> 1 | O11: =IFERROR(__xludf.DUMMYFUNCTION("""COMPUTED_VALUE"""),46024.0) -> 46024 | P11: =IFERROR(__xludf.DUMMYFUNCTION("""COMPUTED_VALUE"""),"CONSUMIDOR FINAL") -> CONSUMIDOR FINAL | Q11: =IFERROR(__xludf.DUMMYFUNCTION("""COMPUTED_VALUE"""),"Arroz Mary tradicional tipo 1 900g") -> Arroz Mary tradicional tipo 1 900g | R11: =IFERROR(__xludf.DUMMYFUNCTION("""COMPUTED_VALUE"""),"AR1") -> AR1 | S11: =IFERROR(__xludf.DUMMYFUNCTION("""COMPUTED_VALUE"""),1.0) -> 1 | T11: =IFERROR(__xludf.DUMMYFUNCTION("""COMPUTED_VALUE"""),2.5) -> 2.5 | U11: =IFERROR(__xludf.DUMMYFUNCTION("""COMPUTED_VALUE"""),2.5) -> 2.5
B12: 46023 | C12: CONSUMIDOR FINAL | D12: Caramelos Bianchi | E12: {=IF(D12="","",XLOOKUP(D12,DATOS!$D$6:D14000,DATOS!$C$6:C14000,0,0,1))} -> CARM2 | F12: 10 | G12: 0.1 | H12: =IF(F12="","",(F12*G12)) -> 1 | K12: =IF(I12="","",(F12*I12)) | L12: =IF(I12="",H12,H12+(K12/J12)) -> 1 | O12: =IFERROR(__xludf.DUMMYFUNCTION("""COMPUTED_VALUE"""),46024.0) -> 46024 | P12: =IFERROR(__xludf.DUMMYFUNCTION("""COMPUTED_VALUE"""),"CONSUMIDOR FINAL") -> CONSUMIDOR FINAL | Q12: =IFERROR(__xludf.DUMMYFUNCTION("""COMPUTED_VALUE"""),"Cubitos") -> Cubitos | R12: =IFERROR(__xludf.DUMMYFUNCTION("""COMPUTED_VALUE"""),"CUBITO1") -> CUBITO1 | S12: =IFERROR(__xludf.DUMMYFUNCTION("""COMPUTED_VALUE"""),3.0) -> 3 | T12: =IFERROR(__xludf.DUMMYFUNCTION("""COMPUTED_VALUE"""),0.5) -> 0.5 | U12: =IFERROR(__xludf.DUMMYFUNCTION("""COMPUTED_VALUE"""),1.5) -> 1.5
B13: 46023 | C13: CONSUMIDOR FINAL | D13: Caramelos Chao | E13: {=IF(D13="","",XLOOKUP(D13,DATOS!$D$6:D14000,DATOS!$C$6:C14000,0,0,1))} -> CARM4 | F13: 10 | G13: 0.1 | H13: =IF(F13="","",(F13*G13)) -> 1 | K13: =IF(I13="","",(F13*I13)) | L13: =IF(I13="",H13,H13+(K13/J13)) -> 1 | O13: =IFERROR(__xludf.DUMMYFUNCTION("""COMPUTED_VALUE"""),46024.0) -> 46024 | P13: =IFERROR(__xludf.DUMMYFUNCTION("""COMPUTED_VALUE"""),"CONSUMIDOR FINAL") -> CONSUMIDOR FINAL | Q13: =IFERROR(__xludf.DUMMYFUNCTION("""COMPUTED_VALUE"""),"PAPEL HIGIENICO MARRON ") -> PAPEL HIGIENICO MARRON | R13: =IFERROR(__xludf.DUMMYFUNCTION("""COMPUTED_VALUE"""),"00097") -> 00097 | S13: =IFERROR(__xludf.DUMMYFUNCTION("""COMPUTED_VALUE"""),1.0) -> 1 | T13: =IFERROR(__xludf.DUMMYFUNCTION("""COMPUTED_VALUE"""),2.0) -> 2 | U13: =IFERROR(__xludf.DUMMYFUNCTION("""COMPUTED_VALUE"""),2.0) -> 2
B14: 46023 | C14: CONSUMIDOR FINAL | D14: Belmont | E14: {=IF(D14="","",XLOOKUP(D14,DATOS!$D$6:D14000,DATOS!$C$6:C14000,0,0,1))} -> BELM | F14: 20 | G14: 0.25 | H14: =IF(F14="","",(F14*G14)) -> 5 | K14: =IF(I14="","",(F14*I14)) | L14: =IF(I14="",H14,H14+(K14/J14)) -> 5 | O14: =IFERROR(__xludf.DUMMYFUNCTION("""COMPUTED_VALUE"""),46024.0) -> 46024 | P14: =IFERROR(__xludf.DUMMYFUNCTION("""COMPUTED_VALUE"""),"CONSUMIDOR FINAL") -> CONSUMIDOR FINAL | Q14: =IFERROR(__xludf.DUMMYFUNCTION("""COMPUTED_VALUE"""),"Jabon las llaves floral (200gr)") -> Jabon las llaves floral (200gr) | R14: =IFERROR(__xludf.DUMMYFUNCTION("""COMPUTED_VALUE"""),"00029") -> 00029 | S14: =IFERROR(__xludf.DUMMYFUNCTION("""COMPUTED_VALUE"""),1.0) -> 1 | T14: =IFERROR(__xludf.DUMMYFUNCTION("""COMPUTED_VALUE"""),2.0) -> 2 | U14: =IFERROR(__xludf.DUMMYFUNCTION("""COMPUTED_VALUE"""),2.0) -> 2
B15: 46023 | C15: CONSUMIDOR FINAL | D15: CARAMELOS FRUTICAS 100UND | E15: {=IF(D15="","",XLOOKUP(D15,DATOS!$D$6:D14000,DATOS!$C$6:C14000,0,0,1))} -> CARM005 | F15: 10 | G15: 0.1 | H15: =IF(F15="","",(F15*G15)) -> 1 | K15: =IF(I15="","",(F15*I15)) | L15: =IF(I15="",H15,H15+(K15/J15)) -> 1 | O15: =IFERROR(__xludf.DUMMYFUNCTION("""COMPUTED_VALUE"""),46024.0) -> 46024 | P15: =IFERROR(__xludf.DUMMYFUNCTION("""COMPUTED_VALUE"""),"CONSUMIDOR FINAL") -> CONSUMIDOR FINAL | Q15: =IFERROR(__xludf.DUMMYFUNCTION("""COMPUTED_VALUE"""),"MARGARINA MAVESA 250GR") -> MARGARINA MAVESA 250GR | R15: =IFERROR(__xludf.DUMMYFUNCTION("""COMPUTED_VALUE"""),"MARG1") -> MARG1 | S15: =IFERROR(__xludf.DUMMYFUNCTION("""COMPUTED_VALUE"""),1.0) -> 1 | T15: =IFERROR(__xludf.DUMMYFUNCTION("""COMPUTED_VALUE"""),3.0) -> 3 | U15: =IFERROR(__xludf.DUMMYFUNCTION("""COMPUTED_VALUE"""),3.0) -> 3
B16: 46023 | C16: CONSUMIDOR FINAL | D16: Queso duro | E16: {=IF(D16="","",XLOOKUP(D16,DATOS!$D$6:D14000,DATOS!$C$6:C14000,0,0,1))} -> QUES1 | F16: 0.2 | G16: 10 | H16: =IF(F16="","",(F16*G16)) -> 2 | K16: =IF(I16="","",(F16*I16)) | L16: =IF(I16="",H16,H16+(K16/J16)) -> 2 | O16: =IFERROR(__xludf.DUMMYFUNCTION("""COMPUTED_VALUE"""),46024.0) -> 46024 | P16: =IFERROR(__xludf.DUMMYFUNCTION("""COMPUTED_VALUE"""),"CONSUMIDOR FINAL") -> CONSUMIDOR FINAL | Q16: =IFERROR(__xludf.DUMMYFUNCTION("""COMPUTED_VALUE"""),"Queso duro") -> Queso duro | R16: =IFERROR(__xludf.DUMMYFUNCTION("""COMPUTED_VALUE"""),"QUES1") -> QUES1 | S16: =IFERROR(__xludf.DUMMYFUNCTION("""COMPUTED_VALUE"""),0.2) -> 0.2 | T16: =IFERROR(__xludf.DUMMYFUNCTION("""COMPUTED_VALUE"""),10.0) -> 10 | U16: =IFERROR(__xludf.DUMMYFUNCTION("""COMPUTED_VALUE"""),2.0) -> 2
B17: 46023 | C17: CONSUMIDOR FINAL | D17: Pollo 1kg | E17: {=IF(D17="","",XLOOKUP(D17,DATOS!$D$6:D14000,DATOS!$C$6:C14000,0,0,1))} -> POLLO | F17: 2.75 | G17: 5 | H17: =IF(F17="","",(F17*G17)) -> 13.75 | K17: =IF(I17="","",(F17*I17)) | L17: =IF(I17="",H17,H17+(K17/J17)) -> 13.75 | O17: =IFERROR(__xludf.DUMMYFUNCTION("""COMPUTED_VALUE"""),46024.0) -> 46024 | P17: =IFERROR(__xludf.DUMMYFUNCTION("""COMPUTED_VALUE"""),"CONSUMIDOR FINAL") -> CONSUMIDOR FINAL | Q17: =IFERROR(__xludf.DUMMYFUNCTION("""COMPUTED_VALUE"""),"Huevo") -> Huevo | R17: =IFERROR(__xludf.DUMMYFUNCTION("""COMPUTED_VALUE"""),"HUEVO") -> HUEVO | S17: =IFERROR(__xludf.DUMMYFUNCTION("""COMPUTED_VALUE"""),6.0) -> 6 | T17: =IFERROR(__xludf.DUMMYFUNCTION("""COMPUTED_VALUE"""),0.3333) -> 0.3333 | U17: =IFERROR(__xludf.DUMMYFUNCTION("""COMPUTED_VALUE"""),1.9998) -> 1.9998
B18: 46023 | C18: CONSUMIDOR FINAL | D18: ATUN PEÑERO OLIVA VERDE | E18: {=IF(D18="","",XLOOKUP(D18,DATOS!$D$6:D14000,DATOS!$C$6:C14000,0,0,1))} -> 00116 | F18: 1 | G18: 3.5 | H18: =IF(F18="","",(F18*G18)) -> 3.5 | K18: =IF(I18="","",(F18*I18)) | L18: =IF(I18="",H18,H18+(K18/J18)) -> 3.5 | O18: =IFERROR(__xludf.DUMMYFUNCTION("""COMPUTED_VALUE"""),46024.0) -> 46024 | P18: =IFERROR(__xludf.DUMMYFUNCTION("""COMPUTED_VALUE"""),"CONSUMIDOR FINAL") -> CONSUMIDOR FINAL | Q18: =IFERROR(__xludf.DUMMYFUNCTION("""COMPUTED_VALUE"""),"GALLETA MARILU CHOCOVAINILLA") -> GALLETA MARILU CHOCOVAINILLA | R18: =IFERROR(__xludf.DUMMYFUNCTION("""COMPUTED_VALUE"""),"GALL024") -> GALL024 | S18: =IFERROR(__xludf.DUMMYFUNCTION("""COMPUTED_VALUE"""),2.0) -> 2 | T18: =IFERROR(__xludf.DUMMYFUNCTION("""COMPUTED_VALUE"""),0.5) -> 0.5 | U18: =IFERROR(__xludf.DUMMYFUNCTION("""COMPUTED_VALUE"""),1.0) -> 1
B19: 46023 | C19: CONSUMIDOR FINAL | D19: CARAMELOS FRUTICAS 100UND | E19: {=IF(D19="","",XLOOKUP(D19,DATOS!$D$6:D14000,DATOS!$C$6:C14000,0,0,1))} -> CARM005 | F19: 5 | G19: 0.1 | H19: =IF(F19="","",(F19*G19)) -> 0.5 | K19: =IF(I19="","",(F19*I19)) | L19: =IF(I19="",H19,H19+(K19/J19)) -> 0.5 | O19: =IFERROR(__xludf.DUMMYFUNCTION("""COMPUTED_VALUE"""),46024.0) -> 46024 | P19: =IFERROR(__xludf.DUMMYFUNCTION("""COMPUTED_VALUE"""),"CONSUMIDOR FINAL") -> CONSUMIDOR FINAL | Q19: =IFERROR(__xludf.DUMMYFUNCTION("""COMPUTED_VALUE"""),"Huevo") -> Huevo | R19: =IFERROR(__xludf.DUMMYFUNCTION("""COMPUTED_VALUE"""),"HUEVO") -> HUEVO | S19: =IFERROR(__xludf.DUMMYFUNCTION("""COMPUTED_VALUE"""),18.0) -> 18 | T19: =IFERROR(__xludf.DUMMYFUNCTION("""COMPUTED_VALUE"""),0.33333) -> 0.33333 | U19: =IFERROR(__xludf.DUMMYFUNCTION("""COMPUTED_VALUE"""),5.9999400000000005) -> 5.99994
B20: 46023 | C20: CONSUMIDOR FINAL | D20: Huevo | E20: {=IF(D20="","",XLOOKUP(D20,DATOS!$D$6:D14000,DATOS!$C$6:C14000,0,0,1))} -> HUEVO | F20: 3 | G20: 0.3333 | H20: =IF(F20="","",(F20*G20)) -> 0.9999 | K20: =IF(I20="","",(F20*I20)) | L20: =IF(I20="",H20,H20+(K20/J20)) -> 0.9999 | O20: =IFERROR(__xludf.DUMMYFUNCTION("""COMPUTED_VALUE"""),46024.0) -> 46024 | P20: =IFERROR(__xludf.DUMMYFUNCTION("""COMPUTED_VALUE"""),"CONSUMIDOR FINAL") -> CONSUMIDOR FINAL | Q20: =IFERROR(__xludf.DUMMYFUNCTION("""COMPUTED_VALUE"""),"Queso duro") -> Queso duro | R20: =IFERROR(__xludf.DUMMYFUNCTION("""COMPUTED_VALUE"""),"QUES1") -> QUES1 | S20: =IFERROR(__xludf.DUMMYFUNCTION("""COMPUTED_VALUE"""),0.25) -> 0.25 | T20: =IFERROR(__xludf.DUMMYFUNCTION("""COMPUTED_VALUE"""),10.0) -> 10 | U20: =IFERROR(__xludf.DUMMYFUNCTION("""COMPUTED_VALUE"""),2.5) -> 2.5
B21: 46023 | C21: CONSUMIDOR FINAL | D21: Panelada 29gr | E21: {=IF(D21="","",XLOOKUP(D21,DATOS!$D$6:D14000,DATOS!$C$6:C14000,0,0,1))} -> PANEL | F21: 1 | G21: 1 | H21: =IF(F21="","",(F21*G21)) -> 1 | K21: =IF(I21="","",(F21*I21)) | L21: =IF(I21="",H21,H21+(K21/J21)) -> 1 | O21: =IFERROR(__xludf.DUMMYFUNCTION("""COMPUTED_VALUE"""),46024.0) -> 46024 | P21: =IFERROR(__xludf.DUMMYFUNCTION("""COMPUTED_VALUE"""),"CONSUMIDOR FINAL") -> CONSUMIDOR FINAL | Q21: =IFERROR(__xludf.DUMMYFUNCTION("""COMPUTED_VALUE"""),"BIG BOG SABORES VARIADOS") -> BIG BOG SABORES VARIADOS | R21: =IFERROR(__xludf.DUMMYFUNCTION("""COMPUTED_VALUE"""),"00081") -> 00081 | S21: =IFERROR(__xludf.DUMMYFUNCTION("""COMPUTED_VALUE"""),1.0) -> 1 | T21: =IFERROR(__xludf.DUMMYFUNCTION("""COMPUTED_VALUE"""),0.5) -> 0.5 | U21: =IFERROR(__xludf.DUMMYFUNCTION("""COMPUTED_VALUE"""),0.5) -> 0.5
B22: 46023 | C22: CONSUMIDOR FINAL | D22: Refrescos 2lt | E22: {=IF(D22="","",XLOOKUP(D22,DATOS!$D$6:D14000,DATOS!$C$6:C14000,0,0,1))} -> REF4 | F22: 1 | G22: 6 | H22: =IF(F22="","",(F22*G22)) -> 6 | K22: =IF(I22="","",(F22*I22)) | L22: =IF(I22="",H22,H22+(K22/J22)) -> 6 | O22: =IFERROR(__xludf.DUMMYFUNCTION("""COMPUTED_VALUE"""),46024.0) -> 46024 | P22: =IFERROR(__xludf.DUMMYFUNCTION("""COMPUTED_VALUE"""),"CONSUMIDOR FINAL") -> CONSUMIDOR FINAL | Q22: =IFERROR(__xludf.DUMMYFUNCTION("""COMPUTED_VALUE"""),"Huevo") -> Huevo | R22: =IFERROR(__xludf.DUMMYFUNCTION("""COMPUTED_VALUE"""),"HUEVO") -> HUEVO | S22: =IFERROR(__xludf.DUMMYFUNCTION("""COMPUTED_VALUE"""),9.0) -> 9 | T22: =IFERROR(__xludf.DUMMYFUNCTION("""COMPUTED_VALUE"""),0.33333333) -> 0.33333333 | U22: =IFERROR(__xludf.DUMMYFUNCTION("""COMPUTED_VALUE"""),2.9999999699999997) -> 3
B23: 46023 | C23: CONSUMIDOR FINAL | D23: caramelo trululu aros 100UND | E23: {=IF(D23="","",XLOOKUP(D23,DATOS!$D$6:D14000,DATOS!$C$6:C14000,0,0,1))} -> 00010 | F23: 10 | G23: 0.1 | H23: =IF(F23="","",(F23*G23)) -> 1 | K23: =IF(I23="","",(F23*I23)) | L23: =IF(I23="",H23,H23+(K23/J23)) -> 1 | O23: =IFERROR(__xludf.DUMMYFUNCTION("""COMPUTED_VALUE"""),46024.0) -> 46024 | P23: =IFERROR(__xludf.DUMMYFUNCTION("""COMPUTED_VALUE"""),"CONSUMIDOR FINAL") -> CONSUMIDOR FINAL | Q23: =IFERROR(__xludf.DUMMYFUNCTION("""COMPUTED_VALUE"""),"BIG BOG SABORES VARIADOS") -> BIG BOG SABORES VARIADOS | R23: =IFERROR(__xludf.DUMMYFUNCTION("""COMPUTED_VALUE"""),"00081") -> 00081 | S23: =IFERROR(__xludf.DUMMYFUNCTION("""COMPUTED_VALUE"""),2.0) -> 2 | T23: =IFERROR(__xludf.DUMMYFUNCTION("""COMPUTED_VALUE"""),0.5) -> 0.5 | U23: =IFERROR(__xludf.DUMMYFUNCTION("""COMPUTED_VALUE"""),1.0) -> 1
B24: 46023 | C24: CONSUMIDOR FINAL | D24: PAPEL HIGIENICO MARRON | E24: {=IF(D24="","",XLOOKUP(D24,DATOS!$D$6:D14000,DATOS!$C$6:C14000,0,0,1))} -> 00097 | F24: 2 | G24: 2 | H24: =IF(F24="","",(F24*G24)) -> 4 | K24: =IF(I24="","",(F24*I24)) | L24: =IF(I24="",H24,H24+(K24/J24)) -> 4 | O24: =IFERROR(__xludf.DUMMYFUNCTION("""COMPUTED_VALUE"""),46024.0) -> 46024 | P24: =IFERROR(__xludf.DUMMYFUNCTION("""COMPUTED_VALUE"""),"CONSUMIDOR FINAL") -> CONSUMIDOR FINAL | Q24: =IFERROR(__xludf.DUMMYFUNCTION("""COMPUTED_VALUE"""),"Queso duro") -> Queso duro | R24: =IFERROR(__xludf.DUMMYFUNCTION("""COMPUTED_VALUE"""),"QUES1") -> QUES1 | S24: =IFERROR(__xludf.DUMMYFUNCTION("""COMPUTED_VALUE"""),0.2) -> 0.2 | T24: =IFERROR(__xludf.DUMMYFUNCTION("""COMPUTED_VALUE"""),10.0) -> 10 | U24: =IFERROR(__xludf.DUMMYFUNCTION("""COMPUTED_VALUE"""),2.0) -> 2
B25: 46023 | C25: CONSUMIDOR FINAL | D25: galleta marilu chocolate | E25: {=IF(D25="","",XLOOKUP(D25,DATOS!$D$6:D14000,DATOS!$C$6:C14000,0,0,1))} -> 00017 | F25: 2 | G25: 0.5 | H25: =IF(F25="","",(F25*G25)) -> 1 | K25: =IF(I25="","",(F25*I25)) | L25: =IF(I25="",H25,H25+(K25/J25)) -> 1 | O25: =IFERROR(__xludf.DUMMYFUNCTION("""COMPUTED_VALUE"""),46024.0) -> 46024 | P25: =IFERROR(__xludf.DUMMYFUNCTION("""COMPUTED_VALUE"""),"CONSUMIDOR FINAL") -> CONSUMIDOR FINAL | Q25: =IFERROR(__xludf.DUMMYFUNCTION("""COMPUTED_VALUE"""),"MARGARINA MAVESA 500GR") -> MARGARINA MAVESA 500GR | R25: =IFERROR(__xludf.DUMMYFUNCTION("""COMPUTED_VALUE"""),"MARG2") -> MARG2 | S25: =IFERROR(__xludf.DUMMYFUNCTION("""COMPUTED_VALUE"""),1.0) -> 1 | T25: =IFERROR(__xludf.DUMMYFUNCTION("""COMPUTED_VALUE"""),4.0) -> 4 | U25: =IFERROR(__xludf.DUMMYFUNCTION("""COMPUTED_VALUE"""),4.0) -> 4
B26: 46023 | C26: CONSUMIDOR FINAL | D26: Caramelos Bianchi | E26: {=IF(D26="","",XLOOKUP(D26,DATOS!$D$6:D14000,DATOS!$C$6:C14000,0,0,1))} -> CARM2 | F26: 10 | G26: 0.1 | H26: =IF(F26="","",(F26*G26)) -> 1 | K26: =IF(I26="","",(F26*I26)) | L26: =IF(I26="",H26,H26+(K26/J26)) -> 1 | O26: =IFERROR(__xludf.DUMMYFUNCTION("""COMPUTED_VALUE"""),46024.0) -> 46024 | P26: =IFERROR(__xludf.DUMMYFUNCTION("""COMPUTED_VALUE"""),"CONSUMIDOR FINAL") -> CONSUMIDOR FINAL | Q26: =IFERROR(__xludf.DUMMYFUNCTION("""COMPUTED_VALUE"""),"Panelada 29gr") -> Panelada 29gr | R26: =IFERROR(__xludf.DUMMYFUNCTION("""COMPUTED_VALUE"""),"PANEL") -> PANEL | S26: =IFERROR(__xludf.DUMMYFUNCTION("""COMPUTED_VALUE"""),2.0) -> 2 | T26: =IFERROR(__xludf.DUMMYFUNCTION("""COMPUTED_VALUE"""),1.0) -> 1 | U26: =IFERROR(__xludf.DUMMYFUNCTION("""COMPUTED_VALUE"""),2.0) -> 2
B27: 46023 | C27: CONSUMIDOR FINAL | D27: FLIPS 28G | E27: {=IF(D27="","",XLOOKUP(D27,DATOS!$D$6:D14000,DATOS!$C$6:C14000,0,0,1))} -> FLIP | F27: 2 | G27: 1 | H27: =IF(F27="","",(F27*G27)) -> 2 | K27: =IF(I27="","",(F27*I27)) | L27: =IF(I27="",H27,H27+(K27/J27)) -> 2 | O27: =IFERROR(__xludf.DUMMYFUNCTION("""COMPUTED_VALUE"""),46024.0) -> 46024 | P27: =IFERROR(__xludf.DUMMYFUNCTION("""COMPUTED_VALUE"""),"CONSUMIDOR FINAL") -> CONSUMIDOR FINAL | Q27: =IFERROR(__xludf.DUMMYFUNCTION("""COMPUTED_VALUE"""),"galleta marilu chocolate") -> galleta marilu chocolate | R27: =IFERROR(__xludf.DUMMYFUNCTION("""COMPUTED_VALUE"""),"00017") -> 00017 | S27: =IFERROR(__xludf.DUMMYFUNCTION("""COMPUTED_VALUE"""),2.0) -> 2 | T27: =IFERROR(__xludf.DUMMYFUNCTION("""COMPUTED_VALUE"""),0.5) -> 0.5 | U27: =IFERROR(__xludf.DUMMYFUNCTION("""COMPUTED_VALUE"""),1.0) -> 1
B28: 46023 | C28: CONSUMIDOR FINAL | D28: Caramelos Bianchi | E28: {=IF(D28="","",XLOOKUP(D28,DATOS!$D$6:D14000,DATOS!$C$6:C14000,0,0,1))} -> CARM2 | F28: 10 | G28: 0.1 | H28: =IF(F28="","",(F28*G28)) -> 1 | K28: =IF(I28="","",(F28*I28)) | L28: =IF(I28="",H28,H28+(K28/J28)) -> 1 | O28: =IFERROR(__xludf.DUMMYFUNCTION("""COMPUTED_VALUE"""),46024.0) -> 46024 | P28: =IFERROR(__xludf.DUMMYFUNCTION("""COMPUTED_VALUE"""),"CONSUMIDOR FINAL") -> CONSUMIDOR FINAL | Q28: =IFERROR(__xludf.DUMMYFUNCTION("""COMPUTED_VALUE"""),"PAÑALES TALLA G BABY FINGER 18UND") -> PAÑALES TALLA G BABY FINGER 18UND | R28: =IFERROR(__xludf.DUMMYFUNCTION("""COMPUTED_VALUE"""),"00082") -> 00082 | S28: =IFERROR(__xludf.DUMMYFUNCTION("""COMPUTED_VALUE"""),2.0) -> 2 | T28: =IFERROR(__xludf.DUMMYFUNCTION("""COMPUTED_VALUE"""),0.5) -> 0.5 | U28: =IFERROR(__xludf.DUMMYFUNCTION("""COMPUTED_VALUE"""),1.0) -> 1
B29: 46023 | C29: CONSUMIDOR FINAL | D29: CHOCOLATE BIANCHI DOBLE CHOCOLATE | E29: {=IF(D29="","",XLOOKUP(D29,DATOS!$D$6:D14000,DATOS!$C$6:C14000,0,0,1))} -> 00087 | F29: 2 | G29: 1 | H29: =IF(F29="","",(F29*G29)) -> 2 | K29: =IF(I29="","",(F29*I29)) | L29: =IF(I29="",H29,H29+(K29/J29)) -> 2 | O29: =IFERROR(__xludf.DUMMYFUNCTION("""COMPUTED_VALUE"""),46024.0) -> 46024 | P29: =IFERROR(__xludf.DUMMYFUNCTION("""COMPUTED_VALUE"""),"CONSUMIDOR FINAL") -> CONSUMIDOR FINAL | Q29: =IFERROR(__xludf.DUMMYFUNCTION("""COMPUTED_VALUE"""),"Refrescos 2lt ") -> Refrescos 2lt | R29: =IFERROR(__xludf.DUMMYFUNCTION("""COMPUTED_VALUE"""),"REF4") -> REF4 | S29: =IFERROR(__xludf.DUMMYFUNCTION("""COMPUTED_VALUE"""),1.0) -> 1 | T29: =IFERROR(__xludf.DUMMYFUNCTION("""COMPUTED_VALUE"""),6.0) -> 6 | U29: =IFERROR(__xludf.DUMMYFUNCTION("""COMPUTED_VALUE"""),6.0) -> 6
B30: 46023 | C30: CONSUMIDOR FINAL | D30: PIAZZA BARQUILLAS | E30: {=IF(D30="","",XLOOKUP(D30,DATOS!$D$6:D14000,DATOS!$C$6:C14000,0,0,1))} -> PIAZ | F30: 2 | G30: 0.5 | H30: =IF(F30="","",(F30*G30)) -> 1 | K30: =IF(I30="","",(F30*I30)) | L30: =IF(I30="",H30,H30+(K30/J30)) -> 1 | O30: =IFERROR(__xludf.DUMMYFUNCTION("""COMPUTED_VALUE"""),46024.0) -> 46024 | P30: =IFERROR(__xludf.DUMMYFUNCTION("""COMPUTED_VALUE"""),"CONSUMIDOR FINAL") -> CONSUMIDOR FINAL | Q30: =IFERROR(__xludf.DUMMYFUNCTION("""COMPUTED_VALUE"""),"Jabon las llaves floral (200gr)") -> Jabon las llaves floral (200gr) | R30: =IFERROR(__xludf.DUMMYFUNCTION("""COMPUTED_VALUE"""),"00029") -> 00029 | S30: =IFERROR(__xludf.DUMMYFUNCTION("""COMPUTED_VALUE"""),2.0) -> 2 | T30: =IFERROR(__xludf.DUMMYFUNCTION("""COMPUTED_VALUE"""),2.0) -> 2 | U30: =IFERROR(__xludf.DUMMYFUNCTION("""COMPUTED_VALUE"""),4.0) -> 4
B31: 46023 | C31: CONSUMIDOR FINAL | D31: GALLETA MARILU CHOCOVAINILLA | E31: {=IF(D31="","",XLOOKUP(D31,DATOS!$D$6:D14000,DATOS!$C$6:C14000,0,0,1))} -> GALL024 | F31: 2 | G31: 0.5 | H31: =IF(F31="","",(F31*G31)) -> 1 | K31: =IF(I31="","",(F31*I31)) | L31: =IF(I31="",H31,H31+(K31/J31)) -> 1 | O31: =IFERROR(__xludf.DUMMYFUNCTION("""COMPUTED_VALUE"""),46024.0) -> 46024 | P31: =IFERROR(__xludf.DUMMYFUNCTION("""COMPUTED_VALUE"""),"CONSUMIDOR FINAL") -> CONSUMIDOR FINAL | Q31: =IFERROR(__xludf.DUMMYFUNCTION("""COMPUTED_VALUE"""),"ACEITE LA PAMPA 700ML ") -> ACEITE LA PAMPA 700ML | R31: =IFERROR(__xludf.DUMMYFUNCTION("""COMPUTED_VALUE"""),"00084") -> 00084 | S31: =IFERROR(__xludf.DUMMYFUNCTION("""COMPUTED_VALUE"""),1.0) -> 1 | T31: =IFERROR(__xludf.DUMMYFUNCTION("""COMPUTED_VALUE"""),4.0) -> 4 | U31: =IFERROR(__xludf.DUMMYFUNCTION("""COMPUTED_VALUE"""),4.0) -> 4
B32: 46023 | C32: CONSUMIDOR FINAL | D32: Pollo 1kg | E32: {=IF(D32="","",XLOOKUP(D32,DATOS!$D$6:D14000,DATOS!$C$6:C14000,0,0,1))} -> POLLO | F32: 3.05 | G32: 5 | H32: =IF(F32="","",(F32*G32)) -> 15.25 | K32: =IF(I32="","",(F32*I32)) | L32: =IF(I32="",H32,H32+(K32/J32)) -> 15.25 | O32: =IFERROR(__xludf.DUMMYFUNCTION("""COMPUTED_VALUE"""),46024.0) -> 46024 | P32: =IFERROR(__xludf.DUMMYFUNCTION("""COMPUTED_VALUE"""),"CONSUMIDOR FINAL") -> CONSUMIDOR FINAL | Q32: =IFERROR(__xludf.DUMMYFUNCTION("""COMPUTED_VALUE"""),"Jabon Popular") -> Jabon Popular | R32: =IFERROR(__xludf.DUMMYFUNCTION("""COMPUTED_VALUE"""),"JAB7") -> JAB7 | S32: =IFERROR(__xludf.DUMMYFUNCTION("""COMPUTED_VALUE"""),1.0) -> 1 | T32: =IFERROR(__xludf.DUMMYFUNCTION("""COMPUTED_VALUE"""),1.5) -> 1.5 | U32: =IFERROR(__xludf.DUMMYFUNCTION("""COMPUTED_VALUE"""),1.5) -> 1.5
B33: 46023 | C33: CONSUMIDOR FINAL | D33: ATUN PEÑERO OLIVA VERDE | E33: {=IF(D33="","",XLOOKUP(D33,DATOS!$D$6:D14000,DATOS!$C$6:C14000,0,0,1))} -> 00116 | F33: 1 | G33: 3.5 | H33: =IF(F33="","",(F33*G33)) -> 3.5 | K33: =IF(I33="","",(F33*I33)) | L33: =IF(I33="",H33,H33+(K33/J33)) -> 3.5 | O33: =IFERROR(__xludf.DUMMYFUNCTION("""COMPUTED_VALUE"""),46024.0) -> 46024 | P33: =IFERROR(__xludf.DUMMYFUNCTION("""COMPUTED_VALUE"""),"CONSUMIDOR FINAL") -> CONSUMIDOR FINAL | Q33: =IFERROR(__xludf.DUMMYFUNCTION("""COMPUTED_VALUE"""),"Galletas Maria") -> Galletas Maria | R33: =IFERROR(__xludf.DUMMYFUNCTION("""COMPUTED_VALUE"""),"GALL22") -> GALL22 | S33: =IFERROR(__xludf.DUMMYFUNCTION("""COMPUTED_VALUE"""),1.0) -> 1 | T33: =IFERROR(__xludf.DUMMYFUNCTION("""COMPUTED_VALUE"""),0.5) -> 0.5 | U33: =IFERROR(__xludf.DUMMYFUNCTION("""COMPUTED_VALUE"""),0.5) -> 0.5
B34: 46023 | C34: CONSUMIDOR FINAL | D34: galleta marilu chocolate | E34: {=IF(D34="","",XLOOKUP(D34,DATOS!$D$6:D14000,DATOS!$C$6:C14000,0,0,1))} -> 00017 | F34: 1 | G34: 0.5 | H34: =IF(F34="","",(F34*G34)) -> 0.5 | K34: =IF(I34="","",(F34*I34)) | L34: =IF(I34="",H34,H34+(K34/J34)) -> 0.5 | O34: =IFERROR(__xludf.DUMMYFUNCTION("""COMPUTED_VALUE"""),46024.0) -> 46024 | P34: =IFERROR(__xludf.DUMMYFUNCTION("""COMPUTED_VALUE"""),"CONSUMIDOR FINAL") -> CONSUMIDOR FINAL | Q34: =IFERROR(__xludf.DUMMYFUNCTION("""COMPUTED_VALUE"""),"Huevo") -> Huevo | R34: =IFERROR(__xludf.DUMMYFUNCTION("""COMPUTED_VALUE"""),"HUEVO") -> HUEVO | S34: =IFERROR(__xludf.DUMMYFUNCTION("""COMPUTED_VALUE"""),9.0) -> 9 | T34: =IFERROR(__xludf.DUMMYFUNCTION("""COMPUTED_VALUE"""),0.33333) -> 0.33333 | U34: =IFERROR(__xludf.DUMMYFUNCTION("""COMPUTED_VALUE"""),2.9999700000000002) -> 2.99997
B35: 46023 | C35: CONSUMIDOR FINAL | D35: Belmont | E35: {=IF(D35="","",XLOOKUP(D35,DATOS!$D$6:D14000,DATOS!$C$6:C14000,0,0,1))} -> BELM | F35: 40 | G35: 0.25 | H35: =IF(F35="","",(F35*G35)) -> 10 | K35: =IF(I35="","",(F35*I35)) | L35: =IF(I35="",H35,H35+(K35/J35)) -> 10 | O35: =IFERROR(__xludf.DUMMYFUNCTION("""COMPUTED_VALUE"""),46024.0) -> 46024 | P35: =IFERROR(__xludf.DUMMYFUNCTION("""COMPUTED_VALUE"""),"CONSUMIDOR FINAL") -> CONSUMIDOR FINAL | Q35: =IFERROR(__xludf.DUMMYFUNCTION("""COMPUTED_VALUE"""),"TORONTO") -> TORONTO | R35: =IFERROR(__xludf.DUMMYFUNCTION("""COMPUTED_VALUE"""),"TORON") -> TORON | S35: =IFERROR(__xludf.DUMMYFUNCTION("""COMPUTED_VALUE"""),1.0) -> 1 | T35: =IFERROR(__xludf.DUMMYFUNCTION("""COMPUTED_VALUE"""),1.0) -> 1 | U35: =IFERROR(__xludf.DUMMYFUNCTION("""COMPUTED_VALUE"""),1.0) -> 1
B36: 46023 | C36: CONSUMIDOR FINAL | D36: Pollo 1kg | E36: {=IF(D36="","",XLOOKUP(D36,DATOS!$D$6:D14000,DATOS!$C$6:C14000,0,0,1))} -> POLLO | F36: 2.45 | G36: 5 | H36: =IF(F36="","",(F36*G36)) -> 12.25 | K36: =IF(I36="","",(F36*I36)) | L36: =IF(I36="",H36,H36+(K36/J36)) -> 12.25 | O36: =IFERROR(__xludf.DUMMYFUNCTION("""COMPUTED_VALUE"""),46024.0) -> 46024 | P36: =IFERROR(__xludf.DUMMYFUNCTION("""COMPUTED_VALUE"""),"CONSUMIDOR FINAL") -> CONSUMIDOR FINAL | Q36: =IFERROR(__xludf.DUMMYFUNCTION("""COMPUTED_VALUE"""),"Refrescos 1,5lt") -> Refrescos 1,5lt | R36: =IFERROR(__xludf.DUMMYFUNCTION("""COMPUTED_VALUE"""),"REF2") -> REF2 | S36: =IFERROR(__xludf.DUMMYFUNCTION("""COMPUTED_VALUE"""),1.0) -> 1 | T36: =IFERROR(__xludf.DUMMYFUNCTION("""COMPUTED_VALUE"""),4.0) -> 4 | U36: =IFERROR(__xludf.DUMMYFUNCTION("""COMPUTED_VALUE"""),4.0) -> 4
B37: 46023 | C37: CONSUMIDOR FINAL | D37: GALLETA MARILU 18 G | E37: {=IF(D37="","",XLOOKUP(D37,DATOS!$D$6:D14000,DATOS!$C$6:C14000,0,0,1))} -> 00049 | F37: 4 | G37: 0.25 | H37: =IF(F37="","",(F37*G37)) -> 1 | K37: =IF(I37="","",(F37*I37)) | L37: =IF(I37="",H37,H37+(K37/J37)) -> 1 | O37: =IFERROR(__xludf.DUMMYFUNCTION("""COMPUTED_VALUE"""),46024.0) -> 46024 | P37: =IFERROR(__xludf.DUMMYFUNCTION("""COMPUTED_VALUE"""),"CONSUMIDOR FINAL") -> CONSUMIDOR FINAL | Q37: =IFERROR(__xludf.DUMMYFUNCTION("""COMPUTED_VALUE"""),"Cubitos") -> Cubitos | R37: =IFERROR(__xludf.DUMMYFUNCTION("""COMPUTED_VALUE"""),"CUBITO1") -> CUBITO1 | S37: =IFERROR(__xludf.DUMMYFUNCTION("""COMPUTED_VALUE"""),2.0) -> 2 | T37: =IFERROR(__xludf.DUMMYFUNCTION("""COMPUTED_VALUE"""),0.5) -> 0.5 | U37: =IFERROR(__xludf.DUMMYFUNCTION("""COMPUTED_VALUE"""),1.0) -> 1
B38: 46023 | C38: CONSUMIDOR FINAL | D38: Huevo | E38: {=IF(D38="","",XLOOKUP(D38,DATOS!$D$6:D14000,DATOS!$C$6:C14000,0,0,1))} -> HUEVO | F38: 6 | G38: 0.333333 | H38: =IF(F38="","",(F38*G38)) -> 1.999998 | K38: =IF(I38="","",(F38*I38)) | L38: =IF(I38="",H38,H38+(K38/J38)) -> 1.999998 | O38: =IFERROR(__xludf.DUMMYFUNCTION("""COMPUTED_VALUE"""),46024.0) -> 46024 | P38: =IFERROR(__xludf.DUMMYFUNCTION("""COMPUTED_VALUE"""),"CONSUMIDOR FINAL") -> CONSUMIDOR FINAL | Q38: =IFERROR(__xludf.DUMMYFUNCTION("""COMPUTED_VALUE"""),"CARAMELOS FRUTICAS 100UND") -> CARAMELOS FRUTICAS 100UND | R38: =IFERROR(__xludf.DUMMYFUNCTION("""COMPUTED_VALUE"""),"CARM005") -> CARM005 | S38: =IFERROR(__xludf.DUMMYFUNCTION("""COMPUTED_VALUE"""),10.0) -> 10 | T38: =IFERROR(__xludf.DUMMYFUNCTION("""COMPUTED_VALUE"""),0.1) -> 0.1 | U38: =IFERROR(__xludf.DUMMYFUNCTION("""COMPUTED_VALUE"""),1.0) -> 1
B39: 46023 | C39: CONSUMIDOR FINAL | D39: Galletas club social | E39: {=IF(D39="","",XLOOKUP(D39,DATOS!$D$6:D14000,DATOS!$C$6:C14000,0,0,1))} -> GALL20 | F39: 12 | G39: 0.5 | H39: =IF(F39="","",(F39*G39)) -> 6 | K39: =IF(I39="","",(F39*I39)) | L39: =IF(I39="",H39,H39+(K39/J39)) -> 6 | O39: =IFERROR(__xludf.DUMMYFUNCTION("""COMPUTED_VALUE"""),46024.0) -> 46024 | P39: =IFERROR(__xludf.DUMMYFUNCTION("""COMPUTED_VALUE"""),"CONSUMIDOR FINAL") -> CONSUMIDOR FINAL | Q39: =IFERROR(__xludf.DUMMYFUNCTION("""COMPUTED_VALUE"""),"Pañal Baby finger XG") -> Pañal Baby finger XG | R39: =IFERROR(__xludf.DUMMYFUNCTION("""COMPUTED_VALUE"""),"PAÑL1") -> PAÑL1 | S39: =IFERROR(__xludf.DUMMYFUNCTION("""COMPUTED_VALUE"""),2.0) -> 2 | T39: =IFERROR(__xludf.DUMMYFUNCTION("""COMPUTED_VALUE"""),0.5) -> 0.5 | U39: =IFERROR(__xludf.DUMMYFUNCTION("""COMPUTED_VALUE"""),1.0) -> 1
B40: 46023 | C40: CONSUMIDOR FINAL | D40: DIABLITO 54G | E40: {=IF(D40="","",XLOOKUP(D40,DATOS!$D$6:D14000,DATOS!$C$6:C14000,0,0,1))} -> DIABLI | F40: 2 | G40: 2 | H40: =IF(F40="","",(F40*G40)) -> 4 | K40: =IF(I40="","",(F40*I40)) | L40: =IF(I40="",H40,H40+(K40/J40)) -> 4 | O40: =IFERROR(__xludf.DUMMYFUNCTION("""COMPUTED_VALUE"""),46024.0) -> 46024 | P40: =IFERROR(__xludf.DUMMYFUNCTION("""COMPUTED_VALUE"""),"CONSUMIDOR FINAL") -> CONSUMIDOR FINAL | Q40: =IFERROR(__xludf.DUMMYFUNCTION("""COMPUTED_VALUE"""),"Refrescos 2lt ") -> Refrescos 2lt | R40: =IFERROR(__xludf.DUMMYFUNCTION("""COMPUTED_VALUE"""),"REF4") -> REF4 | S40: =IFERROR(__xludf.DUMMYFUNCTION("""COMPUTED_VALUE"""),1.0) -> 1 | T40: =IFERROR(__xludf.DUMMYFUNCTION("""COMPUTED_VALUE"""),6.0) -> 6 | U40: =IFERROR(__xludf.DUMMYFUNCTION("""COMPUTED_VALUE"""),6.0) -> 6
B41: 46023 | C41: CONSUMIDOR FINAL | D41: Refrescos 2lt | E41: {=IF(D41="","",XLOOKUP(D41,DATOS!$D$6:D14000,DATOS!$C$6:C14000,0,0,1))} -> REF4 | F41: 1 | G41: 6 | H41: =IF(F41="","",(F41*G41)) -> 6 | K41: =IF(I41="","",(F41*I41)) | L41: =IF(I41="",H41,H41+(K41/J41)) -> 6 | O41: =IFERROR(__xludf.DUMMYFUNCTION("""COMPUTED_VALUE"""),46024.0) -> 46024 | P41: =IFERROR(__xludf.DUMMYFUNCTION("""COMPUTED_VALUE"""),"CONSUMIDOR FINAL") -> CONSUMIDOR FINAL | Q41: =IFERROR(__xludf.DUMMYFUNCTION("""COMPUTED_VALUE"""),"Refrescos 1,5lt") -> Refrescos 1,5lt | R41: =IFERROR(__xludf.DUMMYFUNCTION("""COMPUTED_VALUE"""),"REF2") -> REF2 | S41: =IFERROR(__xludf.DUMMYFUNCTION("""COMPUTED_VALUE"""),1.0) -> 1 | T41: =IFERROR(__xludf.DUMMYFUNCTION("""COMPUTED_VALUE"""),4.0) -> 4 | U41: =IFERROR(__xludf.DUMMYFUNCTION("""COMPUTED_VALUE"""),4.0) -> 4
B42: 46023 | C42: CONSUMIDOR FINAL | D42: Panelada 29gr | E42: {=IF(D42="","",XLOOKUP(D42,DATOS!$D$6:D14000,DATOS!$C$6:C14000,0,0,1))} -> PANEL | F42: 2 | G42: 1 | H42: =IF(F42="","",(F42*G42)) -> 2 | K42: =IF(I42="","",(F42*I42)) | L42: =IF(I42="",H42,H42+(K42/J42)) -> 2 | O42: =IFERROR(__xludf.DUMMYFUNCTION("""COMPUTED_VALUE"""),46024.0) -> 46024 | P42: =IFERROR(__xludf.DUMMYFUNCTION("""COMPUTED_VALUE"""),"CONSUMIDOR FINAL") -> CONSUMIDOR FINAL | Q42: =IFERROR(__xludf.DUMMYFUNCTION("""COMPUTED_VALUE"""),"galleta marilu chocolate") -> galleta marilu chocolate | R42: =IFERROR(__xludf.DUMMYFUNCTION("""COMPUTED_VALUE"""),"00017") -> 00017 | S42: =IFERROR(__xludf.DUMMYFUNCTION("""COMPUTED_VALUE"""),2.0) -> 2 | T42: =IFERROR(__xludf.DUMMYFUNCTION("""COMPUTED_VALUE"""),0.5) -> 0.5 | U42: =IFERROR(__xludf.DUMMYFUNCTION("""COMPUTED_VALUE"""),1.0) -> 1
B43: 46023 | C43: CONSUMIDOR FINAL | D43: Refrescos 2lt | E43: {=IF(D43="","",XLOOKUP(D43,DATOS!$D$6:D14000,DATOS!$C$6:C14000,0,0,1))} -> REF4 | F43: 2 | G43: 6 | H43: =IF(F43="","",(F43*G43)) -> 12 | K43: =IF(I43="","",(F43*I43)) | L43: =IF(I43="",H43,H43+(K43/J43)) -> 12 | O43: =IFERROR(__xludf.DUMMYFUNCTION("""COMPUTED_VALUE"""),46024.0) -> 46024 | P43: =IFERROR(__xludf.DUMMYFUNCTION("""COMPUTED_VALUE"""),"CONSUMIDOR FINAL") -> CONSUMIDOR FINAL | Q43: =IFERROR(__xludf.DUMMYFUNCTION("""COMPUTED_VALUE"""),"Pollo 1kg") -> Pollo 1kg | R43: =IFERROR(__xludf.DUMMYFUNCTION("""COMPUTED_VALUE"""),"POLLO") -> POLLO | S43: =IFERROR(__xludf.DUMMYFUNCTION("""COMPUTED_VALUE"""),2.5) -> 2.5 | T43: =IFERROR(__xludf.DUMMYFUNCTION("""COMPUTED_VALUE"""),5.0) -> 5 | U43: =IFERROR(__xludf.DUMMYFUNCTION("""COMPUTED_VALUE"""),12.5) -> 12.5
B44: 46023 | C44: CONSUMIDOR FINAL | D44: Sardina Omega | E44: {=IF(D44="","",XLOOKUP(D44,DATOS!$D$6:D14000,DATOS!$C$6:C14000,0,0,1))} -> SAR3 | F44: 1 | G44: 1.5 | H44: =IF(F44="","",(F44*G44)) -> 1.5 | K44: =IF(I44="","",(F44*I44)) | L44: =IF(I44="",H44,H44+(K44/J44)) -> 1.5 | O44: =IFERROR(__xludf.DUMMYFUNCTION("""COMPUTED_VALUE"""),46024.0) -> 46024 | P44: =IFERROR(__xludf.DUMMYFUNCTION("""COMPUTED_VALUE"""),"CONSUMIDOR FINAL") -> CONSUMIDOR FINAL | Q44: =IFERROR(__xludf.DUMMYFUNCTION("""COMPUTED_VALUE"""),"Panelada 29gr") -> Panelada 29gr | R44: =IFERROR(__xludf.DUMMYFUNCTION("""COMPUTED_VALUE"""),"PANEL") -> PANEL | S44: =IFERROR(__xludf.DUMMYFUNCTION("""COMPUTED_VALUE"""),1.0) -> 1 | T44: =IFERROR(__xludf.DUMMYFUNCTION("""COMPUTED_VALUE"""),1.0) -> 1 | U44: =IFERROR(__xludf.DUMMYFUNCTION("""COMPUTED_VALUE"""),1.0) -> 1
B45: 46023 | C45: CONSUMIDOR FINAL | D45: Cubitos | E45: {=IF(D45="","",XLOOKUP(D45,DATOS!$D$6:D14000,DATOS!$C$6:C14000,0,0,1))} -> CUBITO1 | F45: 1 | G45: 0.5 | H45: =IF(F45="","",(F45*G45)) -> 0.5 | K45: =IF(I45="","",(F45*I45)) | L45: =IF(I45="",H45,H45+(K45/J45)) -> 0.5 | O45: =IFERROR(__xludf.DUMMYFUNCTION("""COMPUTED_VALUE"""),46024.0) -> 46024 | P45: =IFERROR(__xludf.DUMMYFUNCTION("""COMPUTED_VALUE"""),"CONSUMIDOR FINAL") -> CONSUMIDOR FINAL | Q45: =IFERROR(__xludf.DUMMYFUNCTION("""COMPUTED_VALUE"""),"Refrescos 2lt ") -> Refrescos 2lt | R45: =IFERROR(__xludf.DUMMYFUNCTION("""COMPUTED_VALUE"""),"REF4") -> REF4 | S45: =IFERROR(__xludf.DUMMYFUNCTION("""COMPUTED_VALUE"""),1.0) -> 1 | T45: =IFERROR(__xludf.DUMMYFUNCTION("""COMPUTED_VALUE"""),6.0) -> 6 | U45: =IFERROR(__xludf.DUMMYFUNCTION("""COMPUTED_VALUE"""),6.0) -> 6
B46: 46023 | C46: CONSUMIDOR FINAL | D46: Refrescos 2lt | E46: {=IF(D46="","",XLOOKUP(D46,DATOS!$D$6:D14000,DATOS!$C$6:C14000,0,0,1))} -> REF4 | F46: 1 | G46: 6 | H46: =IF(F46="","",(F46*G46)) -> 6 | K46: =IF(I46="","",(F46*I46)) | L46: =IF(I46="",H46,H46+(K46/J46)) -> 6 | O46: =IFERROR(__xludf.DUMMYFUNCTION("""COMPUTED_VALUE"""),46024.0) -> 46024 | P46: =IFERROR(__xludf.DUMMYFUNCTION("""COMPUTED_VALUE"""),"CONSUMIDOR FINAL") -> CONSUMIDOR FINAL | Q46: =IFERROR(__xludf.DUMMYFUNCTION("""COMPUTED_VALUE"""),"Pollo 1kg") -> Pollo 1kg | R46: =IFERROR(__xludf.DUMMYFUNCTION("""COMPUTED_VALUE"""),"POLLO") -> POLLO | S46: =IFERROR(__xludf.DUMMYFUNCTION("""COMPUTED_VALUE"""),30.0) -> 30 | T46: =IFERROR(__xludf.DUMMYFUNCTION("""COMPUTED_VALUE"""),5.0) -> 5 | U46: =IFERROR(__xludf.DUMMYFUNCTION("""COMPUTED_VALUE"""),150.0) -> 150
B47: 46023 | C47: CONSUMIDOR FINAL | D47: Sardina Omega | E47: {=IF(D47="","",XLOOKUP(D47,DATOS!$D$6:D14000,DATOS!$C$6:C14000,0,0,1))} -> SAR3 | F47: 1 | G47: 1.5 | H47: =IF(F47="","",(F47*G47)) -> 1.5 | K47: =IF(I47="","",(F47*I47)) | L47: =IF(I47="",H47,H47+(K47/J47)) -> 1.5 | O47: =IFERROR(__xludf.DUMMYFUNCTION("""COMPUTED_VALUE"""),46024.0) -> 46024 | P47: =IFERROR(__xludf.DUMMYFUNCTION("""COMPUTED_VALUE"""),"CONSUMIDOR FINAL") -> CONSUMIDOR FINAL | Q47: =IFERROR(__xludf.DUMMYFUNCTION("""COMPUTED_VALUE"""),"Leche Do Bon 400g") -> Leche Do Bon 400g | R47: =IFERROR(__xludf.DUMMYFUNCTION("""COMPUTED_VALUE"""),"LECH7") -> LECH7 | S47: =IFERROR(__xludf.DUMMYFUNCTION("""COMPUTED_VALUE"""),2.0) -> 2 | T47: =IFERROR(__xludf.DUMMYFUNCTION("""COMPUTED_VALUE"""),5.0) -> 5 | U47: =IFERROR(__xludf.DUMMYFUNCTION("""COMPUTED_VALUE"""),10.0) -> 10
B48: 46023 | C48: CONSUMIDOR FINAL | D48: Cubitos | E48: {=IF(D48="","",XLOOKUP(D48,DATOS!$D$6:D14000,DATOS!$C$6:C14000,0,0,1))} -> CUBITO1 | F48: 1 | G48: 0.5 | H48: =IF(F48="","",(F48*G48)) -> 0.5 | K48: =IF(I48="","",(F48*I48)) | L48: =IF(I48="",H48,H48+(K48/J48)) -> 0.5 | O48: =IFERROR(__xludf.DUMMYFUNCTION("""COMPUTED_VALUE"""),46024.0) -> 46024 | P48: =IFERROR(__xludf.DUMMYFUNCTION("""COMPUTED_VALUE"""),"CONSUMIDOR FINAL") -> CONSUMIDOR FINAL | Q48: =IFERROR(__xludf.DUMMYFUNCTION("""COMPUTED_VALUE"""),"MARGARINA MAVESA 500GR") -> MARGARINA MAVESA 500GR | R48: =IFERROR(__xludf.DUMMYFUNCTION("""COMPUTED_VALUE"""),"MARG2") -> MARG2 | S48: =IFERROR(__xludf.DUMMYFUNCTION("""COMPUTED_VALUE"""),2.0) -> 2 | T48: =IFERROR(__xludf.DUMMYFUNCTION("""COMPUTED_VALUE"""),4.0) -> 4 | U48: =IFERROR(__xludf.DUMMYFUNCTION("""COMPUTED_VALUE"""),8.0) -> 8
B49: 46023 | C49: CONSUMIDOR FINAL | D49: MORTADELA ALIBAL 500GR | E49: {=IF(D49="","",XLOOKUP(D49,DATOS!$D$6:D14000,DATOS!$C$6:C14000,0,0,1))} -> MOR04 | F49: 1 | G49: 3 | H49: =IF(F49="","",(F49*G49)) -> 3 | K49: =IF(I49="","",(F49*I49)) | L49: =IF(I49="",H49,H49+(K49/J49)) -> 3 | O49: =IFERROR(__xludf.DUMMYFUNCTION("""COMPUTED_VALUE"""),46024.0) -> 46024 | P49: =IFERROR(__xludf.DUMMYFUNCTION("""COMPUTED_VALUE"""),"CONSUMIDOR FINAL") -> CONSUMIDOR FINAL | Q49: =IFERROR(__xludf.DUMMYFUNCTION("""COMPUTED_VALUE"""),"Refrescos 1lt") -> Refrescos 1lt | R49: =IFERROR(__xludf.DUMMYFUNCTION("""COMPUTED_VALUE"""),"REF3") -> REF3 | S49: =IFERROR(__xludf.DUMMYFUNCTION("""COMPUTED_VALUE"""),6.0) -> 6 | T49: =IFERROR(__xludf.DUMMYFUNCTION("""COMPUTED_VALUE"""),3.0) -> 3 | U49: =IFERROR(__xludf.DUMMYFUNCTION("""COMPUTED_VALUE"""),18.0) -> 18
B50: 46023 | C50: CONSUMIDOR FINAL | D50: pasta/mry/tradicional vermi L | E50: {=IF(D50="","",XLOOKUP(D50,DATOS!$D$6:D14000,DATOS!$C$6:C14000,0,0,1))} -> 00016 | F50: 1 | G50: 3 | H50: =IF(F50="","",(F50*G50)) -> 3 | K50: =IF(I50="","",(F50*I50)) | L50: =IF(I50="",H50,H50+(K50/J50)) -> 3 | O50: =IFERROR(__xludf.DUMMYFUNCTION("""COMPUTED_VALUE"""),46024.0) -> 46024 | P50: =IFERROR(__xludf.DUMMYFUNCTION("""COMPUTED_VALUE"""),"CONSUMIDOR FINAL") -> CONSUMIDOR FINAL | Q50: =IFERROR(__xludf.DUMMYFUNCTION("""COMPUTED_VALUE"""),"MINI SAMBAS") -> MINI SAMBAS | R50: =IFERROR(__xludf.DUMMYFUNCTION("""COMPUTED_VALUE"""),"MINSAM") -> MINSAM | S50: =IFERROR(__xludf.DUMMYFUNCTION("""COMPUTED_VALUE"""),3.0) -> 3 | T50: =IFERROR(__xludf.DUMMYFUNCTION("""COMPUTED_VALUE"""),1.0) -> 1 | U50: =IFERROR(__xludf.DUMMYFUNCTION("""COMPUTED_VALUE"""),3.0) -> 3
B51: 46023 | C51: CONSUMIDOR FINAL | D51: ACEITE LA PAMPA 700ML | E51: {=IF(D51="","",XLOOKUP(D51,DATOS!$D$6:D14000,DATOS!$C$6:C14000,0,0,1))} -> 00084 | F51: 1 | G51: 4 | H51: =IF(F51="","",(F51*G51)) -> 4 | K51: =IF(I51="","",(F51*I51)) | L51: =IF(I51="",H51,H51+(K51/J51)) -> 4 | O51: =IFERROR(__xludf.DUMMYFUNCTION("""COMPUTED_VALUE"""),46024.0) -> 46024 | P51: =IFERROR(__xludf.DUMMYFUNCTION("""COMPUTED_VALUE"""),"CONSUMIDOR FINAL") -> CONSUMIDOR FINAL | Q51: =IFERROR(__xludf.DUMMYFUNCTION("""COMPUTED_VALUE"""),"Refrescos 2lt ") -> Refrescos 2lt | R51: =IFERROR(__xludf.DUMMYFUNCTION("""COMPUTED_VALUE"""),"REF4") -> REF4 | S51: =IFERROR(__xludf.DUMMYFUNCTION("""COMPUTED_VALUE"""),1.0) -> 1 | T51: =IFERROR(__xludf.DUMMYFUNCTION("""COMPUTED_VALUE"""),6.0) -> 6 | U51: =IFERROR(__xludf.DUMMYFUNCTION("""COMPUTED_VALUE"""),6.0) -> 6
B52: 46023 | C52: CONSUMIDOR FINAL | D52: LECHE NAN 1 400GR | E52: {=IF(D52="","",XLOOKUP(D52,DATOS!$D$6:D14000,DATOS!$C$6:C14000,0,0,1))} -> 00100 | F52: 3 | G52: 20 | H52: =IF(F52="","",(F52*G52)) -> 60 | K52: =IF(I52="","",(F52*I52)) | L52: =IF(I52="",H52,H52+(K52/J52)) -> 60 | O52: =IFERROR(__xludf.DUMMYFUNCTION("""COMPUTED_VALUE"""),46024.0) -> 46024 | P52: =IFERROR(__xludf.DUMMYFUNCTION("""COMPUTED_VALUE"""),"CONSUMIDOR FINAL") -> CONSUMIDOR FINAL | Q52: =IFERROR(__xludf.DUMMYFUNCTION("""COMPUTED_VALUE"""),"Azucar Montalban 1kg") -> Azucar Montalban 1kg | R52: =IFERROR(__xludf.DUMMYFUNCTION("""COMPUTED_VALUE"""),"AZ6") -> AZ6 | S52: =IFERROR(__xludf.DUMMYFUNCTION("""COMPUTED_VALUE"""),1.0) -> 1 | T52: =IFERROR(__xludf.DUMMYFUNCTION("""COMPUTED_VALUE"""),3.0) -> 3 | U52: =IFERROR(__xludf.DUMMYFUNCTION("""COMPUTED_VALUE"""),3.0) -> 3
B53: 46023 | C53: CONSUMIDOR FINAL | D53: Panelada 29gr | E53: {=IF(D53="","",XLOOKUP(D53,DATOS!$D$6:D14000,DATOS!$C$6:C14000,0,0,1))} -> PANEL | F53: 1 | G53: 1 | H53: =IF(F53="","",(F53*G53)) -> 1 | K53: =IF(I53="","",(F53*I53)) | L53: =IF(I53="",H53,H53+(K53/J53)) -> 1 | O53: =IFERROR(__xludf.DUMMYFUNCTION("""COMPUTED_VALUE"""),46024.0) -> 46024 | P53: =IFERROR(__xludf.DUMMYFUNCTION("""COMPUTED_VALUE"""),"CONSUMIDOR FINAL") -> CONSUMIDOR FINAL | Q53: =IFERROR(__xludf.DUMMYFUNCTION("""COMPUTED_VALUE"""),"Sardina Omega") -> Sardina Omega | R53: =IFERROR(__xludf.DUMMYFUNCTION("""COMPUTED_VALUE"""),"SAR3") -> SAR3 | S53: =IFERROR(__xludf.DUMMYFUNCTION("""COMPUTED_VALUE"""),2.0) -> 2 | T53: =IFERROR(__xludf.DUMMYFUNCTION("""COMPUTED_VALUE"""),1.5) -> 1.5 | U53: =IFERROR(__xludf.DUMMYFUNCTION("""COMPUTED_VALUE"""),3.0) -> 3
B54: 46023 | C54: CONSUMIDOR FINAL | D54: Pañal Baby finger XG | E54: {=IF(D54="","",XLOOKUP(D54,DATOS!$D$6:D14000,DATOS!$C$6:C14000,0,0,1))} -> PAÑL1 | F54: 4 | G54: 0.5 | H54: =IF(F54="","",(F54*G54)) -> 2 | K54: =IF(I54="","",(F54*I54)) | L54: =IF(I54="",H54,H54+(K54/J54)) -> 2 | O54: =IFERROR(__xludf.DUMMYFUNCTION("""COMPUTED_VALUE"""),46024.0) -> 46024 | P54: =IFERROR(__xludf.DUMMYFUNCTION("""COMPUTED_VALUE"""),"CONSUMIDOR FINAL") -> CONSUMIDOR FINAL | Q54: =IFERROR(__xludf.DUMMYFUNCTION("""COMPUTED_VALUE"""),"Queso duro") -> Queso duro | R54: =IFERROR(__xludf.DUMMYFUNCTION("""COMPUTED_VALUE"""),"QUES1") -> QUES1 | S54: =IFERROR(__xludf.DUMMYFUNCTION("""COMPUTED_VALUE"""),0.2) -> 0.2 | T54: =IFERROR(__xludf.DUMMYFUNCTION("""COMPUTED_VALUE"""),10.0) -> 10 | U54: =IFERROR(__xludf.DUMMYFUNCTION("""COMPUTED_VALUE"""),2.0) -> 2
B55: 46023 | C55: CONSUMIDOR FINAL | D55: Jabon las llaves floral (200gr) | E55: {=IF(D55="","",XLOOKUP(D55,DATOS!$D$6:D14000,DATOS!$C$6:C14000,0,0,1))} -> 00029 | F55: 1 | G55: 2 | H55: =IF(F55="","",(F55*G55)) -> 2 | K55: =IF(I55="","",(F55*I55)) | L55: =IF(I55="",H55,H55+(K55/J55)) -> 2 | O55: =IFERROR(__xludf.DUMMYFUNCTION("""COMPUTED_VALUE"""),46024.0) -> 46024 | P55: =IFERROR(__xludf.DUMMYFUNCTION("""COMPUTED_VALUE"""),"CONSUMIDOR FINAL") -> CONSUMIDOR FINAL | Q55: =IFERROR(__xludf.DUMMYFUNCTION("""COMPUTED_VALUE"""),"Azucar Montalban 1kg") -> Azucar Montalban 1kg | R55: =IFERROR(__xludf.DUMMYFUNCTION("""COMPUTED_VALUE"""),"AZ6") -> AZ6 | S55: =IFERROR(__xludf.DUMMYFUNCTION("""COMPUTED_VALUE"""),1.0) -> 1 | T55: =IFERROR(__xludf.DUMMYFUNCTION("""COMPUTED_VALUE"""),3.0) -> 3 | U55: =IFERROR(__xludf.DUMMYFUNCTION("""COMPUTED_VALUE"""),3.0) -> 3
B56: 46023 | C56: CONSUMIDOR FINAL | D56: Refrescos 2lt | E56: {=IF(D56="","",XLOOKUP(D56,DATOS!$D$6:D14000,DATOS!$C$6:C14000,0,0,1))} -> REF4 | F56: 1 | G56: 6 | H56: =IF(F56="","",(F56*G56)) -> 6 | K56: =IF(I56="","",(F56*I56)) | L56: =IF(I56="",H56,H56+(K56/J56)) -> 6 | O56: =IFERROR(__xludf.DUMMYFUNCTION("""COMPUTED_VALUE"""),46024.0) -> 46024 | P56: =IFERROR(__xludf.DUMMYFUNCTION("""COMPUTED_VALUE"""),"CONSUMIDOR FINAL") -> CONSUMIDOR FINAL | Q56: =IFERROR(__xludf.DUMMYFUNCTION("""COMPUTED_VALUE"""),"MARGARINA MAVESA 500GR") -> MARGARINA MAVESA 500GR | R56: =IFERROR(__xludf.DUMMYFUNCTION("""COMPUTED_VALUE"""),"MARG2") -> MARG2 | S56: =IFERROR(__xludf.DUMMYFUNCTION("""COMPUTED_VALUE"""),1.0) -> 1 | T56: =IFERROR(__xludf.DUMMYFUNCTION("""COMPUTED_VALUE"""),4.0) -> 4 | U56: =IFERROR(__xludf.DUMMYFUNCTION("""COMPUTED_VALUE"""),4.0) -> 4
B57: 46023 | C57: CONSUMIDOR FINAL | D57: Refrescos 1,5lt | E57: {=IF(D57="","",XLOOKUP(D57,DATOS!$D$6:D14000,DATOS!$C$6:C14000,0,0,1))} -> REF2 | F57: 1 | G57: 4 | H57: =IF(F57="","",(F57*G57)) -> 4 | K57: =IF(I57="","",(F57*I57)) | L57: =IF(I57="",H57,H57+(K57/J57)) -> 4 | O57: =IFERROR(__xludf.DUMMYFUNCTION("""COMPUTED_VALUE"""),46024.0) -> 46024 | P57: =IFERROR(__xludf.DUMMYFUNCTION("""COMPUTED_VALUE"""),"CONSUMIDOR FINAL") -> CONSUMIDOR FINAL | Q57: =IFERROR(__xludf.DUMMYFUNCTION("""COMPUTED_VALUE"""),"galleta marilu chocolate") -> galleta marilu chocolate | R57: =IFERROR(__xludf.DUMMYFUNCTION("""COMPUTED_VALUE"""),"00017") -> 00017 | S57: =IFERROR(__xludf.DUMMYFUNCTION("""COMPUTED_VALUE"""),2.0) -> 2 | T57: =IFERROR(__xludf.DUMMYFUNCTION("""COMPUTED_VALUE"""),0.5) -> 0.5 | U57: =IFERROR(__xludf.DUMMYFUNCTION("""COMPUTED_VALUE"""),1.0) -> 1
B58: 46023 | C58: CONSUMIDOR FINAL | D58: CARAMELOS FRUTICAS 100UND | E58: {=IF(D58="","",XLOOKUP(D58,DATOS!$D$6:D14000,DATOS!$C$6:C14000,0,0,1))} -> CARM005 | F58: 5 | G58: 0.1 | H58: =IF(F58="","",(F58*G58)) -> 0.5 | K58: =IF(I58="","",(F58*I58)) | L58: =IF(I58="",H58,H58+(K58/J58)) -> 0.5 | O58: =IFERROR(__xludf.DUMMYFUNCTION("""COMPUTED_VALUE"""),46024.0) -> 46024 | P58: =IFERROR(__xludf.DUMMYFUNCTION("""COMPUTED_VALUE"""),"CONSUMIDOR FINAL") -> CONSUMIDOR FINAL | Q58: =IFERROR(__xludf.DUMMYFUNCTION("""COMPUTED_VALUE"""),"GALLETA MARILU CHOCOVAINILLA") -> GALLETA MARILU CHOCOVAINILLA | R58: =IFERROR(__xludf.DUMMYFUNCTION("""COMPUTED_VALUE"""),"GALL024") -> GALL024 | S58: =IFERROR(__xludf.DUMMYFUNCTION("""COMPUTED_VALUE"""),2.0) -> 2 | T58: =IFERROR(__xludf.DUMMYFUNCTION("""COMPUTED_VALUE"""),0.5) -> 0.5 | U58: =IFERROR(__xludf.DUMMYFUNCTION("""COMPUTED_VALUE"""),1.0) -> 1
B59: 46023 | C59: CONSUMIDOR FINAL | D59: Caramelos Bianchi | E59: {=IF(D59="","",XLOOKUP(D59,DATOS!$D$6:D14000,DATOS!$C$6:C14000,0,0,1))} -> CARM2 | F59: 5 | G59: 0.1 | H59: =IF(F59="","",(F59*G59)) -> 0.5 | K59: =IF(I59="","",(F59*I59)) | L59: =IF(I59="",H59,H59+(K59/J59)) -> 0.5 | O59: =IFERROR(__xludf.DUMMYFUNCTION("""COMPUTED_VALUE"""),46024.0) -> 46024 | P59: =IFERROR(__xludf.DUMMYFUNCTION("""COMPUTED_VALUE"""),"CONSUMIDOR FINAL") -> CONSUMIDOR FINAL | Q59: =IFERROR(__xludf.DUMMYFUNCTION("""COMPUTED_VALUE"""),"Queso duro") -> Queso duro | R59: =IFERROR(__xludf.DUMMYFUNCTION("""COMPUTED_VALUE"""),"QUES1") -> QUES1 | S59: =IFERROR(__xludf.DUMMYFUNCTION("""COMPUTED_VALUE"""),0.2) -> 0.2 | T59: =IFERROR(__xludf.DUMMYFUNCTION("""COMPUTED_VALUE"""),10.0) -> 10 | U59: =IFERROR(__xludf.DUMMYFUNCTION("""COMPUTED_VALUE"""),2.0) -> 2
B60: 46023 | C60: CONSUMIDOR FINAL | D60: HALLACAS | E60: {=IF(D60="","",XLOOKUP(D60,DATOS!$D$6:D14000,DATOS!$C$6:C14000,0,0,1))} -> 00050 | F60: 2 | G60: 3.5 | H60: =IF(F60="","",(F60*G60)) -> 7 | K60: =IF(I60="","",(F60*I60)) | L60: =IF(I60="",H60,H60+(K60/J60)) -> 7 | O60: =IFERROR(__xludf.DUMMYFUNCTION("""COMPUTED_VALUE"""),46024.0) -> 46024 | P60: =IFERROR(__xludf.DUMMYFUNCTION("""COMPUTED_VALUE"""),"CONSUMIDOR FINAL") -> CONSUMIDOR FINAL | Q60: =IFERROR(__xludf.DUMMYFUNCTION("""COMPUTED_VALUE"""),"Huevo") -> Huevo | R60: =IFERROR(__xludf.DUMMYFUNCTION("""COMPUTED_VALUE"""),"HUEVO") -> HUEVO | S60: =IFERROR(__xludf.DUMMYFUNCTION("""COMPUTED_VALUE"""),3.0) -> 3 | T60: =IFERROR(__xludf.DUMMYFUNCTION("""COMPUTED_VALUE"""),0.3333) -> 0.3333 | U60: =IFERROR(__xludf.DUMMYFUNCTION("""COMPUTED_VALUE"""),0.9999) -> 0.9999
B61: 46023 | C61: CONSUMIDOR FINAL | D61: Refrescos 1lt | E61: {=IF(D61="","",XLOOKUP(D61,DATOS!$D$6:D14000,DATOS!$C$6:C14000,0,0,1))} -> REF3 | F61: 1 | G61: 3 | H61: =IF(F61="","",(F61*G61)) -> 3 | K61: =IF(I61="","",(F61*I61)) | L61: =IF(I61="",H61,H61+(K61/J61)) -> 3 | O61: =IFERROR(__xludf.DUMMYFUNCTION("""COMPUTED_VALUE"""),46024.0) -> 46024 | P61: =IFERROR(__xludf.DUMMYFUNCTION("""COMPUTED_VALUE"""),"CONSUMIDOR FINAL") -> CONSUMIDOR FINAL | Q61: =IFERROR(__xludf.DUMMYFUNCTION("""COMPUTED_VALUE"""),"Cubitos") -> Cubitos | R61: =IFERROR(__xludf.DUMMYFUNCTION("""COMPUTED_VALUE"""),"CUBITO1") -> CUBITO1 | S61: =IFERROR(__xludf.DUMMYFUNCTION("""COMPUTED_VALUE"""),2.0) -> 2 | T61: =IFERROR(__xludf.DUMMYFUNCTION("""COMPUTED_VALUE"""),0.5) -> 0.5 | U61: =IFERROR(__xludf.DUMMYFUNCTION("""COMPUTED_VALUE"""),1.0) -> 1
B62: 46023 | C62: CONSUMIDOR FINAL | D62: HALLACAS | E62: {=IF(D62="","",XLOOKUP(D62,DATOS!$D$6:D14000,DATOS!$C$6:C14000,0,0,1))} -> 00050 | F62: 2 | G62: 4.5 | H62: =IF(F62="","",(F62*G62)) -> 9 | K62: =IF(I62="","",(F62*I62)) | L62: =IF(I62="",H62,H62+(K62/J62)) -> 9 | O62: =IFERROR(__xludf.DUMMYFUNCTION("""COMPUTED_VALUE"""),46024.0) -> 46024 | P62: =IFERROR(__xludf.DUMMYFUNCTION("""COMPUTED_VALUE"""),"CONSUMIDOR FINAL") -> CONSUMIDOR FINAL | Q62: =IFERROR(__xludf.DUMMYFUNCTION("""COMPUTED_VALUE"""),"Maltin polar 1,5lt") -> Maltin polar 1,5lt | R62: =IFERROR(__xludf.DUMMYFUNCTION("""COMPUTED_VALUE"""),"MAL1") -> MAL1 | S62: =IFERROR(__xludf.DUMMYFUNCTION("""COMPUTED_VALUE"""),1.0) -> 1 | T62: =IFERROR(__xludf.DUMMYFUNCTION("""COMPUTED_VALUE"""),5.0) -> 5 | U62: =IFERROR(__xludf.DUMMYFUNCTION("""COMPUTED_VALUE"""),5.0) -> 5
B63: 46023 | C63: CONSUMIDOR FINAL | D63: Refrescos 1lt | E63: {=IF(D63="","",XLOOKUP(D63,DATOS!$D$6:D14000,DATOS!$C$6:C14000,0,0,1))} -> REF3 | F63: 1 | G63: 3 | H63: =IF(F63="","",(F63*G63)) -> 3 | K63: =IF(I63="","",(F63*I63)) | L63: =IF(I63="",H63,H63+(K63/J63)) -> 3 | O63: =IFERROR(__xludf.DUMMYFUNCTION("""COMPUTED_VALUE"""),46024.0) -> 46024 | P63: =IFERROR(__xludf.DUMMYFUNCTION("""COMPUTED_VALUE"""),"CONSUMIDOR FINAL") -> CONSUMIDOR FINAL | Q63: =IFERROR(__xludf.DUMMYFUNCTION("""COMPUTED_VALUE"""),"JABON MIMLOT 125 G") -> JABON MIMLOT 125 G | R63: =IFERROR(__xludf.DUMMYFUNCTION("""COMPUTED_VALUE"""),"00065") -> 00065 | S63: =IFERROR(__xludf.DUMMYFUNCTION("""COMPUTED_VALUE"""),1.0) -> 1 | T63: =IFERROR(__xludf.DUMMYFUNCTION("""COMPUTED_VALUE"""),2.0) -> 2 | U63: =IFERROR(__xludf.DUMMYFUNCTION("""COMPUTED_VALUE"""),2.0) -> 2
B64: 46023 | C64: CONSUMIDOR FINAL | D64: Sardina Omega | E64: {=IF(D64="","",XLOOKUP(D64,DATOS!$D$6:D14000,DATOS!$C$6:C14000,0,0,1))} -> SAR3 | F64: 3 | G64: 1.5 | H64: =IF(F64="","",(F64*G64)) -> 4.5 | K64: =IF(I64="","",(F64*I64)) | L64: =IF(I64="",H64,H64+(K64/J64)) -> 4.5 | O64: =IFERROR(__xludf.DUMMYFUNCTION("""COMPUTED_VALUE"""),46024.0) -> 46024 | P64: =IFERROR(__xludf.DUMMYFUNCTION("""COMPUTED_VALUE"""),"CONSUMIDOR FINAL") -> CONSUMIDOR FINAL | Q64: =IFERROR(__xludf.DUMMYFUNCTION("""COMPUTED_VALUE"""),"CAFE AMANECER 100 GR") -> CAFE AMANECER 100 GR | R64: =IFERROR(__xludf.DUMMYFUNCTION("""COMPUTED_VALUE"""),"00058") -> 00058 | S64: =IFERROR(__xludf.DUMMYFUNCTION("""COMPUTED_VALUE"""),1.0) -> 1 | T64: =IFERROR(__xludf.DUMMYFUNCTION("""COMPUTED_VALUE"""),2.0) -> 2 | U64: =IFERROR(__xludf.DUMMYFUNCTION("""COMPUTED_VALUE"""),2.0) -> 2
B65: 46023 | C65: CONSUMIDOR FINAL | D65: Cubitos | E65: {=IF(D65="","",XLOOKUP(D65,DATOS!$D$6:D14000,DATOS!$C$6:C14000,0,0,1))} -> CUBITO1 | F65: 1 | G65: 0.5 | H65: =IF(F65="","",(F65*G65)) -> 0.5 | K65: =IF(I65="","",(F65*I65)) | L65: =IF(I65="",H65,H65+(K65/J65)) -> 0.5 | O65: =IFERROR(__xludf.DUMMYFUNCTION("""COMPUTED_VALUE"""),46024.0) -> 46024 | P65: =IFERROR(__xludf.DUMMYFUNCTION("""COMPUTED_VALUE"""),"CONSUMIDOR FINAL") -> CONSUMIDOR FINAL | Q65: =IFERROR(__xludf.DUMMYFUNCTION("""COMPUTED_VALUE"""),"Harina Pan Maiz Blanca 1kg") -> Harina Pan Maiz Blanca 1kg | R65: =IFERROR(__xludf.DUMMYFUNCTION("""COMPUTED_VALUE"""),"HP3") -> HP3 | S65: =IFERROR(__xludf.DUMMYFUNCTION("""COMPUTED_VALUE"""),1.0) -> 1 | T65: =IFERROR(__xludf.DUMMYFUNCTION("""COMPUTED_VALUE"""),2.5) -> 2.5 | U65: =IFERROR(__xludf.DUMMYFUNCTION("""COMPUTED_VALUE"""),2.5) -> 2.5
B66: 46023 | C66: CONSUMIDOR FINAL | D66: Toddy 200g | E66: {=IF(D66="","",XLOOKUP(D66,DATOS!$D$6:D14000,DATOS!$C$6:C14000,0,0,1))} -> TODDY2 | F66: 1 | G66: 4 | H66: =IF(F66="","",(F66*G66)) -> 4 | K66: =IF(I66="","",(F66*I66)) | L66: =IF(I66="",H66,H66+(K66/J66)) -> 4 | O66: =IFERROR(__xludf.DUMMYFUNCTION("""COMPUTED_VALUE"""),46024.0) -> 46024 | P66: =IFERROR(__xludf.DUMMYFUNCTION("""COMPUTED_VALUE"""),"CONSUMIDOR FINAL") -> CONSUMIDOR FINAL | Q66: =IFERROR(__xludf.DUMMYFUNCTION("""COMPUTED_VALUE"""),"CARAMELOS FRUTICAS 100UND") -> CARAMELOS FRUTICAS 100UND | R66: =IFERROR(__xludf.DUMMYFUNCTION("""COMPUTED_VALUE"""),"CARM005") -> CARM005 | S66: =IFERROR(__xludf.DUMMYFUNCTION("""COMPUTED_VALUE"""),5.0) -> 5 | T66: =IFERROR(__xludf.DUMMYFUNCTION("""COMPUTED_VALUE"""),0.1) -> 0.1 | U66: =IFERROR(__xludf.DUMMYFUNCTION("""COMPUTED_VALUE"""),0.5) -> 0.5
B67: 46023 | C67: CONSUMIDOR FINAL | D67: LECHE DOBON 200GR | E67: {=IF(D67="","",XLOOKUP(D67,DATOS!$D$6:D14000,DATOS!$C$6:C14000,0,0,1))} -> 00083 | F67: 1 | G67: 3 | H67: =IF(F67="","",(F67*G67)) -> 3 | K67: =IF(I67="","",(F67*I67)) | L67: =IF(I67="",H67,H67+(K67/J67)) -> 3 | O67: =IFERROR(__xludf.DUMMYFUNCTION("""COMPUTED_VALUE"""),46024.0) -> 46024 | P67: =IFERROR(__xludf.DUMMYFUNCTION("""COMPUTED_VALUE"""),"CONSUMIDOR FINAL") -> CONSUMIDOR FINAL | Q67: =IFERROR(__xludf.DUMMYFUNCTION("""COMPUTED_VALUE"""),"Huevo") -> Huevo | R67: =IFERROR(__xludf.DUMMYFUNCTION("""COMPUTED_VALUE"""),"HUEVO") -> HUEVO | S67: =IFERROR(__xludf.DUMMYFUNCTION("""COMPUTED_VALUE"""),15.0) -> 15 | T67: =IFERROR(__xludf.DUMMYFUNCTION("""COMPUTED_VALUE"""),0.333333) -> 0.333333 | U67: =IFERROR(__xludf.DUMMYFUNCTION("""COMPUTED_VALUE"""),4.999995) -> 4.999995
B68: 46023 | C68: CONSUMIDOR FINAL | D68: Queso duro | E68: {=IF(D68="","",XLOOKUP(D68,DATOS!$D$6:D14000,DATOS!$C$6:C14000,0,0,1))} -> QUES1 | F68: 0.2 | G68: 10 | H68: =IF(F68="","",(F68*G68)) -> 2 | K68: =IF(I68="","",(F68*I68)) | L68: =IF(I68="",H68,H68+(K68/J68)) -> 2 | O68: =IFERROR(__xludf.DUMMYFUNCTION("""COMPUTED_VALUE"""),46024.0) -> 46024 | P68: =IFERROR(__xludf.DUMMYFUNCTION("""COMPUTED_VALUE"""),"CONSUMIDOR FINAL") -> CONSUMIDOR FINAL | Q68: =IFERROR(__xludf.DUMMYFUNCTION("""COMPUTED_VALUE"""),"Harina Pan Maiz Blanca 1kg") -> Harina Pan Maiz Blanca 1kg | R68: =IFERROR(__xludf.DUMMYFUNCTION("""COMPUTED_VALUE"""),"HP3") -> HP3 | S68: =IFERROR(__xludf.DUMMYFUNCTION("""COMPUTED_VALUE"""),1.0) -> 1 | T68: =IFERROR(__xludf.DUMMYFUNCTION("""COMPUTED_VALUE"""),2.5) -> 2.5 | U68: =IFERROR(__xludf.DUMMYFUNCTION("""COMPUTED_VALUE"""),2.5) -> 2.5
B69: 46023 | C69: CONSUMIDOR FINAL | D69: CARAMELOS FRUTICAS 100UND | E69: {=IF(D69="","",XLOOKUP(D69,DATOS!$D$6:D14000,DATOS!$C$6:C14000,0,0,1))} -> CARM005 | F69: 5 | G69: 0.1 | H69: =IF(F69="","",(F69*G69)) -> 0.5 | K69: =IF(I69="","",(F69*I69)) | L69: =IF(I69="",H69,H69+(K69/J69)) -> 0.5 | O69: =IFERROR(__xludf.DUMMYFUNCTION("""COMPUTED_VALUE"""),46024.0) -> 46024 | P69: =IFERROR(__xludf.DUMMYFUNCTION("""COMPUTED_VALUE"""),"CONSUMIDOR FINAL") -> CONSUMIDOR FINAL | Q69: =IFERROR(__xludf.DUMMYFUNCTION("""COMPUTED_VALUE"""),"CARAMELOS FRUTICAS 100UND") -> CARAMELOS FRUTICAS 100UND | R69: =IFERROR(__xludf.DUMMYFUNCTION("""COMPUTED_VALUE"""),"CARM005") -> CARM005 | S69: =IFERROR(__xludf.DUMMYFUNCTION("""COMPUTED_VALUE"""),5.0) -> 5 | T69: =IFERROR(__xludf.DUMMYFUNCTION("""COMPUTED_VALUE"""),0.1) -> 0.1 | U69: =IFERROR(__xludf.DUMMYFUNCTION("""COMPUTED_VALUE"""),0.5) -> 0.5
B70: 46023 | C70: CONSUMIDOR FINAL | D70: Aceite Vatel 500ml | E70: {=IF(D70="","",XLOOKUP(D70,DATOS!$D$6:D14000,DATOS!$C$6:C14000,0,0,1))} -> AC6 | F70: 1 | G70: 3.5 | H70: =IF(F70="","",(F70*G70)) -> 3.5 | K70: =IF(I70="","",(F70*I70)) | L70: =IF(I70="",H70,H70+(K70/J70)) -> 3.5 | O70: =IFERROR(__xludf.DUMMYFUNCTION("""COMPUTED_VALUE"""),46024.0) -> 46024 | P70: =IFERROR(__xludf.DUMMYFUNCTION("""COMPUTED_VALUE"""),"CONSUMIDOR FINAL") -> CONSUMIDOR FINAL | Q70: =IFERROR(__xludf.DUMMYFUNCTION("""COMPUTED_VALUE"""),"LECHE DOBON 200GR") -> LECHE DOBON 200GR | R70: =IFERROR(__xludf.DUMMYFUNCTION("""COMPUTED_VALUE"""),"00083") -> 00083 | S70: =IFERROR(__xludf.DUMMYFUNCTION("""COMPUTED_VALUE"""),1.0) -> 1 | T70: =IFERROR(__xludf.DUMMYFUNCTION("""COMPUTED_VALUE"""),3.0) -> 3 | U70: =IFERROR(__xludf.DUMMYFUNCTION("""COMPUTED_VALUE"""),3.0) -> 3
B71: 46023 | C71: CONSUMIDOR FINAL | D71: CAFE AMANECER 100 GR | E71: {=IF(D71="","",XLOOKUP(D71,DATOS!$D$6:D14000,DATOS!$C$6:C14000,0,0,1))} -> 00058 | F71: 1 | G71: 2 | H71: =IF(F71="","",(F71*G71)) -> 2 | K71: =IF(I71="","",(F71*I71)) | L71: =IF(I71="",H71,H71+(K71/J71)) -> 2 | O71: =IFERROR(__xludf.DUMMYFUNCTION("""COMPUTED_VALUE"""),46024.0) -> 46024 | P71: =IFERROR(__xludf.DUMMYFUNCTION("""COMPUTED_VALUE"""),"CONSUMIDOR FINAL") -> CONSUMIDOR FINAL | Q71: =IFERROR(__xludf.DUMMYFUNCTION("""COMPUTED_VALUE"""),"Belmont") -> Belmont | R71: =IFERROR(__xludf.DUMMYFUNCTION("""COMPUTED_VALUE"""),"BELM") -> BELM | S71: =IFERROR(__xludf.DUMMYFUNCTION("""COMPUTED_VALUE"""),4.0) -> 4 | T71: =IFERROR(__xludf.DUMMYFUNCTION("""COMPUTED_VALUE"""),0.25) -> 0.25 | U71: =IFERROR(__xludf.DUMMYFUNCTION("""COMPUTED_VALUE"""),1.0) -> 1
B72: 46023 | C72: CONSUMIDOR FINAL | D72: Huevo | E72: {=IF(D72="","",XLOOKUP(D72,DATOS!$D$6:D14000,DATOS!$C$6:C14000,0,0,1))} -> HUEVO | F72: 6 | G72: 0.3333333 | H72: =IF(F72="","",(F72*G72)) -> 1.9999998 | K72: =IF(I72="","",(F72*I72)) | L72: =IF(I72="",H72,H72+(K72/J72)) -> 1.9999998 | O72: =IFERROR(__xludf.DUMMYFUNCTION("""COMPUTED_VALUE"""),46024.0) -> 46024 | P72: =IFERROR(__xludf.DUMMYFUNCTION("""COMPUTED_VALUE"""),"CONSUMIDOR FINAL") -> CONSUMIDOR FINAL | Q72: =IFERROR(__xludf.DUMMYFUNCTION("""COMPUTED_VALUE"""),"Pollo 1kg") -> Pollo 1kg | R72: =IFERROR(__xludf.DUMMYFUNCTION("""COMPUTED_VALUE"""),"POLLO") -> POLLO | S72: =IFERROR(__xludf.DUMMYFUNCTION("""COMPUTED_VALUE"""),2.3) -> 2.3 | T72: =IFERROR(__xludf.DUMMYFUNCTION("""COMPUTED_VALUE"""),5.0) -> 5 | U72: =IFERROR(__xludf.DUMMYFUNCTION("""COMPUTED_VALUE"""),11.5) -> 11.5
B73: 46023 | C73: CONSUMIDOR FINAL | D73: Galletas de soda | E73: {=IF(D73="","",XLOOKUP(D73,DATOS!$D$6:D14000,DATOS!$C$6:C14000,0,0,1))} -> GALL21 | F73: 6 | G73: 0.5 | H73: =IF(F73="","",(F73*G73)) -> 3 | K73: =IF(I73="","",(F73*I73)) | L73: =IF(I73="",H73,H73+(K73/J73)) -> 3 | O73: =IFERROR(__xludf.DUMMYFUNCTION("""COMPUTED_VALUE"""),46024.0) -> 46024 | P73: =IFERROR(__xludf.DUMMYFUNCTION("""COMPUTED_VALUE"""),"CONSUMIDOR FINAL") -> CONSUMIDOR FINAL | Q73: =IFERROR(__xludf.DUMMYFUNCTION("""COMPUTED_VALUE"""),"CARAMELOS FRUTICAS 100UND") -> CARAMELOS FRUTICAS 100UND | R73: =IFERROR(__xludf.DUMMYFUNCTION("""COMPUTED_VALUE"""),"CARM005") -> CARM005 | S73: =IFERROR(__xludf.DUMMYFUNCTION("""COMPUTED_VALUE"""),5.0) -> 5 | T73: =IFERROR(__xludf.DUMMYFUNCTION("""COMPUTED_VALUE"""),0.1) -> 0.1 | U73: =IFERROR(__xludf.DUMMYFUNCTION("""COMPUTED_VALUE"""),0.5) -> 0.5
B74: 46023 | C74: CONSUMIDOR FINAL | D74: DIABLITO 54G | E74: {=IF(D74="","",XLOOKUP(D74,DATOS!$D$6:D14000,DATOS!$C$6:C14000,0,0,1))} -> DIABLI | F74: 1 | G74: 2 | H74: =IF(F74="","",(F74*G74)) -> 2 | K74: =IF(I74="","",(F74*I74)) | L74: =IF(I74="",H74,H74+(K74/J74)) -> 2
B75: 46023 | C75: CONSUMIDOR FINAL | D75: Huevo | E75: {=IF(D75="","",XLOOKUP(D75,DATOS!$D$6:D14000,DATOS!$C$6:C14000,0,0,1))} -> HUEVO | F75: 15 | G75: 0.3333 | H75: =IF(F75="","",(F75*G75)) -> 4.9995 | K75: =IF(I75="","",(F75*I75)) | L75: =IF(I75="",H75,H75+(K75/J75)) -> 4.9995
B76: 46023 | C76: CONSUMIDOR FINAL | D76: Harina Pan Maiz Blanca 1kg | E76: {=IF(D76="","",XLOOKUP(D76,DATOS!$D$6:D14000,DATOS!$C$6:C14000,0,0,1))} -> HP3 | F76: 1 | G76: 2.5 | H76: =IF(F76="","",(F76*G76)) -> 2.5 | K76: =IF(I76="","",(F76*I76)) | L76: =IF(I76="",H76,H76+(K76/J76)) -> 2.5
B77: 46023 | C77: CONSUMIDOR FINAL | D77: Queso duro | E77: {=IF(D77="","",XLOOKUP(D77,DATOS!$D$6:D14000,DATOS!$C$6:C14000,0,0,1))} -> QUES1 | F77: 0.25 | G77: 10 | H77: =IF(F77="","",(F77*G77)) -> 2.5 | K77: =IF(I77="","",(F77*I77)) | L77: =IF(I77="",H77,H77+(K77/J77)) -> 2.5
B78: 46023 | C78: CONSUMIDOR FINAL | D78: Harina Pan Maiz Blanca 1kg | E78: {=IF(D78="","",XLOOKUP(D78,DATOS!$D$6:D14000,DATOS!$C$6:C14000,0,0,1))} -> HP3 | F78: 1 | G78: 2.5 | H78: =IF(F78="","",(F78*G78)) -> 2.5 | K78: =IF(I78="","",(F78*I78)) | L78: =IF(I78="",H78,H78+(K78/J78)) -> 2.5
B79: 46023 | C79: CONSUMIDOR FINAL | D79: Queso duro | E79: {=IF(D79="","",XLOOKUP(D79,DATOS!$D$6:D14000,DATOS!$C$6:C14000,0,0,1))} -> QUES1 | F79: 0.25 | G79: 10 | H79: =IF(F79="","",(F79*G79)) -> 2.5 | K79: =IF(I79="","",(F79*I79)) | L79: =IF(I79="",H79,H79+(K79/J79)) -> 2.5
B80: 46023 | C80: CONSUMIDOR FINAL | D80: DIABLITO 54G | E80: {=IF(D80="","",XLOOKUP(D80,DATOS!$D$6:D14000,DATOS!$C$6:C14000,0,0,1))} -> DIABLI | F80: 2 | G80: 2 | H80: =IF(F80="","",(F80*G80)) -> 4 | K80: =IF(I80="","",(F80*I80)) | L80: =IF(I80="",H80,H80+(K80/J80)) -> 4
B81: 46023 | C81: CONSUMIDOR FINAL | D81: Huevo | E81: {=IF(D81="","",XLOOKUP(D81,DATOS!$D$6:D14000,DATOS!$C$6:C14000,0,0,1))} -> HUEVO | F81: 9 | G81: 0.3333 | H81: =IF(F81="","",(F81*G81)) -> 2.9997 | K81: =IF(I81="","",(F81*I81)) | L81: =IF(I81="",H81,H81+(K81/J81)) -> 2.9997
B82: 46023 | C82: CONSUMIDOR FINAL | D82: Café Flor de Arauca 200g | E82: {=IF(D82="","",XLOOKUP(D82,DATOS!$D$6:D14000,DATOS!$C$6:C14000,0,0,1))} -> CA3 | F82: 1 | G82: 3.5 | H82: =IF(F82="","",(F82*G82)) -> 3.5 | K82: =IF(I82="","",(F82*I82)) | L82: =IF(I82="",H82,H82+(K82/J82)) -> 3.5
B83: 46023 | C83: CONSUMIDOR FINAL | D83: adobo completo l/comadre 24x200gr | E83: {=IF(D83="","",XLOOKUP(D83,DATOS!$D$6:D14000,DATOS!$C$6:C14000,0,0,1))} -> 00011 | F83: 1 | G83: 3 | H83: =IF(F83="","",(F83*G83)) -> 3 | K83: =IF(I83="","",(F83*I83)) | L83: =IF(I83="",H83,H83+(K83/J83)) -> 3
B84: 46023 | C84: CONSUMIDOR FINAL | D84: SAL/ 1KG ENSAL | E84: {=IF(D84="","",XLOOKUP(D84,DATOS!$D$6:D14000,DATOS!$C$6:C14000,0,0,1))} -> 00035 | F84: 1 | G84: 2 | H84: =IF(F84="","",(F84*G84)) -> 2 | K84: =IF(I84="","",(F84*I84)) | L84: =IF(I84="",H84,H84+(K84/J84)) -> 2
B85: 46023 | C85: CONSUMIDOR FINAL | D85: Arroz Mary tradicional tipo 1 900g | E85: {=IF(D85="","",XLOOKUP(D85,DATOS!$D$6:D14000,DATOS!$C$6:C14000,0,0,1))} -> AR1 | F85: 1 | G85: 2.5 | H85: =IF(F85="","",(F85*G85)) -> 2.5 | K85: =IF(I85="","",(F85*I85)) | L85: =IF(I85="",H85,H85+(K85/J85)) -> 2.5
B86: 46023 | C86: CONSUMIDOR FINAL | D86: TOALLA WANITA NOCHE | E86: {=IF(D86="","",XLOOKUP(D86,DATOS!$D$6:D14000,DATOS!$C$6:C14000,0,0,1))} -> 00075 | F86: 1 | G86: 3 | H86: =IF(F86="","",(F86*G86)) -> 3 | K86: =IF(I86="","",(F86*I86)) | L86: =IF(I86="",H86,H86+(K86/J86)) -> 3
B87: 46023 | C87: CONSUMIDOR FINAL | D87: BOLSA (5KG) | E87: {=IF(D87="","",XLOOKUP(D87,DATOS!$D$6:D14000,DATOS!$C$6:C14000,0,0,1))} -> 00030 | F87: 100 | G87: 0.06 | H87: =IF(F87="","",(F87*G87)) -> 6 | K87: =IF(I87="","",(F87*I87)) | L87: =IF(I87="",H87,H87+(K87/J87)) -> 6
B88: 46023 | C88: CONSUMIDOR FINAL | D88: pasta/mry/tradicional vermi L | E88: {=IF(D88="","",XLOOKUP(D88,DATOS!$D$6:D14000,DATOS!$C$6:C14000,0,0,1))} -> 00016 | F88: 1 | G88: 3 | H88: =IF(F88="","",(F88*G88)) -> 3 | K88: =IF(I88="","",(F88*I88)) | L88: =IF(I88="",H88,H88+(K88/J88)) -> 3
B89: 46023 | C89: CONSUMIDOR FINAL | D89: Refrescos 2lt | E89: {=IF(D89="","",XLOOKUP(D89,DATOS!$D$6:D14000,DATOS!$C$6:C14000,0,0,1))} -> REF4 | F89: 1 | G89: 6 | H89: =IF(F89="","",(F89*G89)) -> 6 | K89: =IF(I89="","",(F89*I89)) | L89: =IF(I89="",H89,H89+(K89/J89)) -> 6
B90: 46023 | C90: CONSUMIDOR FINAL | D90: MARGARINA MAVESA 250GR | E90: {=IF(D90="","",XLOOKUP(D90,DATOS!$D$6:D14000,DATOS!$C$6:C14000,0,0,1))} -> MARG1 | F90: 1 | G90: 3 | H90: =IF(F90="","",(F90*G90)) -> 3 | K90: =IF(I90="","",(F90*I90)) | L90: =IF(I90="",H90,H90+(K90/J90)) -> 3
B91: 46023 | C91: CONSUMIDOR FINAL | D91: Queso duro | E91: {=IF(D91="","",XLOOKUP(D91,DATOS!$D$6:D14000,DATOS!$C$6:C14000,0,0,1))} -> QUES1 | F91: 0.25 | G91: 10 | H91: =IF(F91="","",(F91*G91)) -> 2.5 | K91: =IF(I91="","",(F91*I91)) | L91: =IF(I91="",H91,H91+(K91/J91)) -> 2.5
B92: 46023 | C92: CONSUMIDOR FINAL | D92: caramelo trululu aros 100UND | E92: {=IF(D92="","",XLOOKUP(D92,DATOS!$D$6:D14000,DATOS!$C$6:C14000,0,0,1))} -> 00010 | F92: 5 | G92: 0.1 | H92: =IF(F92="","",(F92*G92)) -> 0.5 | K92: =IF(I92="","",(F92*I92)) | L92: =IF(I92="",H92,H92+(K92/J92)) -> 0.5
B93: 46023 | C93: CONSUMIDOR FINAL | D93: Huevo | E93: {=IF(D93="","",XLOOKUP(D93,DATOS!$D$6:D14000,DATOS!$C$6:C14000,0,0,1))} -> HUEVO | F93: 6 | G93: 0.3333 | H93: =IF(F93="","",(F93*G93)) -> 1.9998 | K93: =IF(I93="","",(F93*I93)) | L93: =IF(I93="",H93,H93+(K93/J93)) -> 1.9998
B94: 46023 | C94: CONSUMIDOR FINAL | D94: Panelada 29gr | E94: {=IF(D94="","",XLOOKUP(D94,DATOS!$D$6:D14000,DATOS!$C$6:C14000,0,0,1))} -> PANEL | F94: 1 | G94: 1 | H94: =IF(F94="","",(F94*G94)) -> 1 | K94: =IF(I94="","",(F94*I94)) | L94: =IF(I94="",H94,H94+(K94/J94)) -> 1
B95: 46023 | C95: CONSUMIDOR FINAL | D95: Pollo 1kg | E95: {=IF(D95="","",XLOOKUP(D95,DATOS!$D$6:D14000,DATOS!$C$6:C14000,0,0,1))} -> POLLO | F95: 2.35 | G95: 5 | H95: =IF(F95="","",(F95*G95)) -> 11.75 | K95: =IF(I95="","",(F95*I95)) | L95: =IF(I95="",H95,H95+(K95/J95)) -> 11.75
B96: 46023 | C96: CONSUMIDOR FINAL | D96: Huevo | E96: {=IF(D96="","",XLOOKUP(D96,DATOS!$D$6:D14000,DATOS!$C$6:C14000,0,0,1))} -> HUEVO | F96: 9 | G96: 0.33333 | H96: =IF(F96="","",(F96*G96)) -> 2.99997 | K96: =IF(I96="","",(F96*I96)) | L96: =IF(I96="",H96,H96+(K96/J96)) -> 2.99997
B97: 46024 | C97: CONSUMIDOR FINAL | D97: Huevo | E97: {=IF(D97="","",XLOOKUP(D97,DATOS!$D$6:D14000,DATOS!$C$6:C14000,0,0,1))} -> HUEVO | F97: 15 | G97: 0.3333 | H97: =IF(F97="","",(F97*G97)) -> 4.9995 | K97: =IF(I97="","",(F97*I97)) | L97: =IF(I97="",H97,H97+(K97/J97)) -> 4.9995
B98: 46024 | C98: CONSUMIDOR FINAL | D98: Caramelos Bianchi | E98: {=IF(D98="","",XLOOKUP(D98,DATOS!$D$6:D14000,DATOS!$C$6:C14000,0,0,1))} -> CARM2 | F98: 5 | G98: 0.1 | H98: =IF(F98="","",(F98*G98)) -> 0.5 | K98: =IF(I98="","",(F98*I98)) | L98: =IF(I98="",H98,H98+(K98/J98)) -> 0.5
B99: 46024 | C99: CONSUMIDOR FINAL | D99: CARAMELOS FRUTICAS 100UND | E99: {=IF(D99="","",XLOOKUP(D99,DATOS!$D$6:D14000,DATOS!$C$6:C14000,0,0,1))} -> CARM005 | F99: 5 | G99: 0.1 | H99: =IF(F99="","",(F99*G99)) -> 0.5 | K99: =IF(I99="","",(F99*I99)) | L99: =IF(I99="",H99,H99+(K99/J99)) -> 0.5
B100: 46024 | C100: CONSUMIDOR FINAL | D100: Huevo | E100: {=IF(D100="","",XLOOKUP(D100,DATOS!$D$6:D14000,DATOS!$C$6:C14000,0,0,1))} -> HUEVO | F100: 12 | G100: 0.3333 | H100: =IF(F100="","",(F100*G100)) -> 3.9996 | K100: =IF(I100="","",(F100*I100)) | L100: =IF(I100="",H100,H100+(K100/J100)) -> 3.9996
...

Sheet COMPRAS
C1: BODEGA3 | Y1: BODEGA3
G2: TOTALES | R2: =SUM(R5:R2624) -> 833.11828 | S2: =SUM(S5:S2624) -> 21.9 | X2: FECHA | Y2: PROVEEDOR | Z2: No. COMPROB | AC2: TOTALES | AH2: =SUM(AH5:AH2624) -> 229321.62 | AM2: =SUM(AM5:AM2624) -> 0 | AN2: =SUM(AN5:AN2624) -> 744.18828
G3: =SUM($G$5:$G2624) -> 2486 | I3: COMPRAS EN BOLIVARES | O3: COMPRA EN DOLARES | X3: 46028 | Y3: INVERSIONES DOBLE PICA, C.A. | Z3: 237136 | AC3: =SUM($AC$5:$AC2624) -> 1746 | AD3: COMPRAS EN BOLIVARES | AJ3: COMPRA EN DOLARES
B4: FECHA | C4: PROVEEDOR | D4: No. COMPROB | E4: PRODUCTO | F4: COD/PROD | G4: CANT | H4: CANT/BTO | I4: PRECIO/UNIT | J4: (I/E) | K4: PREC/UNIT/IVA | L4: MONTO/TOT/FACT | M4: TASA | N4: PRECIO/UNIT/$ | O4: PRECIO/UNIT/$ | P4: (I/E) | Q4: PREC/UNIT/IVA | R4: MONTO/TOT/FACT/$ | S4: FLETE | T4: PREC/UNIT/IVA/FLETE | V4: PROB | X4: FECHA | Y4: PROVEEDOR | Z4: No. COMPROB | AA4: PRODUCTO | AB4: COD/PROD | AC4: CANT | AD4: CANT/BTO | AE4: PRECIO/UNIT | AF4: (I/E) | AG4: PREC/UNIT/IVA | AH4: MONTO/TOT/FACT | AI4: TASA | AJ4: PRECIO/UNIT/$ | AK4: PRECIO/UNIT/$ | AL4: (I/E) | AM4: PREC/UNIT/IVA | AN4: MONTO/TOT/FACT/$ | AO4: FLETE | AP4: PREC/UNIT/IVA/FLETE
B5: 46028 | C5: INVERSIONES DOBLE PICA, C.A. | D5: 237136 | E5: ATUN PEÑERO OLIVA VERDE | F5: {=IF(E5="","",XLOOKUP(E5,DATOS!$D$6:$D2624,DATOS!$C$6:$C2624,0,0,1))} -> 00116 | G5: 12 | H5: 12 | I5: =8505.08/G5 -> 708.75667 | J5: E | K5: =IF(I5="","", IF(J5="E",I5,I5*1.16)) -> 708.75667 | L5: =IF(I5="","",G5*K5) -> 8505.08 | M5: 308.15 | N5: =IF(M5="","",K5/M5) -> 2.3000379 | Q5: =IF(O5="","", IF(P5="E",O5,O5*1.16)) | R5: =IF(G5="","",(G5*Q5))+IF(G5="","",(G5*N5)) -> 27.600454 | S5: {=XLOOKUP(E5,PESOS!$B$2:$B2624,PESOS!$F$2:$F2624,"")} | T5: =IF(B5="","",N5+Q5+S5) -> 2.3000379 | V5: =IF(M5="","",(L5/M5)) -> 27.600454 | X5: =IFERROR(__xludf.DUMMYFUNCTION("FILTER(B5:T2624,B5:B2624=X3,C5:C2624=Y3,D5:D2624=Z3)"),46028.0) -> 46028 | Y5: =IFERROR(__xludf.DUMMYFUNCTION("""COMPUTED_VALUE"""),"INVERSIONES DOBLE PICA, C.A.") -> INVERSIONES DOBLE PICA, C.A. | Z5: =IFERROR(__xludf.DUMMYFUNCTION("""COMPUTED_VALUE"""),237136.0) -> 237136 | AA5: =IFERROR(__xludf.DUMMYFUNCTION("""COMPUTED_VALUE"""),"ATUN PEÑERO OLIVA VERDE") -> ATUN PEÑERO OLIVA VERDE | AB5: =IFERROR(__xludf.DUMMYFUNCTION("""COMPUTED_VALUE"""),"00116") -> 00116 | AC5: =IFERROR(__xludf.DUMMYFUNCTION("""COMPUTED_VALUE"""),12.0) -> 12 | AD5: =IFERROR(__xludf.DUMMYFUNCTION("""COMPUTED_VALUE"""),12.0) -> 12 | AE5: =IFERROR(__xludf.DUMMYFUNCTION("""COMPUTED_VALUE"""),708.7566666666667) -> 708.75667 | AF5: =IFERROR(__xludf.DUMMYFUNCTION("""COMPUTED_VALUE"""),"E") -> E | AG5: =IFERROR(__xludf.DUMMYFUNCTION("""COMPUTED_VALUE"""),708.7566666666667) -> 708.75667 | AH5: =IFERROR(__xludf.DUMMYFUNCTION("""COMPUTED_VALUE"""),8505.08) -> 8505.08 | AI5: =IFERROR(__xludf.DUMMYFUNCTION("""COMPUTED_VALUE"""),308.15) -> 308.15 | AJ5: =IFERROR(__xludf.DUMMYFUNCTION("""COMPUTED_VALUE"""),2.300037860349397) -> 2.3000379 | AM5: =IFERROR(__xludf.DUMMYFUNCTION("""COMPUTED_VALUE"""),"") | AN5: =IFERROR(__xludf.DUMMYFUNCTION("""COMPUTED_VALUE"""),27.600454324192768) -> 27.600454 | AO5: =IFERROR(__xludf.DUMMYFUNCTION("""COMPUTED_VALUE"""),"") | AP5: =IFERROR(__xludf.DUMMYFUNCTION("""COMPUTED_VALUE"""),2.300037860349397) -> 2.3000379
B6: 46028 | C6: INVERSIONES DOBLE PICA, C.A. | D6: 237136 | E6: Pañal Baby finger XG | F6: {=IF(E6="","",XLOOKUP(E6,DATOS!$D$6:$D2624,DATOS!$C$6:$C2624,0,0,1))} -> PAÑL1 | G6: 192 | H6: 192 | I6: =17745.48/G6 -> 92.424375 | J6: E | K6: =IF(I6="","", IF(J6="E",I6,I6*1.16)) -> 92.424375 | L6: =IF(I6="","",G6*K6) -> 17745.48 | M6: 308.15 | N6: =IF(M6="","",K6/M6) -> 0.29993307 | Q6: =IF(O6="","", IF(P6="E",O6,O6*1.16)) | R6: =IF(G6="","",(G6*Q6))+IF(G6="","",(G6*N6)) -> 57.587149 | S6: {=XLOOKUP(E6,PESOS!$B$2:$B2624,PESOS!$F$2:$F2624,"")} | T6: =IF(B6="","",N6+Q6+S6) -> 0.29993307 | V6: =IF(M6="","",(L6/M6)) -> 57.587149 | X6: =IFERROR(__xludf.DUMMYFUNCTION("""COMPUTED_VALUE"""),46028.0) -> 46028 | Y6: =IFERROR(__xludf.DUMMYFUNCTION("""COMPUTED_VALUE"""),"INVERSIONES DOBLE PICA, C.A.") -> INVERSIONES DOBLE PICA, C.A. | Z6: =IFERROR(__xludf.DUMMYFUNCTION("""COMPUTED_VALUE"""),237136.0) -> 237136 | AA6: =IFERROR(__xludf.DUMMYFUNCTION("""COMPUTED_VALUE"""),"Pañal Baby finger XG") -> Pañal Baby finger XG | AB6: =IFERROR(__xludf.DUMMYFUNCTION("""COMPUTED_VALUE"""),"PAÑL1") -> PAÑL1 | AC6: =IFERROR(__xludf.DUMMYFUNCTION("""COMPUTED_VALUE"""),192.0) -> 192 | AD6: =IFERROR(__xludf.DUMMYFUNCTION("""COMPUTED_VALUE"""),192.0) -> 192 | AE6: =IFERROR(__xludf.DUMMYFUNCTION("""COMPUTED_VALUE"""),92.424375) -> 92.424375 | AF6: =IFERROR(__xludf.DUMMYFUNCTION("""COMPUTED_VALUE"""),"E") -> E | AG6: =IFERROR(__xludf.DUMMYFUNCTION("""COMPUTED_VALUE"""),92.424375) -> 92.424375 | AH6: =IFERROR(__xludf.DUMMYFUNCTION("""COMPUTED_VALUE"""),17745.48) -> 17745.48 | AI6: =IFERROR(__xludf.DUMMYFUNCTION("""COMPUTED_VALUE"""),308.15) -> 308.15 | AJ6: =IFERROR(__xludf.DUMMYFUNCTION("""COMPUTED_VALUE"""),0.29993306831088756) -> 0.29993307 | AM6: =IFERROR(__xludf.DUMMYFUNCTION("""COMPUTED_VALUE"""),"") | AN6: =IFERROR(__xludf.DUMMYFUNCTION("""COMPUTED_VALUE"""),57.58714911569041) -> 57.587149 | AO6: =IFERROR(__xludf.DUMMYFUNCTION("""COMPUTED_VALUE"""),"") | AP6: =IFERROR(__xludf.DUMMYFUNCTION("""COMPUTED_VALUE"""),0.29993306831088756) -> 0.29993307
B7: 46028 | C7: INVERSIONES DOBLE PICA, C.A. | D7: 237136 | E7: CAFE AMANECER 500GR | F7: {=IF(E7="","",XLOOKUP(E7,DATOS!$D$6:$D2624,DATOS!$C$6:$C2624,0,0,1))} -> 00120 | G7: 10 | H7: 10 | I7: =19382.95/G7 -> 1938.295 | J7: E | K7: =IF(I7="","", IF(J7="E",I7,I7*1.16)) -> 1938.295 | L7: =IF(I7="","",G7*K7) -> 19382.95 | M7: 308.15 | N7: =IF(M7="","",K7/M7) -> 6.2901022 | Q7: =IF(O7="","", IF(P7="E",O7,O7*1.16)) | R7: =IF(G7="","",(G7*Q7))+IF(G7="","",(G7*N7)) -> 62.901022 | S7: {=XLOOKUP(E7,PESOS!$B$2:$B2624,PESOS!$F$2:$F2624,"")} | T7: =IF(B7="","",N7+Q7+S7) -> 6.2901022 | V7: =IF(M7="","",(L7/M7)) -> 62.901022 | X7: =IFERROR(__xludf.DUMMYFUNCTION("""COMPUTED_VALUE"""),46028.0) -> 46028 | Y7: =IFERROR(__xludf.DUMMYFUNCTION("""COMPUTED_VALUE"""),"INVERSIONES DOBLE PICA, C.A.") -> INVERSIONES DOBLE PICA, C.A. | Z7: =IFERROR(__xludf.DUMMYFUNCTION("""COMPUTED_VALUE"""),237136.0) -> 237136 | AA7: =IFERROR(__xludf.DUMMYFUNCTION("""COMPUTED_VALUE"""),"CAFE AMANECER 500GR") -> CAFE AMANECER 500GR | AB7: =IFERROR(__xludf.DUMMYFUNCTION("""COMPUTED_VALUE"""),"00120") -> 00120 | AC7: =IFERROR(__xludf.DUMMYFUNCTION("""COMPUTED_VALUE"""),10.0) -> 10 | AD7: =IFERROR(__xludf.DUMMYFUNCTION("""COMPUTED_VALUE"""),10.0) -> 10 | AE7: =IFERROR(__xludf.DUMMYFUNCTION("""COMPUTED_VALUE"""),1938.295) -> 1938.295 | AF7: =IFERROR(__xludf.DUMMYFUNCTION("""COMPUTED_VALUE"""),"E") -> E | AG7: =IFERROR(__xludf.DUMMYFUNCTION("""COMPUTED_VALUE"""),1938.295) -> 1938.295 | AH7: =IFERROR(__xludf.DUMMYFUNCTION("""COMPUTED_VALUE"""),19382.95) -> 19382.95 | AI7: =IFERROR(__xludf.DUMMYFUNCTION("""COMPUTED_VALUE"""),308.15) -> 308.15 | AJ7: =IFERROR(__xludf.DUMMYFUNCTION("""COMPUTED_VALUE"""),6.290102222943372) -> 6.2901022 | AM7: =IFERROR(__xludf.DUMMYFUNCTION("""COMPUTED_VALUE"""),"") | AN7: =IFERROR(__xludf.DUMMYFUNCTION("""COMPUTED_VALUE"""),62.90102222943372) -> 62.901022 | AO7: =IFERROR(__xludf.DUMMYFUNCTION("""COMPUTED_VALUE"""),"") | AP7: =IFERROR(__xludf.DUMMYFUNCTION("""COMPUTED_VALUE"""),6.290102222943372) -> 6.2901022
B8: 46028 | C8: INVERSIONES DOBLE PICA, C.A. | D8: 237136 | E8: Café Amanecer 200g | F8: {=IF(E8="","",XLOOKUP(E8,DATOS!$D$6:$D2624,DATOS!$C$6:$C2624,0,0,1))} -> CA1 | G8: 24 | H8: 24 | I8: =18366.04/G8 -> 765.25167 | J8: E | K8: =IF(I8="","", IF(J8="E",I8,I8*1.16)) -> 765.25167 | L8: =IF(I8="","",G8*K8) -> 18366.04 | M8: 308.15 | N8: =IF(M8="","",K8/M8) -> 2.4833739 | Q8: =IF(O8="","", IF(P8="E",O8,O8*1.16)) | R8: =IF(G8="","",(G8*Q8))+IF(G8="","",(G8*N8)) -> 59.600974 | S8: {=XLOOKUP(E8,PESOS!$B$2:$B2624,PESOS!$F$2:$F2624,"")} | T8: =IF(B8="","",N8+Q8+S8) -> 2.4833739 | V8: =IF(M8="","",(L8/M8)) -> 59.600974 | X8: =IFERROR(__xludf.DUMMYFUNCTION("""COMPUTED_VALUE"""),46028.0) -> 46028 | Y8: =IFERROR(__xludf.DUMMYFUNCTION("""COMPUTED_VALUE"""),"INVERSIONES DOBLE PICA, C.A.") -> INVERSIONES DOBLE PICA, C.A. | Z8: =IFERROR(__xludf.DUMMYFUNCTION("""COMPUTED_VALUE"""),237136.0) -> 237136 | AA8: =IFERROR(__xludf.DUMMYFUNCTION("""COMPUTED_VALUE"""),"Café Amanecer 200g") -> Café Amanecer 200g | AB8: =IFERROR(__xludf.DUMMYFUNCTION("""COMPUTED_VALUE"""),"CA1") -> CA1 | AC8: =IFERROR(__xludf.DUMMYFUNCTION("""COMPUTED_VALUE"""),24.0) -> 24 | AD8: =IFERROR(__xludf.DUMMYFUNCTION("""COMPUTED_VALUE"""),24.0) -> 24 | AE8: =IFERROR(__xludf.DUMMYFUNCTION("""COMPUTED_VALUE"""),765.2516666666667) -> 765.25167 | AF8: =IFERROR(__xludf.DUMMYFUNCTION("""COMPUTED_VALUE"""),"E") -> E | AG8: =IFERROR(__xludf.DUMMYFUNCTION("""COMPUTED_VALUE"""),765.2516666666667) -> 765.25167 | AH8: =IFERROR(__xludf.DUMMYFUNCTION("""COMPUTED_VALUE"""),18366.04) -> 18366.04 | AI8: =IFERROR(__xludf.DUMMYFUNCTION("""COMPUTED_VALUE"""),308.15) -> 308.15 | AJ8: =IFERROR(__xludf.DUMMYFUNCTION("""COMPUTED_VALUE"""),2.4833738979934017) -> 2.4833739 | AM8: =IFERROR(__xludf.DUMMYFUNCTION("""COMPUTED_VALUE"""),"") | AN8: =IFERROR(__xludf.DUMMYFUNCTION("""COMPUTED_VALUE"""),59.60097355184164) -> 59.600974 | AO8: =IFERROR(__xludf.DUMMYFUNCTION("""COMPUTED_VALUE"""),"") | AP8: =IFERROR(__xludf.DUMMYFUNCTION("""COMPUTED_VALUE"""),2.4833738979934017) -> 2.4833739
B9: 46028 | C9: INVERSIONES DOBLE PICA, C.A. | D9: 237136 | E9: Belmont | F9: {=IF(E9="","",XLOOKUP(E9,DATOS!$D$6:$D2624,DATOS!$C$6:$C2624,0,0,1))} -> BELM | G9: 1000 | H9: 200 | I9: =39906.07/G9 -> 39.90607 | J9: E | K9: =IF(I9="","", IF(J9="E",I9,I9*1.16)) -> 39.90607 | L9: =IF(I9="","",G9*K9) -> 39906.07 | M9: 308.15 | N9: =IF(M9="","",K9/M9) -> 0.12950209 | Q9: =IF(O9="","", IF(P9="E",O9,O9*1.16)) | R9: =IF(G9="","",(G9*Q9))+IF(G9="","",(G9*N9)) -> 129.50209 | S9: {=XLOOKUP(E9,PESOS!$B$2:$B2624,PESOS!$F$2:$F2624,"")} | T9: =IF(B9="","",N9+Q9+S9) -> 0.12950209 | V9: =IF(M9="","",(L9/M9)) -> 129.50209 | X9: =IFERROR(__xludf.DUMMYFUNCTION("""COMPUTED_VALUE"""),46028.0) -> 46028 | Y9: =IFERROR(__xludf.DUMMYFUNCTION("""COMPUTED_VALUE"""),"INVERSIONES DOBLE PICA, C.A.") -> INVERSIONES DOBLE PICA, C.A. | Z9: =IFERROR(__xludf.DUMMYFUNCTION("""COMPUTED_VALUE"""),237136.0) -> 237136 | AA9: =IFERROR(__xludf.DUMMYFUNCTION("""COMPUTED_VALUE"""),"Belmont") -> Belmont | AB9: =IFERROR(__xludf.DUMMYFUNCTION("""COMPUTED_VALUE"""),"BELM") -> BELM | AC9: =IFERROR(__xludf.DUMMYFUNCTION("""COMPUTED_VALUE"""),1000.0) -> 1000 | AD9: =IFERROR(__xludf.DUMMYFUNCTION("""COMPUTED_VALUE"""),200.0) -> 200 | AE9: =IFERROR(__xludf.DUMMYFUNCTION("""COMPUTED_VALUE"""),39.90607) -> 39.90607 | AF9: =IFERROR(__xludf.DUMMYFUNCTION("""COMPUTED_VALUE"""),"E") -> E | AG9: =IFERROR(__xludf.DUMMYFUNCTION("""COMPUTED_VALUE"""),39.90607) -> 39.90607 | AH9: =IFERROR(__xludf.DUMMYFUNCTION("""COMPUTED_VALUE"""),39906.07) -> 39906.07 | AI9: =IFERROR(__xludf.DUMMYFUNCTION("""COMPUTED_VALUE"""),308.15) -> 308.15 | AJ9: =IFERROR(__xludf.DUMMYFUNCTION("""COMPUTED_VALUE"""),0.12950209313645952) -> 0.12950209 | AM9: =IFERROR(__xludf.DUMMYFUNCTION("""COMPUTED_VALUE"""),"") | AN9: =IFERROR(__xludf.DUMMYFUNCTION("""COMPUTED_VALUE"""),129.50209313645954) -> 129.50209 | AO9: =IFERROR(__xludf.DUMMYFUNCTION("""COMPUTED_VALUE"""),"") | AP9: =IFERROR(__xludf.DUMMYFUNCTION("""COMPUTED_VALUE"""),0.12950209313645952) -> 0.12950209
B10: 46028 | C10: INVERSIONES DOBLE PICA, C.A. | D10: 237136 | E10: Cubitos | F10: {=IF(E10="","",XLOOKUP(E10,DATOS!$D$6:$D2624,DATOS!$C$6:$C2624,0,0,1))} -> CUBITO1 | G10: 250 | H10: 250 | I10: =12087.11/G10 -> 48.34844 | J10: G | K10: =IF(I10="","", IF(J10="E",I10,I10*1.16)) -> 56.08419 | L10: =IF(I10="","",G10*K10) -> 14021.048 | M10: 308.15 | N10: =IF(M10="","",K10/M10) -> 0.18200289 | Q10: =IF(O10="","", IF(P10="E",O10,O10*1.16)) | R10: =IF(G10="","",(G10*Q10))+IF(G10="","",(G10*N10)) -> 45.500722 | S10: {=XLOOKUP(E10,PESOS!$B$2:$B2624,PESOS!$F$2:$F2624,"")} | T10: =IF(B10="","",N10+Q10+S10) -> 0.18200289 | V10: =IF(M10="","",(L10/M10)) -> 45.500722 | X10: =IFERROR(__xludf.DUMMYFUNCTION("""COMPUTED_VALUE"""),46028.0) -> 46028 | Y10: =IFERROR(__xludf.DUMMYFUNCTION("""COMPUTED_VALUE"""),"INVERSIONES DOBLE PICA, C.A.") -> INVERSIONES DOBLE PICA, C.A. | Z10: =IFERROR(__xludf.DUMMYFUNCTION("""COMPUTED_VALUE"""),237136.0) -> 237136 | AA10: =IFERROR(__xludf.DUMMYFUNCTION("""COMPUTED_VALUE"""),"Cubitos") -> Cubitos | AB10: =IFERROR(__xludf.DUMMYFUNCTION("""COMPUTED_VALUE"""),"CUBITO1") -> CUBITO1 | AC10: =IFERROR(__xludf.DUMMYFUNCTION("""COMPUTED_VALUE"""),250.0) -> 250 | AD10: =IFERROR(__xludf.DUMMYFUNCTION("""COMPUTED_VALUE"""),250.0) -> 250 | AE10: =IFERROR(__xludf.DUMMYFUNCTION("""COMPUTED_VALUE"""),48.348440000000004) -> 48.34844 | AF10: =IFERROR(__xludf.DUMMYFUNCTION("""COMPUTED_VALUE"""),"G") -> G | AG10: =IFERROR(__xludf.DUMMYFUNCTION("""COMPUTED_VALUE"""),56.0841904) -> 56.08419 | AH10: =IFERROR(__xludf.DUMMYFUNCTION("""COMPUTED_VALUE"""),14021.0476) -> 14021.048 | AI10: =IFERROR(__xludf.DUMMYFUNCTION("""COMPUTED_VALUE"""),308.15) -> 308.15 | AJ10: =IFERROR(__xludf.DUMMYFUNCTION("""COMPUTED_VALUE"""),0.18200288950186597) -> 0.18200289 | AM10: =IFERROR(__xludf.DUMMYFUNCTION("""COMPUTED_VALUE"""),"") | AN10: =IFERROR(__xludf.DUMMYFUNCTION("""COMPUTED_VALUE"""),45.500722375466495) -> 45.500722 | AO10: =IFERROR(__xludf.DUMMYFUNCTION("""COMPUTED_VALUE"""),"") | AP10: =IFERROR(__xludf.DUMMYFUNCTION("""COMPUTED_VALUE"""),0.18200288950186597) -> 0.18200289
B11: 46028 | C11: INVERSIONES DOBLE PICA, C.A. | D11: 237136 | E11: alive/detergente c/suavisante 1kg | F11: {=IF(E11="","",XLOOKUP(E11,DATOS!$D$6:$D2624,DATOS!$C$6:$C2624,0,0,1))} -> 00002 | G11: 24 | H11: 12 | I11: =17958/G11 -> 748.25 | J11: G | K11: =IF(I11="","", IF(J11="E",I11,I11*1.16)) -> 867.97 | L11: =IF(I11="","",G11*K11) -> 20831.28 | M11: 308.15 | N11: =IF(M11="","",K11/M11) -> 2.8167126 | Q11: =IF(O11="","", IF(P11="E",O11,O11*1.16)) | R11: =IF(G11="","",(G11*Q11))+IF(G11="","",(G11*N11)) -> 67.601103 | S11: {=XLOOKUP(E11,PESOS!$B$2:$B2624,PESOS!$F$2:$F2624,"")} | T11: =IF(B11="","",N11+Q11+S11) -> 2.8167126 | V11: =IF(M11="","",(L11/M11)) -> 67.601103 | X11: =IFERROR(__xludf.DUMMYFUNCTION("""COMPUTED_VALUE"""),46028.0) -> 46028 | Y11: =IFERROR(__xludf.DUMMYFUNCTION("""COMPUTED_VALUE"""),"INVERSIONES DOBLE PICA, C.A.") -> INVERSIONES DOBLE PICA, C.A. | Z11: =IFERROR(__xludf.DUMMYFUNCTION("""COMPUTED_VALUE"""),237136.0) -> 237136 | AA11: =IFERROR(__xludf.DUMMYFUNCTION("""COMPUTED_VALUE"""),"alive/detergente c/suavisante 1kg") -> alive/detergente c/suavisante 1kg | AB11: =IFERROR(__xludf.DUMMYFUNCTION("""COMPUTED_VALUE"""),"00002 ") -> 00002 | AC11: =IFERROR(__xludf.DUMMYFUNCTION("""COMPUTED_VALUE"""),24.0) -> 24 | AD11: =IFERROR(__xludf.DUMMYFUNCTION("""COMPUTED_VALUE"""),12.0) -> 12 | AE11: =IFERROR(__xludf.DUMMYFUNCTION("""COMPUTED_VALUE"""),748.25) -> 748.25 | AF11: =IFERROR(__xludf.DUMMYFUNCTION("""COMPUTED_VALUE"""),"G") -> G | AG11: =IFERROR(__xludf.DUMMYFUNCTION("""COMPUTED_VALUE"""),867.9699999999999) -> 867.97 | AH11: =IFERROR(__xludf.DUMMYFUNCTION("""COMPUTED_VALUE"""),20831.28) -> 20831.28 | AI11: =IFERROR(__xludf.DUMMYFUNCTION("""COMPUTED_VALUE"""),308.15) -> 308.15 | AJ11: =IFERROR(__xludf.DUMMYFUNCTION("""COMPUTED_VALUE"""),2.816712639948077) -> 2.8167126 | AM11: =IFERROR(__xludf.DUMMYFUNCTION("""COMPUTED_VALUE"""),"") | AN11: =IFERROR(__xludf.DUMMYFUNCTION("""COMPUTED_VALUE"""),67.60110335875385) -> 67.601103 | AO11: =IFERROR(__xludf.DUMMYFUNCTION("""COMPUTED_VALUE"""),"") | AP11: =IFERROR(__xludf.DUMMYFUNCTION("""COMPUTED_VALUE"""),2.816712639948077) -> 2.8167126
B12: 46028 | C12: INVERSIONES DOBLE PICA, C.A. | D12: 237136 | E12: DETERGENTE ALIVE 500GR | F12: {=IF(E12="","",XLOOKUP(E12,DATOS!$D$6:$D2624,DATOS!$C$6:$C2624,0,0,1))} -> 00098 | G12: 48 | H12: 24 | I12: =17958/G12 -> 374.125 | J12: G | K12: =IF(I12="","", IF(J12="E",I12,I12*1.16)) -> 433.985 | L12: =IF(I12="","",G12*K12) -> 20831.28 | M12: 308.15 | N12: =IF(M12="","",K12/M12) -> 1.4083563 | Q12: =IF(O12="","", IF(P12="E",O12,O12*1.16)) | R12: =IF(G12="","",(G12*Q12))+IF(G12="","",(G12*N12)) -> 67.601103 | S12: {=XLOOKUP(E12,PESOS!$B$2:$B2624,PESOS!$F$2:$F2624,"")} | T12: =IF(B12="","",N12+Q12+S12) -> 1.4083563 | V12: =IF(M12="","",(L12/M12)) -> 67.601103 | X12: =IFERROR(__xludf.DUMMYFUNCTION("""COMPUTED_VALUE"""),46028.0) -> 46028 | Y12: =IFERROR(__xludf.DUMMYFUNCTION("""COMPUTED_VALUE"""),"INVERSIONES DOBLE PICA, C.A.") -> INVERSIONES DOBLE PICA, C.A. | Z12: =IFERROR(__xludf.DUMMYFUNCTION("""COMPUTED_VALUE"""),237136.0) -> 237136 | AA12: =IFERROR(__xludf.DUMMYFUNCTION("""COMPUTED_VALUE"""),"DETERGENTE ALIVE 500GR") -> DETERGENTE ALIVE 500GR | AB12: =IFERROR(__xludf.DUMMYFUNCTION("""COMPUTED_VALUE"""),"00098") -> 00098 | AC12: =IFERROR(__xludf.DUMMYFUNCTION("""COMPUTED_VALUE"""),48.0) -> 48 | AD12: =IFERROR(__xludf.DUMMYFUNCTION("""COMPUTED_VALUE"""),24.0) -> 24 | AE12: =IFERROR(__xludf.DUMMYFUNCTION("""COMPUTED_VALUE"""),374.125) -> 374.125 | AF12: =IFERROR(__xludf.DUMMYFUNCTION("""COMPUTED_VALUE"""),"G") -> G | AG12: =IFERROR(__xludf.DUMMYFUNCTION("""COMPUTED_VALUE"""),433.98499999999996) -> 433.985 | AH12: =IFERROR(__xludf.DUMMYFUNCTION("""COMPUTED_VALUE"""),20831.28) -> 20831.28 | AI12: =IFERROR(__xludf.DUMMYFUNCTION("""COMPUTED_VALUE"""),308.15) -> 308.15 | AJ12: =IFERROR(__xludf.DUMMYFUNCTION("""COMPUTED_VALUE"""),1.4083563199740385) -> 1.4083563 | AM12: =IFERROR(__xludf.DUMMYFUNCTION("""COMPUTED_VALUE"""),"") | AN12: =IFERROR(__xludf.DUMMYFUNCTION("""COMPUTED_VALUE"""),67.60110335875385) -> 67.601103 | AO12: =IFERROR(__xludf.DUMMYFUNCTION("""COMPUTED_VALUE"""),"") | AP12: =IFERROR(__xludf.DUMMYFUNCTION("""COMPUTED_VALUE"""),1.4083563199740385) -> 1.4083563
B13: 46028 | C13: INVERSIONES DOBLE PICA, C.A. | D13: 237136 | E13: ACEITE LA PAMPA 700ML | F13: {=IF(E13="","",XLOOKUP(E13,DATOS!$D$6:$D2624,DATOS!$C$6:$C2624,0,0,1))} -> 00084 | G13: 40 | H13: 10 | I13: =13152.06/G13 -> 328.8015 | J13: E | K13: =IF(I13="","", IF(J13="E",I13,I13*1.16)) -> 328.8015 | L13: =IF(I13="","",G13*K13) -> 13152.06 | M13: 308.15 | N13: =IF(M13="","",K13/M13) -> 1.0670177 | Q13: =IF(O13="","", IF(P13="E",O13,O13*1.16)) | R13: =IF(G13="","",(G13*Q13))+IF(G13="","",(G13*N13)) -> 42.680707 | S13: {=XLOOKUP(E13,PESOS!$B$2:$B2624,PESOS!$F$2:$F2624,"")} | T13: =IF(B13="","",N13+Q13+S13) -> 1.0670177 | V13: =IF(M13="","",(L13/M13)) -> 42.680707 | X13: =IFERROR(__xludf.DUMMYFUNCTION("""COMPUTED_VALUE"""),46028.0) -> 46028 | Y13: =IFERROR(__xludf.DUMMYFUNCTION("""COMPUTED_VALUE"""),"INVERSIONES DOBLE PICA, C.A.") -> INVERSIONES DOBLE PICA, C.A. | Z13: =IFERROR(__xludf.DUMMYFUNCTION("""COMPUTED_VALUE"""),237136.0) -> 237136 | AA13: =IFERROR(__xludf.DUMMYFUNCTION("""COMPUTED_VALUE"""),"ACEITE LA PAMPA 700ML ") -> ACEITE LA PAMPA 700ML | AB13: =IFERROR(__xludf.DUMMYFUNCTION("""COMPUTED_VALUE"""),"00084") -> 00084 | AC13: =IFERROR(__xludf.DUMMYFUNCTION("""COMPUTED_VALUE"""),40.0) -> 40 | AD13: =IFERROR(__xludf.DUMMYFUNCTION("""COMPUTED_VALUE"""),10.0) -> 10 | AE13: =IFERROR(__xludf.DUMMYFUNCTION("""COMPUTED_VALUE"""),328.8015) -> 328.8015 | AF13: =IFERROR(__xludf.DUMMYFUNCTION("""COMPUTED_VALUE"""),"E") -> E | AG13: =IFERROR(__xludf.DUMMYFUNCTION("""COMPUTED_VALUE"""),328.8015) -> 328.8015 | AH13: =IFERROR(__xludf.DUMMYFUNCTION("""COMPUTED_VALUE"""),13152.06) -> 13152.06 | AI13: =IFERROR(__xludf.DUMMYFUNCTION("""COMPUTED_VALUE"""),308.15) -> 308.15 | AJ13: =IFERROR(__xludf.DUMMYFUNCTION("""COMPUTED_VALUE"""),1.0670176861917897) -> 1.0670177 | AM13: =IFERROR(__xludf.DUMMYFUNCTION("""COMPUTED_VALUE"""),"") | AN13: =IFERROR(__xludf.DUMMYFUNCTION("""COMPUTED_VALUE"""),42.68070744767159) -> 42.680707 | AO13: =IFERROR(__xludf.DUMMYFUNCTION("""COMPUTED_VALUE"""),"") | AP13: =IFERROR(__xludf.DUMMYFUNCTION("""COMPUTED_VALUE"""),1.0670176861917897) -> 1.0670177
B14: 46028 | C14: INVERSIONES DOBLE PICA, C.A. | D14: 237136 | E14: MARGARINA MAVESA 250GR | F14: {=IF(E14="","",XLOOKUP(E14,DATOS!$D$6:$D2624,DATOS!$C$6:$C2624,0,0,1))} -> MARG1 | G14: 24 | H14: 24 | I14: =10779.26/G14 -> 449.13583 | J14: E | K14: =IF(I14="","", IF(J14="E",I14,I14*1.16)) -> 449.13583 | L14: =IF(I14="","",G14*K14) -> 10779.26 | M14: 308.15 | N14: =IF(M14="","",K14/M14) -> 1.4575234 | Q14: =IF(O14="","", IF(P14="E",O14,O14*1.16)) | R14: =IF(G14="","",(G14*Q14))+IF(G14="","",(G14*N14)) -> 34.980561 | S14: {=XLOOKUP(E14,PESOS!$B$2:$B2624,PESOS!$F$2:$F2624,"")} -> 6.9 | T14: =IF(B14="","",N14+Q14+S14) -> 8.3575234 | V14: =IF(M14="","",(L14/M14)) -> 34.980561 | X14: =IFERROR(__xludf.DUMMYFUNCTION("""COMPUTED_VALUE"""),46028.0) -> 46028 | Y14: =IFERROR(__xludf.DUMMYFUNCTION("""COMPUTED_VALUE"""),"INVERSIONES DOBLE PICA, C.A.") -> INVERSIONES DOBLE PICA, C.A. | Z14: =IFERROR(__xludf.DUMMYFUNCTION("""COMPUTED_VALUE"""),237136.0) -> 237136 | AA14: =IFERROR(__xludf.DUMMYFUNCTION("""COMPUTED_VALUE"""),"MARGARINA MAVESA 250GR") -> MARGARINA MAVESA 250GR | AB14: =IFERROR(__xludf.DUMMYFUNCTION("""COMPUTED_VALUE"""),"MARG1") -> MARG1 | AC14: =IFERROR(__xludf.DUMMYFUNCTION("""COMPUTED_VALUE"""),24.0) -> 24 | AD14: =IFERROR(__xludf.DUMMYFUNCTION("""COMPUTED_VALUE"""),24.0) -> 24 | AE14: =IFERROR(__xludf.DUMMYFUNCTION("""COMPUTED_VALUE"""),449.1358333333333) -> 449.13583 | AF14: =IFERROR(__xludf.DUMMYFUNCTION("""COMPUTED_VALUE"""),"E") -> E | AG14: =IFERROR(__xludf.DUMMYFUNCTION("""COMPUTED_VALUE"""),449.1358333333333) -> 449.13583 | AH14: =IFERROR(__xludf.DUMMYFUNCTION("""COMPUTED_VALUE"""),10779.26) -> 10779.26 | AI14: =IFERROR(__xludf.DUMMYFUNCTION("""COMPUTED_VALUE"""),308.15) -> 308.15 | AJ14: =IFERROR(__xludf.DUMMYFUNCTION("""COMPUTED_VALUE"""),1.457523392287306) -> 1.4575234 | AM14: =IFERROR(__xludf.DUMMYFUNCTION("""COMPUTED_VALUE"""),"") | AN14: =IFERROR(__xludf.DUMMYFUNCTION("""COMPUTED_VALUE"""),34.98056141489535) -> 34.980561 | AO14: =IFERROR(__xludf.DUMMYFUNCTION("""COMPUTED_VALUE"""),6.9) -> 6.9 | AP14: =IFERROR(__xludf.DUMMYFUNCTION("""COMPUTED_VALUE"""),8.357523392287307) -> 8.3575234
B15: 46028 | C15: INVERSIONES DOBLE PICA, C.A. | D15: 237136 | E15: MARGARINA MAVESA 500GR | F15: {=IF(E15="","",XLOOKUP(E15,DATOS!$D$6:$D2624,DATOS!$C$6:$C2624,0,0,1))} -> MARG2 | G15: 12 | H15: 12 | I15: =9827.06/G15 -> 818.92167 | J15: E | K15: =IF(I15="","", IF(J15="E",I15,I15*1.16)) -> 818.92167 | L15: =IF(I15="","",G15*K15) -> 9827.06 | M15: 308.15 | N15: =IF(M15="","",K15/M15) -> 2.6575423 | Q15: =IF(O15="","", IF(P15="E",O15,O15*1.16)) | R15: =IF(G15="","",(G15*Q15))+IF(G15="","",(G15*N15)) -> 31.890508 | S15: {=XLOOKUP(E15,PESOS!$B$2:$B2624,PESOS!$F$2:$F2624,"")} -> 6.6 | T15: =IF(B15="","",N15+Q15+S15) -> 9.2575423 | V15: =IF(M15="","",(L15/M15)) -> 31.890508 | X15: =IFERROR(__xludf.DUMMYFUNCTION("""COMPUTED_VALUE"""),46028.0) -> 46028 | Y15: =IFERROR(__xludf.DUMMYFUNCTION("""COMPUTED_VALUE"""),"INVERSIONES DOBLE PICA, C.A.") -> INVERSIONES DOBLE PICA, C.A. | Z15: =IFERROR(__xludf.DUMMYFUNCTION("""COMPUTED_VALUE"""),237136.0) -> 237136 | AA15: =IFERROR(__xludf.DUMMYFUNCTION("""COMPUTED_VALUE"""),"MARGARINA MAVESA 500GR") -> MARGARINA MAVESA 500GR | AB15: =IFERROR(__xludf.DUMMYFUNCTION("""COMPUTED_VALUE"""),"MARG2") -> MARG2 | AC15: =IFERROR(__xludf.DUMMYFUNCTION("""COMPUTED_VALUE"""),12.0) -> 12 | AD15: =IFERROR(__xludf.DUMMYFUNCTION("""COMPUTED_VALUE"""),12.0) -> 12 | AE15: =IFERROR(__xludf.DUMMYFUNCTION("""COMPUTED_VALUE"""),818.9216666666666) -> 818.92167 | AF15: =IFERROR(__xludf.DUMMYFUNCTION("""COMPUTED_VALUE"""),"E") -> E | AG15: =IFERROR(__xludf.DUMMYFUNCTION("""COMPUTED_VALUE"""),818.9216666666666) -> 818.92167 | AH15: =IFERROR(__xludf.DUMMYFUNCTION("""COMPUTED_VALUE"""),9827.06) -> 9827.06 | AI15: =IFERROR(__xludf.DUMMYFUNCTION("""COMPUTED_VALUE"""),308.15) -> 308.15 | AJ15: =IFERROR(__xludf.DUMMYFUNCTION("""COMPUTED_VALUE"""),2.6575423224620045) -> 2.6575423 | AM15: =IFERROR(__xludf.DUMMYFUNCTION("""COMPUTED_VALUE"""),"") | AN15: =IFERROR(__xludf.DUMMYFUNCTION("""COMPUTED_VALUE"""),31.890507869544052) -> 31.890508 | AO15: =IFERROR(__xludf.DUMMYFUNCTION("""COMPUTED_VALUE"""),6.6) -> 6.6 | AP15: =IFERROR(__xludf.DUMMYFUNCTION("""COMPUTED_VALUE"""),9.257542322462005) -> 9.2575423
B16: 46028 | C16: INVERSIONES DOBLE PICA, C.A. | D16: 237136 | E16: Mayonesa Mavesa 445gr | F16: {=IF(E16="","",XLOOKUP(E16,DATOS!$D$6:$D2624,DATOS!$C$6:$C2624,0,0,1))} -> MAYO2 | G16: 12 | H16: 12 | I16: =12011.88/G16 -> 1000.99 | J16: E | K16: =IF(I16="","", IF(J16="E",I16,I16*1.16)) -> 1000.99 | L16: =IF(I16="","",G16*K16) -> 12011.88 | M16: 308.15 | N16: =IF(M16="","",K16/M16) -> 3.2483855 | Q16: =IF(O16="","", IF(P16="E",O16,O16*1.16)) | R16: =IF(G16="","",(G16*Q16))+IF(G16="","",(G16*N16)) -> 38.980626 | S16: {=XLOOKUP(E16,PESOS!$B$2:$B2624,PESOS!$F$2:$F2624,"")} -> 8.4 | T16: =IF(B16="","",N16+Q16+S16) -> 11.648386 | V16: =IF(M16="","",(L16/M16)) -> 38.980626 | X16: =IFERROR(__xludf.DUMMYFUNCTION("""COMPUTED_VALUE"""),46028.0) -> 46028 | Y16: =IFERROR(__xludf.DUMMYFUNCTION("""COMPUTED_VALUE"""),"INVERSIONES DOBLE PICA, C.A.") -> INVERSIONES DOBLE PICA, C.A. | Z16: =IFERROR(__xludf.DUMMYFUNCTION("""COMPUTED_VALUE"""),237136.0) -> 237136 | AA16: =IFERROR(__xludf.DUMMYFUNCTION("""COMPUTED_VALUE"""),"Mayonesa Mavesa 445gr") -> Mayonesa Mavesa 445gr | AB16: =IFERROR(__xludf.DUMMYFUNCTION("""COMPUTED_VALUE"""),"MAYO2") -> MAYO2 | AC16: =IFERROR(__xludf.DUMMYFUNCTION("""COMPUTED_VALUE"""),12.0) -> 12 | AD16: =IFERROR(__xludf.DUMMYFUNCTION("""COMPUTED_VALUE"""),12.0) -> 12 | AE16: =IFERROR(__xludf.DUMMYFUNCTION("""COMPUTED_VALUE"""),1000.9899999999999) -> 1000.99 | AF16: =IFERROR(__xludf.DUMMYFUNCTION("""COMPUTED_VALUE"""),"E") -> E | AG16: =IFERROR(__xludf.DUMMYFUNCTION("""COMPUTED_VALUE"""),1000.9899999999999) -> 1000.99 | AH16: =IFERROR(__xludf.DUMMYFUNCTION("""COMPUTED_VALUE"""),12011.88) -> 12011.88 | AI16: =IFERROR(__xludf.DUMMYFUNCTION("""COMPUTED_VALUE"""),308.15) -> 308.15 | AJ16: =IFERROR(__xludf.DUMMYFUNCTION("""COMPUTED_VALUE"""),3.2483855265292876) -> 3.2483855 | AM16: =IFERROR(__xludf.DUMMYFUNCTION("""COMPUTED_VALUE"""),"") | AN16: =IFERROR(__xludf.DUMMYFUNCTION("""COMPUTED_VALUE"""),38.980626318351455) -> 38.980626 | AO16: =IFERROR(__xludf.DUMMYFUNCTION("""COMPUTED_VALUE"""),8.4) -> 8.4 | AP16: =IFERROR(__xludf.DUMMYFUNCTION("""COMPUTED_VALUE"""),11.648385526529289) -> 11.648386
B17: 46028 | C17: INVERSIONES DOBLE PICA, C.A. | D17: 237136 | E17: MAYONESA MAVESA 900GR | F17: {=IF(E17="","",XLOOKUP(E17,DATOS!$D$6:$D2624,DATOS!$C$6:$C2624,0,0,1))} -> 00118 | G17: 2 | H17: 2 | I17: 2126.27 | J17: E | K17: =IF(I17="","", IF(J17="E",I17,I17*1.16)) -> 2126.27 | L17: =IF(I17="","",G17*K17) -> 4252.54 | M17: 308.15 | N17: =IF(M17="","",K17/M17) -> 6.9001136 | Q17: =IF(O17="","", IF(P17="E",O17,O17*1.16)) | R17: =IF(G17="","",(G17*Q17))+IF(G17="","",(G17*N17)) -> 13.800227 | S17: {=XLOOKUP(E17,PESOS!$B$2:$B2624,PESOS!$F$2:$F2624,"")} | T17: =IF(B17="","",N17+Q17+S17) -> 6.9001136 | V17: =IF(M17="","",(L17/M17)) -> 13.800227 | X17: =IFERROR(__xludf.DUMMYFUNCTION("""COMPUTED_VALUE"""),46028.0) -> 46028 | Y17: =IFERROR(__xludf.DUMMYFUNCTION("""COMPUTED_VALUE"""),"INVERSIONES DOBLE PICA, C.A.") -> INVERSIONES DOBLE PICA, C.A. | Z17: =IFERROR(__xludf.DUMMYFUNCTION("""COMPUTED_VALUE"""),237136.0) -> 237136 | AA17: =IFERROR(__xludf.DUMMYFUNCTION("""COMPUTED_VALUE"""),"MAYONESA MAVESA 900GR") -> MAYONESA MAVESA 900GR | AB17: =IFERROR(__xludf.DUMMYFUNCTION("""COMPUTED_VALUE"""),"00118") -> 00118 | AC17: =IFERROR(__xludf.DUMMYFUNCTION("""COMPUTED_VALUE"""),2.0) -> 2 | AD17: =IFERROR(__xludf.DUMMYFUNCTION("""COMPUTED_VALUE"""),2.0) -> 2 | AE17: =IFERROR(__xludf.DUMMYFUNCTION("""COMPUTED_VALUE"""),2126.27) -> 2126.27 | AF17: =IFERROR(__xludf.DUMMYFUNCTION("""COMPUTED_VALUE"""),"E") -> E | AG17: =IFERROR(__xludf.DUMMYFUNCTION("""COMPUTED_VALUE"""),2126.27) -> 2126.27 | AH17: =IFERROR(__xludf.DUMMYFUNCTION("""COMPUTED_VALUE"""),4252.54) -> 4252.54 | AI17: =IFERROR(__xludf.DUMMYFUNCTION("""COMPUTED_VALUE"""),308.15) -> 308.15 | AJ17: =IFERROR(__xludf.DUMMYFUNCTION("""COMPUTED_VALUE"""),6.900113581048191) -> 6.9001136 | AM17: =IFERROR(__xludf.DUMMYFUNCTION("""COMPUTED_VALUE"""),"") | AN17: =IFERROR(__xludf.DUMMYFUNCTION("""COMPUTED_VALUE"""),13.800227162096382) -> 13.800227 | AO17: =IFERROR(__xludf.DUMMYFUNCTION("""COMPUTED_VALUE"""),"") | AP17: =IFERROR(__xludf.DUMMYFUNCTION("""COMPUTED_VALUE"""),6.900113581048191) -> 6.9001136
B18: 46028 | C18: INVERSIONES DOBLE PICA, C.A. | D18: 237136 | E18: Sardina Omega | F18: {=IF(E18="","",XLOOKUP(E18,DATOS!$D$6:$D2624,DATOS!$C$6:$C2624,0,0,1))} -> SAR3 | G18: 96 | H18: 24 | I18: =19709.59/G18 -> 205.30823 | J18: E | K18: =IF(I18="","", IF(J18="E",I18,I18*1.16)) -> 205.30823 | L18: =IF(I18="","",G18*K18) -> 19709.59 | M18: 308.15 | N18: =IF(M18="","",K18/M18) -> 0.66626068 | Q18: =IF(O18="","", IF(P18="E",O18,O18*1.16)) | R18: =IF(G18="","",(G18*Q18))+IF(G18="","",(G18*N18)) -> 63.961025 | S18: {=XLOOKUP(E18,PESOS!$B$2:$B2624,PESOS!$F$2:$F2624,"")} | T18: =IF(B18="","",N18+Q18+S18) -> 0.66626068 | V18: =IF(M18="","",(L18/M18)) -> 63.961025 | X18: =IFERROR(__xludf.DUMMYFUNCTION("""COMPUTED_VALUE"""),46028.0) -> 46028 | Y18: =IFERROR(__xludf.DUMMYFUNCTION("""COMPUTED_VALUE"""),"INVERSIONES DOBLE PICA, C.A.") -> INVERSIONES DOBLE PICA, C.A. | Z18: =IFERROR(__xludf.DUMMYFUNCTION("""COMPUTED_VALUE"""),237136.0) -> 237136 | AA18: =IFERROR(__xludf.DUMMYFUNCTION("""COMPUTED_VALUE"""),"Sardina Omega") -> Sardina Omega | AB18: =IFERROR(__xludf.DUMMYFUNCTION("""COMPUTED_VALUE"""),"SAR3") -> SAR3 | AC18: =IFERROR(__xludf.DUMMYFUNCTION("""COMPUTED_VALUE"""),96.0) -> 96 | AD18: =IFERROR(__xludf.DUMMYFUNCTION("""COMPUTED_VALUE"""),24.0) -> 24 | AE18: =IFERROR(__xludf.DUMMYFUNCTION("""COMPUTED_VALUE"""),205.30822916666668) -> 205.30823 | AF18: =IFERROR(__xludf.DUMMYFUNCTION("""COMPUTED_VALUE"""),"E") -> E | AG18: =IFERROR(__xludf.DUMMYFUNCTION("""COMPUTED_VALUE"""),205.30822916666668) -> 205.30823 | AH18: =IFERROR(__xludf.DUMMYFUNCTION("""COMPUTED_VALUE"""),19709.59) -> 19709.59 | AI18: =IFERROR(__xludf.DUMMYFUNCTION("""COMPUTED_VALUE"""),308.15) -> 308.15 | AJ18: =IFERROR(__xludf.DUMMYFUNCTION("""COMPUTED_VALUE"""),0.6662606820271514) -> 0.66626068 | AM18: =IFERROR(__xludf.DUMMYFUNCTION("""COMPUTED_VALUE"""),"") | AN18: =IFERROR(__xludf.DUMMYFUNCTION("""COMPUTED_VALUE"""),63.96102547460653) -> 63.961025 | AO18: =IFERROR(__xludf.DUMMYFUNCTION("""COMPUTED_VALUE"""),"") | AP18: =IFERROR(__xludf.DUMMYFUNCTION("""COMPUTED_VALUE"""),0.6662606820271514) -> 0.66626068
B19: 46028 | C19: INVERSIONES UNARE 3, C.A. | D19: 382654 | E19: MORTADELA ALIBAL 500GR | F19: {=IF(E19="","",XLOOKUP(E19,DATOS!$D$6:$D2624,DATOS!$C$6:$C2624,0,0,1))} -> MOR04 | G19: 20 | H19: 20 | I19: =13537.03/G19 -> 676.8515 | J19: E | K19: =IF(I19="","", IF(J19="E",I19,I19*1.16)) -> 676.8515 | L19: =IF(I19="","",G19*K19) -> 13537.03 | M19: 308.15 | N19: =IF(M19="","",K19/M19) -> 2.1965001 | Q19: =IF(O19="","", IF(P19="E",O19,O19*1.16)) | R19: =IF(G19="","",(G19*Q19))+IF(G19="","",(G19*N19)) -> 43.930002 | S19: {=XLOOKUP(E19,PESOS!$B$2:$B2624,PESOS!$F$2:$F2624,"")} -> 0 | T19: =IF(B19="","",N19+Q19+S19) -> 2.1965001 | V19: =IF(M19="","",(L19/M19)) -> 43.930002
B20: 46028 | C20: OMAR MATOS | E20: Huevo | F20: {=IF(E20="","",XLOOKUP(E20,DATOS!$D$6:$D2624,DATOS!$C$6:$C2624,0,0,1))} -> HUEVO | G20: 720 | H20: 360 | K20: =IF(I20="","", IF(J20="E",I20,I20*1.16)) | L20: =IF(I20="","",G20*K20) | N20: =IF(M20="","",K20/M20) | O20: =45/G20 -> 0.0625 | P20: E | Q20: =IF(O20="","", IF(P20="E",O20,O20*1.16)) -> 0.0625 | R20: =IF(G20="","",(G20*Q20))+IF(G20="","",(G20*N20)) -> 45 | S20: {=XLOOKUP(E20,PESOS!$B$2:$B2624,PESOS!$F$2:$F2624,"")} | T20: =IF(B20="","",N20+Q20+S20) -> 0.0625 | V20: =IF(M20="","",(L20/M20))
F21: {=IF(E21="","",XLOOKUP(E21,DATOS!$D$6:$D2624,DATOS!$C$6:$C2624,0,0,1))} | K21: =IF(I21="","", IF(J21="E",I21,I21*1.16)) | L21: =IF(I21="","",G21*K21) | N21: =IF(M21="","",K21/M21) | Q21: =IF(O21="","", IF(P21="E",O21,O21*1.16)) | R21: =IF(G21="","",(G21*Q21))+IF(G21="","",(G21*N21)) -> 0 | S21: {=XLOOKUP(E21,PESOS!$B$2:$B2624,PESOS!$F$2:$F2624,"")} | T21: =IF(B21="","",N21+Q21+S21) | V21: =IF(M21="","",(L21/M21))
F22: {=IF(E22="","",XLOOKUP(E22,DATOS!$D$6:$D2624,DATOS!$C$6:$C2624,0,0,1))} | K22: =IF(I22="","", IF(J22="E",I22,I22*1.16)) | L22: =IF(I22="","",G22*K22) | N22: =IF(M22="","",K22/M22) | Q22: =IF(O22="","", IF(P22="E",O22,O22*1.16)) | R22: =IF(G22="","",(G22*Q22))+IF(G22="","",(G22*N22)) -> 0 | S22: {=XLOOKUP(E22,PESOS!$B$2:$B2624,PESOS!$F$2:$F2624,"")} | T22: =IF(B22="","",N22+Q22+S22) | V22: =IF(M22="","",(L22/M22))
F23: {=IF(E23="","",XLOOKUP(E23,DATOS!$D$6:$D2624,DATOS!$C$6:$C2624,0,0,1))} | K23: =IF(I23="","", IF(J23="E",I23,I23*1.16)) | L23: =IF(I23="","",G23*K23) | N23: =IF(M23="","",K23/M23) | Q23: =IF(O23="","", IF(P23="E",O23,O23*1.16)) | R23: =IF(G23="","",(G23*Q23))+IF(G23="","",(G23*N23)) -> 0 | S23: {=XLOOKUP(E23,PESOS!$B$2:$B2624,PESOS!$F$2:$F2624,"")} | T23: =IF(B23="","",N23+Q23+S23) | V23: =IF(M23="","",(L23/M23))
F24: {=IF(E24="","",XLOOKUP(E24,DATOS!$D$6:$D2624,DATOS!$C$6:$C2624,0,0,1))} | K24: =IF(I24="","", IF(J24="E",I24,I24*1.16)) | L24: =IF(I24="","",G24*K24) | N24: =IF(M24="","",K24/M24) | Q24: =IF(O24="","", IF(P24="E",O24,O24*1.16)) | R24: =IF(G24="","",(G24*Q24))+IF(G24="","",(G24*N24)) -> 0 | S24: {=XLOOKUP(E24,PESOS!$B$2:$B2624,PESOS!$F$2:$F2624,"")} | T24: =IF(B24="","",N24+Q24+S24) | V24: =IF(M24="","",(L24/M24))
F25: {=IF(E25="","",XLOOKUP(E25,DATOS!$D$6:$D2624,DATOS!$C$6:$C2624,0,0,1))} | K25: =IF(I25="","", IF(J25="E",I25,I25*1.16)) | L25: =IF(I25="","",G25*K25) | N25: =IF(M25="","",K25/M25) | Q25: =IF(O25="","", IF(P25="E",O25,O25*1.16)) | R25: =IF(G25="","",(G25*Q25))+IF(G25="","",(G25*N25)) -> 0 | S25: {=XLOOKUP(E25,PESOS!$B$2:$B2624,PESOS!$F$2:$F2624,"")} | T25: =IF(B25="","",N25+Q25+S25) | V25: =IF(M25="","",(L25/M25))
F26: {=IF(E26="","",XLOOKUP(E26,DATOS!$D$6:$D2624,DATOS!$C$6:$C2624,0,0,1))} | K26: =IF(I26="","", IF(J26="E",I26,I26*1.16)) | L26: =IF(I26="","",G26*K26) | N26: =IF(M26="","",K26/M26) | Q26: =IF(O26="","", IF(P26="E",O26,O26*1.16)) | R26: =IF(G26="","",(G26*Q26))+IF(G26="","",(G26*N26)) -> 0 | S26: {=XLOOKUP(E26,PESOS!$B$2:$B2624,PESOS!$F$2:$F2624,"")} | T26: =IF(B26="","",N26+Q26+S26) | V26: =IF(M26="","",(L26/M26))
F27: {=IF(E27="","",XLOOKUP(E27,DATOS!$D$6:$D2624,DATOS!$C$6:$C2624,0,0,1))} | K27: =IF(I27="","", IF(J27="E",I27,I27*1.16)) | L27: =IF(I27="","",G27*K27) | N27: =IF(M27="","",K27/M27) | Q27: =IF(O27="","", IF(P27="E",O27,O27*1.16)) | R27: =IF(G27="","",(G27*Q27))+IF(G27="","",(G27*N27)) -> 0 | S27: {=XLOOKUP(E27,PESOS!$B$2:$B2624,PESOS!$F$2:$F2624,"")} | T27: =IF(B27="","",N27+Q27+S27) | V27: =IF(M27="","",(L27/M27))
F28: {=IF(E28="","",XLOOKUP(E28,DATOS!$D$6:$D2624,DATOS!$C$6:$C2624,0,0,1))} | K28: =IF(I28="","", IF(J28="E",I28,I28*1.16)) | L28: =IF(I28="","",G28*K28) | N28: =IF(M28="","",K28/M28) | Q28: =IF(O28="","", IF(P28="E",O28,O28*1.16)) | R28: =IF(G28="","",(G28*Q28))+IF(G28="","",(G28*N28)) -> 0 | S28: {=XLOOKUP(E28,PESOS!$B$2:$B2624,PESOS!$F$2:$F2624,"")} | T28: =IF(B28="","",N28+Q28+S28) | V28: =IF(M28="","",(L28/M28))
F29: {=IF(E29="","",XLOOKUP(E29,DATOS!$D$6:$D2624,DATOS!$C$6:$C2624,0,0,1))} | K29: =IF(I29="","", IF(J29="E",I29,I29*1.16)) | L29: =IF(I29="","",G29*K29) | N29: =IF(M29="","",K29/M29) | Q29: =IF(O29="","", IF(P29="E",O29,O29*1.16)) | R29: =IF(G29="","",(G29*Q29))+IF(G29="","",(G29*N29)) -> 0 | S29: {=XLOOKUP(E29,PESOS!$B$2:$B2624,PESOS!$F$2:$F2624,"")} | T29: =IF(B29="","",N29+Q29+S29) | V29: =IF(M29="","",(L29/M29))
F30: {=IF(E30="","",XLOOKUP(E30,DATOS!$D$6:$D2624,DATOS!$C$6:$C2624,0,0,1))} | K30: =IF(I30="","", IF(J30="E",I30,I30*1.16)) | L30: =IF(I30="","",G30*K30) | N30: =IF(M30="","",K30/M30) | Q30: =IF(O30="","", IF(P30="E",O30,O30*1.16)) | R30: =IF(G30="","",(G30*Q30))+IF(G30="","",(G30*N30)) -> 0 | S30: {=XLOOKUP(E30,PESOS!$B$2:$B2624,PESOS!$F$2:$F2624,"")} | T30: =IF(B30="","",N30+Q30+S30) | V30: =IF(M30="","",(L30/M30))
F31: {=IF(E31="","",XLOOKUP(E31,DATOS!$D$6:$D2624,DATOS!$C$6:$C2624,0,0,1))} | K31: =IF(I31="","", IF(J31="E",I31,I31*1.16)) | L31: =IF(I31="","",G31*K31) | N31: =IF(M31="","",K31/M31) | Q31: =IF(O31="","", IF(P31="E",O31,O31*1.16)) | R31: =IF(G31="","",(G31*Q31))+IF(G31="","",(G31*N31)) -> 0 | S31: {=XLOOKUP(E31,PESOS!$B$2:$B2624,PESOS!$F$2:$F2624,"")} | T31: =IF(B31="","",N31+Q31+S31) | V31: =IF(M31="","",(L31/M31))
F32: {=IF(E32="","",XLOOKUP(E32,DATOS!$D$6:$D2624,DATOS!$C$6:$C2624,0,0,1))} | K32: =IF(I32="","", IF(J32="E",I32,I32*1.16)) | L32: =IF(I32="","",G32*K32) | N32: =IF(M32="","",K32/M32) | Q32: =IF(O32="","", IF(P32="E",O32,O32*1.16)) | R32: =IF(G32="","",(G32*Q32))+IF(G32="","",(G32*N32)) -> 0 | S32: {=XLOOKUP(E32,PESOS!$B$2:$B2624,PESOS!$F$2:$F2624,"")} | T32: =IF(B32="","",N32+Q32+S32) | V32: =IF(M32="","",(L32/M32))
F33: {=IF(E33="","",XLOOKUP(E33,DATOS!$D$6:$D2624,DATOS!$C$6:$C2624,0,0,1))} | K33: =IF(I33="","", IF(J33="E",I33,I33*1.16)) | L33: =IF(I33="","",G33*K33) | N33: =IF(M33="","",K33/M33) | Q33: =IF(O33="","", IF(P33="E",O33,O33*1.16)) | R33: =IF(G33="","",(G33*Q33))+IF(G33="","",(G33*N33)) -> 0 | S33: {=XLOOKUP(E33,PESOS!$B$2:$B2624,PESOS!$F$2:$F2624,"")} | T33: =IF(B33="","",N33+Q33+S33) | V33: =IF(M33="","",(L33/M33))
F34: {=IF(E34="","",XLOOKUP(E34,DATOS!$D$6:$D2624,DATOS!$C$6:$C2624,0,0,1))} | K34: =IF(I34="","", IF(J34="E",I34,I34*1.16)) | L34: =IF(I34="","",G34*K34) | N34: =IF(M34="","",K34/M34) | Q34: =IF(O34="","", IF(P34="E",O34,O34*1.16)) | R34: =IF(G34="","",(G34*Q34))+IF(G34="","",(G34*N34)) -> 0 | S34: {=XLOOKUP(E34,PESOS!$B$2:$B2624,PESOS!$F$2:$F2624,"")} | T34: =IF(B34="","",N34+Q34+S34) | V34: =IF(M34="","",(L34/M34))
F35: {=IF(E35="","",XLOOKUP(E35,DATOS!$D$6:$D2624,DATOS!$C$6:$C2624,0,0,1))} | K35: =IF(I35="","", IF(J35="E",I35,I35*1.16)) | L35: =IF(I35="","",G35*K35) | N35: =IF(M35="","",K35/M35) | Q35: =IF(O35="","", IF(P35="E",O35,O35*1.16)) | R35: =IF(G35="","",(G35*Q35))+IF(G35="","",(G35*N35)) -> 0 | S35: {=XLOOKUP(E35,PESOS!$B$2:$B2624,PESOS!$F$2:$F2624,"")} | T35: =IF(B35="","",N35+Q35+S35) | V35: =IF(M35="","",(L35/M35))
F36: {=IF(E36="","",XLOOKUP(E36,DATOS!$D$6:$D2624,DATOS!$C$6:$C2624,0,0,1))} | K36: =IF(I36="","", IF(J36="E",I36,I36*1.16)) | L36: =IF(I36="","",G36*K36) | N36: =IF(M36="","",K36/M36) | Q36: =IF(O36="","", IF(P36="E",O36,O36*1.16)) | R36: =IF(G36="","",(G36*Q36))+IF(G36="","",(G36*N36)) -> 0 | S36: {=XLOOKUP(E36,PESOS!$B$2:$B2624,PESOS!$F$2:$F2624,"")} | T36: =IF(B36="","",N36+Q36+S36) | V36: =IF(M36="","",(L36/M36))
F37: {=IF(E37="","",XLOOKUP(E37,DATOS!$D$6:$D2624,DATOS!$C$6:$C2624,0,0,1))} | K37: =IF(I37="","", IF(J37="E",I37,I37*1.16)) | L37: =IF(I37="","",G37*K37) | N37: =IF(M37="","",K37/M37) | Q37: =IF(O37="","", IF(P37="E",O37,O37*1.16)) | R37: =IF(G37="","",(G37*Q37))+IF(G37="","",(G37*N37)) -> 0 | S37: {=XLOOKUP(E37,PESOS!$B$2:$B2624,PESOS!$F$2:$F2624,"")} | T37: =IF(B37="","",N37+Q37+S37) | V37: =IF(M37="","",(L37/M37))
F38: {=IF(E38="","",XLOOKUP(E38,DATOS!$D$6:$D2624,DATOS!$C$6:$C2624,0,0,1))} | K38: =IF(I38="","", IF(J38="E",I38,I38*1.16)) | L38: =IF(I38="","",G38*K38) | N38: =IF(M38="","",K38/M38) | Q38: =IF(O38="","", IF(P38="E",O38,O38*1.16)) | R38: =IF(G38="","",(G38*Q38))+IF(G38="","",(G38*N38)) -> 0 | S38: {=XLOOKUP(E38,PESOS!$B$2:$B2624,PESOS!$F$2:$F2624,"")} | T38: =IF(B38="","",N38+Q38+S38) | V38: =IF(M38="","",(L38/M38))
F39: {=IF(E39="","",XLOOKUP(E39,DATOS!$D$6:$D2624,DATOS!$C$6:$C2624,0,0,1))} | K39: =IF(I39="","", IF(J39="E",I39,I39*1.16)) | L39: =IF(I39="","",G39*K39) | N39: =IF(M39="","",K39/M39) | Q39: =IF(O39="","", IF(P39="E",O39,O39*1.16)) | R39: =IF(G39="","",(G39*Q39))+IF(G39="","",(G39*N39)) -> 0 | S39: {=XLOOKUP(E39,PESOS!$B$2:$B2624,PESOS!$F$2:$F2624,"")} | T39: =IF(B39="","",N39+Q39+S39) | V39: =IF(M39="","",(L39/M39))
F40: {=IF(E40="","",XLOOKUP(E40,DATOS!$D$6:$D2624,DATOS!$C$6:$C2624,0,0,1))} | K40: =IF(I40="","", IF(J40="E",I40,I40*1.16)) | L40: =IF(I40="","",G40*K40) | N40: =IF(M40="","",K40/M40) | Q40: =IF(O40="","", IF(P40="E",O40,O40*1.16)) | R40: =IF(G40="","",(G40*Q40))+IF(G40="","",(G40*N40)) -> 0 | S40: {=XLOOKUP(E40,PESOS!$B$2:$B2624,PESOS!$F$2:$F2624,"")} | T40: =IF(B40="","",N40+Q40+S40) | V40: =IF(M40="","",(L40/M40))
F41: {=IF(E41="","",XLOOKUP(E41,DATOS!$D$6:$D2624,DATOS!$C$6:$C2624,0,0,1))} | K41: =IF(I41="","", IF(J41="E",I41,I41*1.16)) | L41: =IF(I41="","",G41*K41) | N41: =IF(M41="","",K41/M41) | Q41: =IF(O41="","", IF(P41="E",O41,O41*1.16)) | R41: =IF(G41="","",(G41*Q41))+IF(G41="","",(G41*N41)) -> 0 | S41: {=XLOOKUP(E41,PESOS!$B$2:$B2624,PESOS!$F$2:$F2624,"")} | T41: =IF(B41="","",N41+Q41+S41) | V41: =IF(M41="","",(L41/M41))
F42: {=IF(E42="","",XLOOKUP(E42,DATOS!$D$6:$D2624,DATOS!$C$6:$C2624,0,0,1))} | K42: =IF(I42="","", IF(J42="E",I42,I42*1.16)) | L42: =IF(I42="","",G42*K42) | N42: =IF(M42="","",K42/M42) | Q42: =IF(O42="","", IF(P42="E",O42,O42*1.16)) | R42: =IF(G42="","",(G42*Q42))+IF(G42="","",(G42*N42)) -> 0 | S42: {=XLOOKUP(E42,PESOS!$B$2:$B2624,PESOS!$F$2:$F2624,"")} | T42: =IF(B42="","",N42+Q42+S42) | V42: =IF(M42="","",(L42/M42))
F43: {=IF(E43="","",XLOOKUP(E43,DATOS!$D$6:$D2624,DATOS!$C$6:$C2624,0,0,1))} | K43: =IF(I43="","", IF(J43="E",I43,I43*1.16)) | L43: =IF(I43="","",G43*K43) | N43: =IF(M43="","",K43/M43) | Q43: =IF(O43="","", IF(P43="E",O43,O43*1.16)) | R43: =IF(G43="","",(G43*Q43))+IF(G43="","",(G43*N43)) -> 0 | S43: {=XLOOKUP(E43,PESOS!$B$2:$B2624,PESOS!$F$2:$F2624,"")} | T43: =IF(B43="","",N43+Q43+S43) | V43: =IF(M43="","",(L43/M43))
F44: {=IF(E44="","",XLOOKUP(E44,DATOS!$D$6:$D2624,DATOS!$C$6:$C2624,0,0,1))} | K44: =IF(I44="","", IF(J44="E",I44,I44*1.16)) | L44: =IF(I44="","",G44*K44) | N44: =IF(M44="","",K44/M44) | Q44: =IF(O44="","", IF(P44="E",O44,O44*1.16)) | R44: =IF(G44="","",(G44*Q44))+IF(G44="","",(G44*N44)) -> 0 | S44: {=XLOOKUP(E44,PESOS!$B$2:$B2624,PESOS!$F$2:$F2624,"")} | T44: =IF(B44="","",N44+Q44+S44) | V44: =IF(M44="","",(L44/M44))
F45: {=IF(E45="","",XLOOKUP(E45,DATOS!$D$6:$D2624,DATOS!$C$6:$C2624,0,0,1))} | K45: =IF(I45="","", IF(J45="E",I45,I45*1.16)) | L45: =IF(I45="","",G45*K45) | N45: =IF(M45="","",K45/M45) | Q45: =IF(O45="","", IF(P45="E",O45,O45*1.16)) | R45: =IF(G45="","",(G45*Q45))+IF(G45="","",(G45*N45)) -> 0 | S45: {=XLOOKUP(E45,PESOS!$B$2:$B2624,PESOS!$F$2:$F2624,"")} | T45: =IF(B45="","",N45+Q45+S45) | V45: =IF(M45="","",(L45/M45))
F46: {=IF(E46="","",XLOOKUP(E46,DATOS!$D$6:$D2624,DATOS!$C$6:$C2624,0,0,1))} | K46: =IF(I46="","", IF(J46="E",I46,I46*1.16)) | L46: =IF(I46="","",G46*K46) | N46: =IF(M46="","",K46/M46) | Q46: =IF(O46="","", IF(P46="E",O46,O46*1.16)) | R46: =IF(G46="","",(G46*Q46))+IF(G46="","",(G46*N46)) -> 0 | S46: {=XLOOKUP(E46,PESOS!$B$2:$B2624,PESOS!$F$2:$F2624,"")} | T46: =IF(B46="","",N46+Q46+S46) | V46: =IF(M46="","",(L46/M46))
F47: {=IF(E47="","",XLOOKUP(E47,DATOS!$D$6:$D2624,DATOS!$C$6:$C2624,0,0,1))} | K47: =IF(I47="","", IF(J47="E",I47,I47*1.16)) | L47: =IF(I47="","",G47*K47) | N47: =IF(M47="","",K47/M47) | Q47: =IF(O47="","", IF(P47="E",O47,O47*1.16)) | R47: =IF(G47="","",(G47*Q47))+IF(G47="","",(G47*N47)) -> 0 | S47: {=XLOOKUP(E47,PESOS!$B$2:$B2624,PESOS!$F$2:$F2624,"")} | T47: =IF(B47="","",N47+Q47+S47) | V47: =IF(M47="","",(L47/M47))
F48: {=IF(E48="","",XLOOKUP(E48,DATOS!$D$6:$D2624,DATOS!$C$6:$C2624,0,0,1))} | K48: =IF(I48="","", IF(J48="E",I48,I48*1.16)) | L48: =IF(I48="","",G48*K48) | N48: =IF(M48="","",K48/M48) | Q48: =IF(O48="","", IF(P48="E",O48,O48*1.16)) | R48: =IF(G48="","",(G48*Q48))+IF(G48="","",(G48*N48)) -> 0 | S48: {=XLOOKUP(E48,PESOS!$B$2:$B2624,PESOS!$F$2:$F2624,"")} | T48: =IF(B48="","",N48+Q48+S48) | V48: =IF(M48="","",(L48/M48))
F49: {=IF(E49="","",XLOOKUP(E49,DATOS!$D$6:$D2624,DATOS!$C$6:$C2624,0,0,1))} | K49: =IF(I49="","", IF(J49="E",I49,I49*1.16)) | L49: =IF(I49="","",G49*K49) | N49: =IF(M49="","",K49/M49) | Q49: =IF(O49="","", IF(P49="E",O49,O49*1.16)) | R49: =IF(G49="","",(G49*Q49))+IF(G49="","",(G49*N49)) -> 0 | S49: {=XLOOKUP(E49,PESOS!$B$2:$B2624,PESOS!$F$2:$F2624,"")} | T49: =IF(B49="","",N49+Q49+S49) | V49: =IF(M49="","",(L49/M49))
F50: {=IF(E50="","",XLOOKUP(E50,DATOS!$D$6:$D2624,DATOS!$C$6:$C2624,0,0,1))} | K50: =IF(I50="","", IF(J50="E",I50,I50*1.16)) | L50: =IF(I50="","",G50*K50) | N50: =IF(M50="","",K50/M50) | Q50: =IF(O50="","", IF(P50="E",O50,O50*1.16)) | R50: =IF(G50="","",(G50*Q50))+IF(G50="","",(G50*N50)) -> 0 | S50: {=XLOOKUP(E50,PESOS!$B$2:$B2624,PESOS!$F$2:$F2624,"")} | T50: =IF(B50="","",N50+Q50+S50) | V50: =IF(M50="","",(L50/M50))
F51: {=IF(E51="","",XLOOKUP(E51,DATOS!$D$6:$D2624,DATOS!$C$6:$C2624,0,0,1))} | K51: =IF(I51="","", IF(J51="E",I51,I51*1.16)) | L51: =IF(I51="","",G51*K51) | N51: =IF(M51="","",K51/M51) | Q51: =IF(O51="","", IF(P51="E",O51,O51*1.16)) | R51: =IF(G51="","",(G51*Q51))+IF(G51="","",(G51*N51)) -> 0 | S51: {=XLOOKUP(E51,PESOS!$B$2:$B2624,PESOS!$F$2:$F2624,"")} | T51: =IF(B51="","",N51+Q51+S51) | V51: =IF(M51="","",(L51/M51))
F52: {=IF(E52="","",XLOOKUP(E52,DATOS!$D$6:$D2624,DATOS!$C$6:$C2624,0,0,1))} | K52: =IF(I52="","", IF(J52="E",I52,I52*1.16)) | L52: =IF(I52="","",G52*K52) | N52: =IF(M52="","",K52/M52) | Q52: =IF(O52="","", IF(P52="E",O52,O52*1.16)) | R52: =IF(G52="","",(G52*Q52))+IF(G52="","",(G52*N52)) -> 0 | S52: {=XLOOKUP(E52,PESOS!$B$2:$B2624,PESOS!$F$2:$F2624,"")} | T52: =IF(B52="","",N52+Q52+S52) | V52: =IF(M52="","",(L52/M52))
F53: {=IF(E53="","",XLOOKUP(E53,DATOS!$D$6:$D2624,DATOS!$C$6:$C2624,0,0,1))} | K53: =IF(I53="","", IF(J53="E",I53,I53*1.16)) | L53: =IF(I53="","",G53*K53) | N53: =IF(M53="","",K53/M53) | Q53: =IF(O53="","", IF(P53="E",O53,O53*1.16)) | R53: =IF(G53="","",(G53*Q53))+IF(G53="","",(G53*N53)) -> 0 | S53: {=XLOOKUP(E53,PESOS!$B$2:$B2624,PESOS!$F$2:$F2624,"")} | T53: =IF(B53="","",N53+Q53+S53) | V53: =IF(M53="","",(L53/M53))
F54: {=IF(E54="","",XLOOKUP(E54,DATOS!$D$6:$D2624,DATOS!$C$6:$C2624,0,0,1))} | K54: =IF(I54="","", IF(J54="E",I54,I54*1.16)) | L54: =IF(I54="","",G54*K54) | N54: =IF(M54="","",K54/M54) | Q54: =IF(O54="","", IF(P54="E",O54,O54*1.16)) | R54: =IF(G54="","",(G54*Q54))+IF(G54="","",(G54*N54)) -> 0 | S54: {=XLOOKUP(E54,PESOS!$B$2:$B2624,PESOS!$F$2:$F2624,"")} | T54: =IF(B54="","",N54+Q54+S54) | V54: =IF(M54="","",(L54/M54))
F55: {=IF(E55="","",XLOOKUP(E55,DATOS!$D$6:$D2624,DATOS!$C$6:$C2624,0,0,1))} | K55: =IF(I55="","", IF(J55="E",I55,I55*1.16)) | L55: =IF(I55="","",G55*K55) | N55: =IF(M55="","",K55/M55) | Q55: =IF(O55="","", IF(P55="E",O55,O55*1.16)) | R55: =IF(G55="","",(G55*Q55))+IF(G55="","",(G55*N55)) -> 0 | S55: {=XLOOKUP(E55,PESOS!$B$2:$B2624,PESOS!$F$2:$F2624,"")} | T55: =IF(B55="","",N55+Q55+S55) | V55: =IF(M55="","",(L55/M55))
F56: {=IF(E56="","",XLOOKUP(E56,DATOS!$D$6:$D2624,DATOS!$C$6:$C2624,0,0,1))} | K56: =IF(I56="","", IF(J56="E",I56,I56*1.16)) | L56: =IF(I56="","",G56*K56) | N56: =IF(M56="","",K56/M56) | Q56: =IF(O56="","", IF(P56="E",O56,O56*1.16)) | R56: =IF(G56="","",(G56*Q56))+IF(G56="","",(G56*N56)) -> 0 | S56: {=XLOOKUP(E56,PESOS!$B$2:$B2624,PESOS!$F$2:$F2624,"")} | T56: =IF(B56="","",N56+Q56+S56) | V56: =IF(M56="","",(L56/M56))
F57: {=IF(E57="","",XLOOKUP(E57,DATOS!$D$6:$D2624,DATOS!$C$6:$C2624,0,0,1))} | K57: =IF(I57="","", IF(J57="E",I57,I57*1.16)) | L57: =IF(I57="","",G57*K57) | N57: =IF(M57="","",K57/M57) | Q57: =IF(O57="","", IF(P57="E",O57,O57*1.16)) | R57: =IF(G57="","",(G57*Q57))+IF(G57="","",(G57*N57)) -> 0 | S57: {=XLOOKUP(E57,PESOS!$B$2:$B2624,PESOS!$F$2:$F2624,"")} | T57: =IF(B57="","",N57+Q57+S57) | V57: =IF(M57="","",(L57/M57))
F58: {=IF(E58="","",XLOOKUP(E58,DATOS!$D$6:$D2624,DATOS!$C$6:$C2624,0,0,1))} | K58: =IF(I58="","", IF(J58="E",I58,I58*1.16)) | L58: =IF(I58="","",G58*K58) | N58: =IF(M58="","",K58/M58) | Q58: =IF(O58="","", IF(P58="E",O58,O58*1.16)) | R58: =IF(G58="","",(G58*Q58))+IF(G58="","",(G58*N58)) -> 0 | S58: {=XLOOKUP(E58,PESOS!$B$2:$B2624,PESOS!$F$2:$F2624,"")} | T58: =IF(B58="","",N58+Q58+S58) | V58: =IF(M58="","",(L58/M58))
F59: {=IF(E59="","",XLOOKUP(E59,DATOS!$D$6:$D2624,DATOS!$C$6:$C2624,0,0,1))} | K59: =IF(I59="","", IF(J59="E",I59,I59*1.16)) | L59: =IF(I59="","",G59*K59) | N59: =IF(M59="","",K59/M59) | Q59: =IF(O59="","", IF(P59="E",O59,O59*1.16)) | R59: =IF(G59="","",(G59*Q59))+IF(G59="","",(G59*N59)) -> 0 | S59: {=XLOOKUP(E59,PESOS!$B$2:$B2624,PESOS!$F$2:$F2624,"")} | T59: =IF(B59="","",N59+Q59+S59) | V59: =IF(M59="","",(L59/M59))
F60: {=IF(E60="","",XLOOKUP(E60,DATOS!$D$6:$D2624,DATOS!$C$6:$C2624,0,0,1))} | K60: =IF(I60="","", IF(J60="E",I60,I60*1.16)) | L60: =IF(I60="","",G60*K60) | N60: =IF(M60="","",K60/M60) | Q60: =IF(O60="","", IF(P60="E",O60,O60*1.16)) | R60: =IF(G60="","",(G60*Q60))+IF(G60="","",(G60*N60)) -> 0 | S60: {=XLOOKUP(E60,PESOS!$B$2:$B2624,PESOS!$F$2:$F2624,"")} | T60: =IF(B60="","",N60+Q60+S60) | V60: =IF(M60="","",(L60/M60))
F61: {=IF(E61="","",XLOOKUP(E61,DATOS!$D$6:$D2624,DATOS!$C$6:$C2624,0,0,1))} | K61: =IF(I61="","", IF(J61="E",I61,I61*1.16)) | L61: =IF(I61="","",G61*K61) | N61: =IF(M61="","",K61/M61) | Q61: =IF(O61="","", IF(P61="E",O61,O61*1.16)) | R61: =IF(G61="","",(G61*Q61))+IF(G61="","",(G61*N61)) -> 0 | S61: {=XLOOKUP(E61,PESOS!$B$2:$B2624,PESOS!$F$2:$F2624,"")} | T61: =IF(B61="","",N61+Q61+S61) | V61: =IF(M61="","",(L61/M61))
F62: {=IF(E62="","",XLOOKUP(E62,DATOS!$D$6:$D2624,DATOS!$C$6:$C2624,0,0,1))} | K62: =IF(I62="","", IF(J62="E",I62,I62*1.16)) | L62: =IF(I62="","",G62*K62) | N62: =IF(M62="","",K62/M62) | Q62: =IF(O62="","", IF(P62="E",O62,O62*1.16)) | R62: =IF(G62="","",(G62*Q62))+IF(G62="","",(G62*N62)) -> 0 | S62: {=XLOOKUP(E62,PESOS!$B$2:$B2624,PESOS!$F$2:$F2624,"")} | T62: =IF(B62="","",N62+Q62+S62) | V62: =IF(M62="","",(L62/M62))
F63: {=IF(E63="","",XLOOKUP(E63,DATOS!$D$6:$D2624,DATOS!$C$6:$C2624,0,0,1))} | K63: =IF(I63="","", IF(J63="E",I63,I63*1.16)) | L63: =IF(I63="","",G63*K63) | N63: =IF(M63="","",K63/M63) | Q63: =IF(O63="","", IF(P63="E",O63,O63*1.16)) | R63: =IF(G63="","",(G63*Q63))+IF(G63="","",(G63*N63)) -> 0 | S63: {=XLOOKUP(E63,PESOS!$B$2:$B2624,PESOS!$F$2:$F2624,"")} | T63: =IF(B63="","",N63+Q63+S63) | V63: =IF(M63="","",(L63/M63))
F64: {=IF(E64="","",XLOOKUP(E64,DATOS!$D$6:$D2624,DATOS!$C$6:$C2624,0,0,1))} | K64: =IF(I64="","", IF(J64="E",I64,I64*1.16)) | L64: =IF(I64="","",G64*K64) | N64: =IF(M64="","",K64/M64) | Q64: =IF(O64="","", IF(P64="E",O64,O64*1.16)) | R64: =IF(G64="","",(G64*Q64))+IF(G64="","",(G64*N64)) -> 0 | S64: {=XLOOKUP(E64,PESOS!$B$2:$B2624,PESOS!$F$2:$F2624,"")} | T64: =IF(B64="","",N64+Q64+S64) | V64: =IF(M64="","",(L64/M64))
F65: {=IF(E65="","",XLOOKUP(E65,DATOS!$D$6:$D2624,DATOS!$C$6:$C2624,0,0,1))} | K65: =IF(I65="","", IF(J65="E",I65,I65*1.16)) | L65: =IF(I65="","",G65*K65) | N65: =IF(M65="","",K65/M65) | Q65: =IF(O65="","", IF(P65="E",O65,O65*1.16)) | R65: =IF(G65="","",(G65*Q65))+IF(G65="","",(G65*N65)) -> 0 | S65: {=XLOOKUP(E65,PESOS!$B$2:$B2624,PESOS!$F$2:$F2624,"")} | T65: =IF(B65="","",N65+Q65+S65) | V65: =IF(M65="","",(L65/M65))
F66: {=IF(E66="","",XLOOKUP(E66,DATOS!$D$6:$D2624,DATOS!$C$6:$C2624,0,0,1))} | K66: =IF(I66="","", IF(J66="E",I66,I66*1.16)) | L66: =IF(I66="","",G66*K66) | N66: =IF(M66="","",K66/M66) | Q66: =IF(O66="","", IF(P66="E",O66,O66*1.16)) | R66: =IF(G66="","",(G66*Q66))+IF(G66="","",(G66*N66)) -> 0 | S66: {=XLOOKUP(E66,PESOS!$B$2:$B2624,PESOS!$F$2:$F2624,"")} | T66: =IF(B66="","",N66+Q66+S66) | V66: =IF(M66="","",(L66/M66))
F67: {=IF(E67="","",XLOOKUP(E67,DATOS!$D$6:$D2624,DATOS!$C$6:$C2624,0,0,1))} | K67: =IF(I67="","", IF(J67="E",I67,I67*1.16)) | L67: =IF(I67="","",G67*K67) | N67: =IF(M67="","",K67/M67) | Q67: =IF(O67="","", IF(P67="E",O67,O67*1.16)) | R67: =IF(G67="","",(G67*Q67))+IF(G67="","",(G67*N67)) -> 0 | S67: {=XLOOKUP(E67,PESOS!$B$2:$B2624,PESOS!$F$2:$F2624,"")} | T67: =IF(B67="","",N67+Q67+S67) | V67: =IF(M67="","",(L67/M67))
F68: {=IF(E68="","",XLOOKUP(E68,DATOS!$D$6:$D2624,DATOS!$C$6:$C2624,0,0,1))} | K68: =IF(I68="","", IF(J68="E",I68,I68*1.16)) | L68: =IF(I68="","",G68*K68) | N68: =IF(M68="","",K68/M68) | Q68: =IF(O68="","", IF(P68="E",O68,O68*1.16)) | R68: =IF(G68="","",(G68*Q68))+IF(G68="","",(G68*N68)) -> 0 | S68: {=XLOOKUP(E68,PESOS!$B$2:$B2624,PESOS!$F$2:$F2624,"")} | T68: =IF(B68="","",N68+Q68+S68) | V68: =IF(M68="","",(L68/M68))
F69: {=IF(E69="","",XLOOKUP(E69,DATOS!$D$6:$D2624,DATOS!$C$6:$C2624,0,0,1))} | K69: =IF(I69="","", IF(J69="E",I69,I69*1.16)) | L69: =IF(I69="","",G69*K69) | N69: =IF(M69="","",K69/M69) | Q69: =IF(O69="","", IF(P69="E",O69,O69*1.16)) | R69: =IF(G69="","",(G69*Q69))+IF(G69="","",(G69*N69)) -> 0 | S69: {=XLOOKUP(E69,PESOS!$B$2:$B2624,PESOS!$F$2:$F2624,"")} | T69: =IF(B69="","",N69+Q69+S69) | V69: =IF(M69="","",(L69/M69))
F70: {=IF(E70="","",XLOOKUP(E70,DATOS!$D$6:$D2624,DATOS!$C$6:$C2624,0,0,1))} | K70: =IF(I70="","", IF(J70="E",I70,I70*1.16)) | L70: =IF(I70="","",G70*K70) | N70: =IF(M70="","",K70/M70) | Q70: =IF(O70="","", IF(P70="E",O70,O70*1.16)) | R70: =IF(G70="","",(G70*Q70))+IF(G70="","",(G70*N70)) -> 0 | S70: {=XLOOKUP(E70,PESOS!$B$2:$B2624,PESOS!$F$2:$F2624,"")} | T70: =IF(B70="","",N70+Q70+S70) | V70: =IF(M70="","",(L70/M70))
F71: {=IF(E71="","",XLOOKUP(E71,DATOS!$D$6:$D2624,DATOS!$C$6:$C2624,0,0,1))} | K71: =IF(I71="","", IF(J71="E",I71,I71*1.16)) | L71: =IF(I71="","",G71*K71) | N71: =IF(M71="","",K71/M71) | Q71: =IF(O71="","", IF(P71="E",O71,O71*1.16)) | R71: =IF(G71="","",(G71*Q71))+IF(G71="","",(G71*N71)) -> 0 | S71: {=XLOOKUP(E71,PESOS!$B$2:$B2624,PESOS!$F$2:$F2624,"")} | T71: =IF(B71="","",N71+Q71+S71) | V71: =IF(M71="","",(L71/M71))
F72: {=IF(E72="","",XLOOKUP(E72,DATOS!$D$6:$D2624,DATOS!$C$6:$C2624,0,0,1))} | K72: =IF(I72="","", IF(J72="E",I72,I72*1.16)) | L72: =IF(I72="","",G72*K72) | N72: =IF(M72="","",K72/M72) | Q72: =IF(O72="","", IF(P72="E",O72,O72*1.16)) | R72: =IF(G72="","",(G72*Q72))+IF(G72="","",(G72*N72)) -> 0 | S72: {=XLOOKUP(E72,PESOS!$B$2:$B2624,PESOS!$F$2:$F2624,"")} | T72: =IF(B72="","",N72+Q72+S72) | V72: =IF(M72="","",(L72/M72))
F73: {=IF(E73="","",XLOOKUP(E73,DATOS!$D$6:$D2624,DATOS!$C$6:$C2624,0,0,1))} | K73: =IF(I73="","", IF(J73="E",I73,I73*1.16)) | L73: =IF(I73="","",G73*K73) | N73: =IF(M73="","",K73/M73) | Q73: =IF(O73="","", IF(P73="E",O73,O73*1.16)) | R73: =IF(G73="","",(G73*Q73))+IF(G73="","",(G73*N73)) -> 0 | S73: {=XLOOKUP(E73,PESOS!$B$2:$B2624,PESOS!$F$2:$F2624,"")} | T73: =IF(B73="","",N73+Q73+S73) | V73: =IF(M73="","",(L73/M73))
F74: {=IF(E74="","",XLOOKUP(E74,DATOS!$D$6:$D2624,DATOS!$C$6:$C2624,0,0,1))} | K74: =IF(I74="","", IF(J74="E",I74,I74*1.16)) | L74: =IF(I74="","",G74*K74) | N74: =IF(M74="","",K74/M74) | Q74: =IF(O74="","", IF(P74="E",O74,O74*1.16)) | R74: =IF(G74="","",(G74*Q74))+IF(G74="","",(G74*N74)) -> 0 | S74: {=XLOOKUP(E74,PESOS!$B$2:$B2624,PESOS!$F$2:$F2624,"")} | T74: =IF(B74="","",N74+Q74+S74) | V74: =IF(M74="","",(L74/M74))
F75: {=IF(E75="","",XLOOKUP(E75,DATOS!$D$6:$D2624,DATOS!$C$6:$C2624,0,0,1))} | K75: =IF(I75="","", IF(J75="E",I75,I75*1.16)) | L75: =IF(I75="","",G75*K75) | N75: =IF(M75="","",K75/M75) | Q75: =IF(O75="","", IF(P75="E",O75,O75*1.16)) | R75: =IF(G75="","",(G75*Q75))+IF(G75="","",(G75*N75)) -> 0 | S75: {=XLOOKUP(E75,PESOS!$B$2:$B2624,PESOS!$F$2:$F2624,"")} | T75: =IF(B75="","",N75+Q75+S75) | V75: =IF(M75="","",(L75/M75))
F76: {=IF(E76="","",XLOOKUP(E76,DATOS!$D$6:$D2624,DATOS!$C$6:$C2624,0,0,1))} | K76: =IF(I76="","", IF(J76="E",I76,I76*1.16)) | L76: =IF(I76="","",G76*K76) | N76: =IF(M76="","",K76/M76) | Q76: =IF(O76="","", IF(P76="E",O76,O76*1.16)) | R76: =IF(G76="","",(G76*Q76))+IF(G76="","",(G76*N76)) -> 0 | S76: {=XLOOKUP(E76,PESOS!$B$2:$B2624,PESOS!$F$2:$F2624,"")} | T76: =IF(B76="","",N76+Q76+S76) | V76: =IF(M76="","",(L76/M76))
F77: {=IF(E77="","",XLOOKUP(E77,DATOS!$D$6:$D2624,DATOS!$C$6:$C2624,0,0,1))} | K77: =IF(I77="","", IF(J77="E",I77,I77*1.16)) | L77: =IF(I77="","",G77*K77) | N77: =IF(M77="","",K77/M77) | Q77: =IF(O77="","", IF(P77="E",O77,O77*1.16)) | R77: =IF(G77="","",(G77*Q77))+IF(G77="","",(G77*N77)) -> 0 | S77: {=XLOOKUP(E77,PESOS!$B$2:$B2624,PESOS!$F$2:$F2624,"")} | T77: =IF(B77="","",N77+Q77+S77) | V77: =IF(M77="","",(L77/M77))
F78: {=IF(E78="","",XLOOKUP(E78,DATOS!$D$6:$D2624,DATOS!$C$6:$C2624,0,0,1))} | K78: =IF(I78="","", IF(J78="E",I78,I78*1.16)) | L78: =IF(I78="","",G78*K78) | N78: =IF(M78="","",K78/M78) | Q78: =IF(O78="","", IF(P78="E",O78,O78*1.16)) | R78: =IF(G78="","",(G78*Q78))+IF(G78="","",(G78*N78)) -> 0 | S78: {=XLOOKUP(E78,PESOS!$B$2:$B2624,PESOS!$F$2:$F2624,"")} | T78: =IF(B78="","",N78+Q78+S78) | V78: =IF(M78="","",(L78/M78))
F79: {=IF(E79="","",XLOOKUP(E79,DATOS!$D$6:$D2624,DATOS!$C$6:$C2624,0,0,1))} | K79: =IF(I79="","", IF(J79="E",I79,I79*1.16)) | L79: =IF(I79="","",G79*K79) | N79: =IF(M79="","",K79/M79) | Q79: =IF(O79="","", IF(P79="E",O79,O79*1.16)) | R79: =IF(G79="","",(G79*Q79))+IF(G79="","",(G79*N79)) -> 0 | S79: {=XLOOKUP(E79,PESOS!$B$2:$B2624,PESOS!$F$2:$F2624,"")} | T79: =IF(B79="","",N79+Q79+S79) | V79: =IF(M79="","",(L79/M79))
F80: {=IF(E80="","",XLOOKUP(E80,DATOS!$D$6:$D2624,DATOS!$C$6:$C2624,0,0,1))} | K80: =IF(I80="","", IF(J80="E",I80,I80*1.16)) | L80: =IF(I80="","",G80*K80) | N80: =IF(M80="","",K80/M80) | Q80: =IF(O80="","", IF(P80="E",O80,O80*1.16)) | R80: =IF(G80="","",(G80*Q80))+IF(G80="","",(G80*N80)) -> 0 | S80: {=XLOOKUP(E80,PESOS!$B$2:$B2624,PESOS!$F$2:$F2624,"")} | T80: =IF(B80="","",N80+Q80+S80) | V80: =IF(M80="","",(L80/M80))
F81: {=IF(E81="","",XLOOKUP(E81,DATOS!$D$6:$D2624,DATOS!$C$6:$C2624,0,0,1))} | K81: =IF(I81="","", IF(J81="E",I81,I81*1.16)) | L81: =IF(I81="","",G81*K81) | N81: =IF(M81="","",K81/M81) | Q81: =IF(O81="","", IF(P81="E",O81,O81*1.16)) | R81: =IF(G81="","",(G81*Q81))+IF(G81="","",(G81*N81)) -> 0 | S81: {=XLOOKUP(E81,PESOS!$B$2:$B2624,PESOS!$F$2:$F2624,"")} | T81: =IF(B81="","",N81+Q81+S81) | V81: =IF(M81="","",(L81/M81))
F82: {=IF(E82="","",XLOOKUP(E82,DATOS!$D$6:$D2624,DATOS!$C$6:$C2624,0,0,1))} | K82: =IF(I82="","", IF(J82="E",I82,I82*1.16)) | L82: =IF(I82="","",G82*K82) | N82: =IF(M82="","",K82/M82) | Q82: =IF(O82="","", IF(P82="E",O82,O82*1.16)) | R82: =IF(G82="","",(G82*Q82))+IF(G82="","",(G82*N82)) -> 0 | S82: {=XLOOKUP(E82,PESOS!$B$2:$B2624,PESOS!$F$2:$F2624,"")} | T82: =IF(B82="","",N82+Q82+S82) | V82: =IF(M82="","",(L82/M82))
F83: {=IF(E83="","",XLOOKUP(E83,DATOS!$D$6:$D2624,DATOS!$C$6:$C2624,0,0,1))} | K83: =IF(I83="","", IF(J83="E",I83,I83*1.16)) | L83: =IF(I83="","",G83*K83) | N83: =IF(M83="","",K83/M83) | Q83: =IF(O83="","", IF(P83="E",O83,O83*1.16)) | R83: =IF(G83="","",(G83*Q83))+IF(G83="","",(G83*N83)) -> 0 | S83: {=XLOOKUP(E83,PESOS!$B$2:$B2624,PESOS!$F$2:$F2624,"")} | T83: =IF(B83="","",N83+Q83+S83) | V83: =IF(M83="","",(L83/M83))
F84: {=IF(E84="","",XLOOKUP(E84,DATOS!$D$6:$D2624,DATOS!$C$6:$C2624,0,0,1))} | K84: =IF(I84="","", IF(J84="E",I84,I84*1.16)) | L84: =IF(I84="","",G84*K84) | N84: =IF(M84="","",K84/M84) | Q84: =IF(O84="","", IF(P84="E",O84,O84*1.16)) | R84: =IF(G84="","",(G84*Q84))+IF(G84="","",(G84*N84)) -> 0 | S84: {=XLOOKUP(E84,PESOS!$B$2:$B2624,PESOS!$F$2:$F2624,"")} | T84: =IF(B84="","",N84+Q84+S84) | V84: =IF(M84="","",(L84/M84))
F85: {=IF(E85="","",XLOOKUP(E85,DATOS!$D$6:$D2624,DATOS!$C$6:$C2624,0,0,1))} | K85: =IF(I85="","", IF(J85="E",I85,I85*1.16)) | L85: =IF(I85="","",G85*K85) | N85: =IF(M85="","",K85/M85) | Q85: =IF(O85="","", IF(P85="E",O85,O85*1.16)) | R85: =IF(G85="","",(G85*Q85))+IF(G85="","",(G85*N85)) -> 0 | S85: {=XLOOKUP(E85,PESOS!$B$2:$B2624,PESOS!$F$2:$F2624,"")} | T85: =IF(B85="","",N85+Q85+S85) | V85: =IF(M85="","",(L85/M85))
F86: {=IF(E86="","",XLOOKUP(E86,DATOS!$D$6:$D2624,DATOS!$C$6:$C2624,0,0,1))} | K86: =IF(I86="","", IF(J86="E",I86,I86*1.16)) | L86: =IF(I86="","",G86*K86) | N86: =IF(M86="","",K86/M86) | Q86: =IF(O86="","", IF(P86="E",O86,O86*1.16)) | R86: =IF(G86="","",(G86*Q86))+IF(G86="","",(G86*N86)) -> 0 | S86: {=XLOOKUP(E86,PESOS!$B$2:$B2624,PESOS!$F$2:$F2624,"")} | T86: =IF(B86="","",N86+Q86+S86) | V86: =IF(M86="","",(L86/M86))
F87: {=IF(E87="","",XLOOKUP(E87,DATOS!$D$6:$D2624,DATOS!$C$6:$C2624,0,0,1))} | K87: =IF(I87="","", IF(J87="E",I87,I87*1.16)) | L87: =IF(I87="","",G87*K87) | N87: =IF(M87="","",K87/M87) | Q87: =IF(O87="","", IF(P87="E",O87,O87*1.16)) | R87: =IF(G87="","",(G87*Q87))+IF(G87="","",(G87*N87)) -> 0 | S87: {=XLOOKUP(E87,PESOS!$B$2:$B2624,PESOS!$F$2:$F2624,"")} | T87: =IF(B87="","",N87+Q87+S87) | V87: =IF(M87="","",(L87/M87))
F88: {=IF(E88="","",XLOOKUP(E88,DATOS!$D$6:$D2624,DATOS!$C$6:$C2624,0,0,1))} | K88: =IF(I88="","", IF(J88="E",I88,I88*1.16)) | L88: =IF(I88="","",G88*K88) | N88: =IF(M88="","",K88/M88) | Q88: =IF(O88="","", IF(P88="E",O88,O88*1.16)) | R88: =IF(G88="","",(G88*Q88))+IF(G88="","",(G88*N88)) -> 0 | S88: {=XLOOKUP(E88,PESOS!$B$2:$B2624,PESOS!$F$2:$F2624,"")} | T88: =IF(B88="","",N88+Q88+S88) | V88: =IF(M88="","",(L88/M88))
F89: {=IF(E89="","",XLOOKUP(E89,DATOS!$D$6:$D2624,DATOS!$C$6:$C2624,0,0,1))} | K89: =IF(I89="","", IF(J89="E",I89,I89*1.16)) | L89: =IF(I89="","",G89*K89) | N89: =IF(M89="","",K89/M89) | Q89: =IF(O89="","", IF(P89="E",O89,O89*1.16)) | R89: =IF(G89="","",(G89*Q89))+IF(G89="","",(G89*N89)) -> 0 | S89: {=XLOOKUP(E89,PESOS!$B$2:$B2624,PESOS!$F$2:$F2624,"")} | T89: =IF(B89="","",N89+Q89+S89) | V89: =IF(M89="","",(L89/M89))
F90: {=IF(E90="","",XLOOKUP(E90,DATOS!$D$6:$D2624,DATOS!$C$6:$C2624,0,0,1))} | K90: =IF(I90="","", IF(J90="E",I90,I90*1.16)) | L90: =IF(I90="","",G90*K90) | N90: =IF(M90="","",K90/M90) | Q90: =IF(O90="","", IF(P90="E",O90,O90*1.16)) | R90: =IF(G90="","",(G90*Q90))+IF(G90="","",(G90*N90)) -> 0 | S90: {=XLOOKUP(E90,PESOS!$B$2:$B2624,PESOS!$F$2:$F2624,"")} | T90: =IF(B90="","",N90+Q90+S90) | V90: =IF(M90="","",(L90/M90))
F91: {=IF(E91="","",XLOOKUP(E91,DATOS!$D$6:$D2624,DATOS!$C$6:$C2624,0,0,1))} | K91: =IF(I91="","", IF(J91="E",I91,I91*1.16)) | L91: =IF(I91="","",G91*K91) | N91: =IF(M91="","",K91/M91) | Q91: =IF(O91="","", IF(P91="E",O91,O91*1.16)) | R91: =IF(G91="","",(G91*Q91))+IF(G91="","",(G91*N91)) -> 0 | S91: {=XLOOKUP(E91,PESOS!$B$2:$B2624,PESOS!$F$2:$F2624,"")} | T91: =IF(B91="","",N91+Q91+S91) | V91: =IF(M91="","",(L91/M91))
F92: {=IF(E92="","",XLOOKUP(E92,DATOS!$D$6:$D2624,DATOS!$C$6:$C2624,0,0,1))} | K92: =IF(I92="","", IF(J92="E",I92,I92*1.16)) | L92: =IF(I92="","",G92*K92) | N92: =IF(M92="","",K92/M92) | Q92: =IF(O92="","", IF(P92="E",O92,O92*1.16)) | R92: =IF(G92="","",(G92*Q92))+IF(G92="","",(G92*N92)) -> 0 | S92: {=XLOOKUP(E92,PESOS!$B$2:$B2624,PESOS!$F$2:$F2624,"")} | T92: =IF(B92="","",N92+Q92+S92) | V92: =IF(M92="","",(L92/M92))
F93: {=IF(E93="","",XLOOKUP(E93,DATOS!$D$6:$D2624,DATOS!$C$6:$C2624,0,0,1))} | K93: =IF(I93="","", IF(J93="E",I93,I93*1.16)) | L93: =IF(I93="","",G93*K93) | N93: =IF(M93="","",K93/M93) | Q93: =IF(O93="","", IF(P93="E",O93,O93*1.16)) | R93: =IF(G93="","",(G93*Q93))+IF(G93="","",(G93*N93)) -> 0 | S93: {=XLOOKUP(E93,PESOS!$B$2:$B2624,PESOS!$F$2:$F2624,"")} | T93: =IF(B93="","",N93+Q93+S93) | V93: =IF(M93="","",(L93/M93))
F94: {=IF(E94="","",XLOOKUP(E94,DATOS!$D$6:$D2624,DATOS!$C$6:$C2624,0,0,1))} | K94: =IF(I94="","", IF(J94="E",I94,I94*1.16)) | L94: =IF(I94="","",G94*K94) | N94: =IF(M94="","",K94/M94) | Q94: =IF(O94="","", IF(P94="E",O94,O94*1.16)) | R94: =IF(G94="","",(G94*Q94))+IF(G94="","",(G94*N94)) -> 0 | S94: {=XLOOKUP(E94,PESOS!$B$2:$B2624,PESOS!$F$2:$F2624,"")} | T94: =IF(B94="","",N94+Q94+S94) | V94: =IF(M94="","",(L94/M94))
F95: {=IF(E95="","",XLOOKUP(E95,DATOS!$D$6:$D2624,DATOS!$C$6:$C2624,0,0,1))} | K95: =IF(I95="","", IF(J95="E",I95,I95*1.16)) | L95: =IF(I95="","",G95*K95) | N95: =IF(M95="","",K95/M95) | Q95: =IF(O95="","", IF(P95="E",O95,O95*1.16)) | R95: =IF(G95="","",(G95*Q95))+IF(G95="","",(G95*N95)) -> 0 | S95: {=XLOOKUP(E95,PESOS!$B$2:$B2624,PESOS!$F$2:$F2624,"")} | T95: =IF(B95="","",N95+Q95+S95) | V95: =IF(M95="","",(L95/M95))
F96: {=IF(E96="","",XLOOKUP(E96,DATOS!$D$6:$D2624,DATOS!$C$6:$C2624,0,0,1))} | K96: =IF(I96="","", IF(J96="E",I96,I96*1.16)) | L96: =IF(I96="","",G96*K96) | N96: =IF(M96="","",K96/M96) | Q96: =IF(O96="","", IF(P96="E",O96,O96*1.16)) | R96: =IF(G96="","",(G96*Q96))+IF(G96="","",(G96*N96)) -> 0 | S96: {=XLOOKUP(E96,PESOS!$B$2:$B2624,PESOS!$F$2:$F2624,"")} | T96: =IF(B96="","",N96+Q96+S96) | V96: =IF(M96="","",(L96/M96))
F97: {=IF(E97="","",XLOOKUP(E97,DATOS!$D$6:$D2624,DATOS!$C$6:$C2624,0,0,1))} | K97: =IF(I97="","", IF(J97="E",I97,I97*1.16)) | L97: =IF(I97="","",G97*K97) | N97: =IF(M97="","",K97/M97) | Q97: =IF(O97="","", IF(P97="E",O97,O97*1.16)) | R97: =IF(G97="","",(G97*Q97))+IF(G97="","",(G97*N97)) -> 0 | S97: {=XLOOKUP(E97,PESOS!$B$2:$B2624,PESOS!$F$2:$F2624,"")} | T97: =IF(B97="","",N97+Q97+S97) | V97: =IF(M97="","",(L97/M97))
F98: {=IF(E98="","",XLOOKUP(E98,DATOS!$D$6:$D2624,DATOS!$C$6:$C2624,0,0,1))} | K98: =IF(I98="","", IF(J98="E",I98,I98*1.16)) | L98: =IF(I98="","",G98*K98) | N98: =IF(M98="","",K98/M98) | Q98: =IF(O98="","", IF(P98="E",O98,O98*1.16)) | R98: =IF(G98="","",(G98*Q98))+IF(G98="","",(G98*N98)) -> 0 | S98: {=XLOOKUP(E98,PESOS!$B$2:$B2624,PESOS!$F$2:$F2624,"")} | T98: =IF(B98="","",N98+Q98+S98) | V98: =IF(M98="","",(L98/M98))
F99: {=IF(E99="","",XLOOKUP(E99,DATOS!$D$6:$D2624,DATOS!$C$6:$C2624,0,0,1))} | K99: =IF(I99="","", IF(J99="E",I99,I99*1.16)) | L99: =IF(I99="","",G99*K99) | N99: =IF(M99="","",K99/M99) | Q99: =IF(O99="","", IF(P99="E",O99,O99*1.16)) | R99: =IF(G99="","",(G99*Q99))+IF(G99="","",(G99*N99)) -> 0 | S99: {=XLOOKUP(E99,PESOS!$B$2:$B2624,PESOS!$F$2:$F2624,"")} | T99: =IF(B99="","",N99+Q99+S99) | V99: =IF(M99="","",(L99/M99))
F100: {=IF(E100="","",XLOOKUP(E100,DATOS!$D$6:$D2624,DATOS!$C$6:$C2624,0,0,1))} | K100: =IF(I100="","", IF(J100="E",I100,I100*1.16)) | L100: =IF(I100="","",G100*K100) | N100: =IF(M100="","",K100/M100) | Q100: =IF(O100="","", IF(P100="E",O100,O100*1.16)) | R100: =IF(G100="","",(G100*Q100))+IF(G100="","",(G100*N100)) -> 0 | S100: {=XLOOKUP(E100,PESOS!$B$2:$B2624,PESOS!$F$2:$F2624,"")} | T100: =IF(B100="","",N100+Q100+S100) | V100: =IF(M100="","",(L100/M100))
...

Sheet INVENTARIO
B1: BODEGA3 | I1: EXCESO EN LA VENTA S/STOCK | L1: =TODAY() -> 46177 | N1: % UTIL PROM INV
D2: TOTALES | I2: MINIMO STOCK INVENTARIO | L2: UTILIDAD MENOR 30% | N2: =(O3-N3)/N3 -> 0.96240681
D3: =SUM(D5:D1000) -> 2486 | E3: =SUM(E5:E1000) -> 1096 | F3: =SUM(F5:F1000) -> 1390 | G3: =SUM(G5:G1000) -> 16 | H3: =SUM(H5:H1000) -> 1 | I3: REPOSICION DE MERCANCIA MAYOR O IGUAL A 3 VECES | N3: =SUM(N5:N1000) -> 368.17011 | O3: =SUM(O5:O1000) -> 722.49953
B4: PRODUCTO | C4: CODIGO | D4: ENTRADA | E4: SALIDA | F4: INV | G4: REPOSICION | H4: % REPOSICION | I4: P/VENTA | J4: P/COSTO | K4: UTIL/PROD/UNIT | L4: UTIL/PROD/TOTAL | M4: % UTIL | N4: VALOR/INV/COSTO HIST | O4: VALOR/INV/PVS
B5: {=SORT(UNIQUE(COMPRAS!E5:E1000,0,0))} -> ACEITE LA PAMPA 700ML | C5: {=IF(B5="","",XLOOKUP(B5,DATOS!D6:D1000,DATOS!C6:C1000,0,0,1))} -> 00084 | D5: =IF(B5="","", SUMIFS(COMPRAS!$G$5:$G1000,COMPRAS!$E$5:$E1000,B5)) -> 40 | E5: =IF(C5="","", SUMIFS(VENTAS!$F$5:$F1000,VENTAS!$D$5:$D1000,B5)) -> 6 | F5: =IF(B5="","",D5-E5) -> 34 | G5: =IF(B5="","",COUNTIFS(COMPRAS!$E$5:$E1000,B5)) -> 1 | H5: =IF(B5="","",G5/$G$3) -> 0.0625 | I5: =IFERROR(IF(B5="","",AVERAGEIFS(VENTAS!$G$5:$G1000,VENTAS!$D$5:$D1000,B5)),0) -> 4 | J5: =IFERROR(IF(C5="","",AVERAGEIFS(COMPRAS!$T$5:$T1000,COMPRAS!$E$5:$E1000,B5)),0) -> 1.0670177 | K5: =IF(E5=0,"",I5-J5) -> 2.9329823 | L5: =IF(B5="","",(E5*I5)-(E5*J5)) -> 17.597894 | M5: =IFERROR(IF(E5=0,"",K5/J5),"") -> 2.7487664 | N5: =F5*J5 -> 36.278601 | O5: =F5*I5 -> 136
B6: alive/detergente c/suavisante 1kg | C6: {=IF(B6="","",XLOOKUP(B6,DATOS!D7:D1000,DATOS!C7:C1000,0,0,1))} -> 00002 | D6: =IF(B6="","", SUMIFS(COMPRAS!$G$5:$G1000,COMPRAS!$E$5:$E1000,B6)) -> 24 | E6: =IF(C6="","", SUMIFS(VENTAS!$F$5:$F1000,VENTAS!$D$5:$D1000,B6)) -> 3 | F6: =IF(B6="","",D6-E6) -> 21 | G6: =IF(B6="","",COUNTIFS(COMPRAS!$E$5:$E1000,B6)) -> 1 | H6: =IF(B6="","",G6/$G$3) -> 0.0625 | I6: =IFERROR(IF(B6="","",AVERAGEIFS(VENTAS!$G$5:$G1000,VENTAS!$D$5:$D1000,B6)),0) -> 5 | J6: =IFERROR(IF(C6="","",AVERAGEIFS(COMPRAS!$T$5:$T1000,COMPRAS!$E$5:$E1000,B6)),0) -> 2.8167126 | K6: =IF(E6=0,"",I6-J6) -> 2.1832874 | L6: =IF(B6="","",(E6*I6)-(E6*J6)) -> 6.5498621 | M6: =IFERROR(IF(E6=0,"",K6/J6),"") -> 0.77511896 | N6: =F6*J6 -> 59.150965 | O6: =F6*I6 -> 105
B7: ATUN PEÑERO OLIVA VERDE | C7: {=IF(B7="","",XLOOKUP(B7,DATOS!D8:D1000,DATOS!C8:C1000,0,0,1))} -> 00116 | D7: =IF(B7="","", SUMIFS(COMPRAS!$G$5:$G1000,COMPRAS!$E$5:$E1000,B7)) -> 12 | E7: =IF(C7="","", SUMIFS(VENTAS!$F$5:$F1000,VENTAS!$D$5:$D1000,B7)) -> 38 | F7: =IF(B7="","",D7-E7) -> -26 | G7: =IF(B7="","",COUNTIFS(COMPRAS!$E$5:$E1000,B7)) -> 1 | H7: =IF(B7="","",G7/$G$3) -> 0.0625 | I7: =IFERROR(IF(B7="","",AVERAGEIFS(VENTAS!$G$5:$G1000,VENTAS!$D$5:$D1000,B7)),0) -> 3.5 | J7: =IFERROR(IF(C7="","",AVERAGEIFS(COMPRAS!$T$5:$T1000,COMPRAS!$E$5:$E1000,B7)),0) -> 2.3000379 | K7: =IF(E7=0,"",I7-J7) -> 1.1999621 | L7: =IF(B7="","",(E7*I7)-(E7*J7)) -> 45.598561 | M7: =IFERROR(IF(E7=0,"",K7/J7),"") -> 0.52171408 | N7: =F7*J7 -> -59.800984 | O7: =F7*I7 -> -91
B8: Belmont | C8: {=IF(B8="","",XLOOKUP(B8,DATOS!D9:D1000,DATOS!C9:C1000,0,0,1))} -> BELM | D8: =IF(B8="","", SUMIFS(COMPRAS!$G$5:$G1000,COMPRAS!$E$5:$E1000,B8)) -> 1000 | E8: =IF(C8="","", SUMIFS(VENTAS!$F$5:$F1000,VENTAS!$D$5:$D1000,B8)) -> 84 | F8: =IF(B8="","",D8-E8) -> 916 | G8: =IF(B8="","",COUNTIFS(COMPRAS!$E$5:$E1000,B8)) -> 1 | H8: =IF(B8="","",G8/$G$3) -> 0.0625 | I8: =IFERROR(IF(B8="","",AVERAGEIFS(VENTAS!$G$5:$G1000,VENTAS!$D$5:$D1000,B8)),0) -> 0.25 | J8: =IFERROR(IF(C8="","",AVERAGEIFS(COMPRAS!$T$5:$T1000,COMPRAS!$E$5:$E1000,B8)),0) -> 0.12950209 | K8: =IF(E8=0,"",I8-J8) -> 0.12049791 | L8: =IF(B8="","",(E8*I8)-(E8*J8)) -> 10.121824 | M8: =IFERROR(IF(E8=0,"",K8/J8),"") -> 0.93047073 | N8: =F8*J8 -> 118.62392 | O8: =F8*I8 -> 229
B9: Café Amanecer 200g | C9: {=IF(B9="","",XLOOKUP(B9,DATOS!D10:D1000,DATOS!C10:C1000,0,0,1))} -> CA1 | D9: =IF(B9="","", SUMIFS(COMPRAS!$G$5:$G1000,COMPRAS!$E$5:$E1000,B9)) -> 24 | E9: =IF(C9="","", SUMIFS(VENTAS!$F$5:$F1000,VENTAS!$D$5:$D1000,B9)) -> 42 | F9: =IF(B9="","",D9-E9) -> -18 | G9: =IF(B9="","",COUNTIFS(COMPRAS!$E$5:$E1000,B9)) -> 1 | H9: =IF(B9="","",G9/$G$3) -> 0.0625 | I9: =IFERROR(IF(B9="","",AVERAGEIFS(VENTAS!$G$5:$G1000,VENTAS!$D$5:$D1000,B9)),0) -> 3.5 | J9: =IFERROR(IF(C9="","",AVERAGEIFS(COMPRAS!$T$5:$T1000,COMPRAS!$E$5:$E1000,B9)),0) -> 2.4833739 | K9: =IF(E9=0,"",I9-J9) -> 1.0166261 | L9: =IF(B9="","",(E9*I9)-(E9*J9)) -> 42.698296 | M9: =IFERROR(IF(E9=0,"",K9/J9),"") -> 0.40937295 | N9: =F9*J9 -> -44.70073 | O9: =F9*I9 -> -63
B10: CAFE AMANECER 500GR | C10: {=IF(B10="","",XLOOKUP(B10,DATOS!D11:D1000,DATOS!C11:C1000,0,0,1))} -> 00120 | D10: =IF(B10="","", SUMIFS(COMPRAS!$G$5:$G1000,COMPRAS!$E$5:$E1000,B10)) -> 10 | E10: =IF(C10="","", SUMIFS(VENTAS!$F$5:$F1000,VENTAS!$D$5:$D1000,B10)) -> 4 | F10: =IF(B10="","",D10-E10) -> 6 | G10: =IF(B10="","",COUNTIFS(COMPRAS!$E$5:$E1000,B10)) -> 1 | H10: =IF(B10="","",G10/$G$3) -> 0.0625 | I10: =IFERROR(IF(B10="","",AVERAGEIFS(VENTAS!$G$5:$G1000,VENTAS!$D$5:$D1000,B10)),0) -> 8 | J10: =IFERROR(IF(C10="","",AVERAGEIFS(COMPRAS!$T$5:$T1000,COMPRAS!$E$5:$E1000,B10)),0) -> 6.2901022 | K10: =IF(E10=0,"",I10-J10) -> 1.7098978 | L10: =IF(B10="","",(E10*I10)-(E10*J10)) -> 6.8395911 | M10: =IFERROR(IF(E10=0,"",K10/J10),"") -> 0.27183943 | N10: =F10*J10 -> 37.740613 | O10: =F10*I10 -> 48
B11: Cubitos | C11: {=IF(B11="","",XLOOKUP(B11,DATOS!D12:D1000,DATOS!C12:C1000,0,0,1))} -> CUBITO1 | D11: =IF(B11="","", SUMIFS(COMPRAS!$G$5:$G1000,COMPRAS!$E$5:$E1000,B11)) -> 250 | E11: =IF(C11="","", SUMIFS(VENTAS!$F$5:$F1000,VENTAS!$D$5:$D1000,B11)) -> 51 | F11: =IF(B11="","",D11-E11) -> 199 | G11: =IF(B11="","",COUNTIFS(COMPRAS!$E$5:$E1000,B11)) -> 1 | H11: =IF(B11="","",G11/$G$3) -> 0.0625 | I11: =IFERROR(IF(B11="","",AVERAGEIFS(VENTAS!$G$5:$G1000,VENTAS!$D$5:$D1000,B11)),0) -> 0.5 | J11: =IFERROR(IF(C11="","",AVERAGEIFS(COMPRAS!$T$5:$T1000,COMPRAS!$E$5:$E1000,B11)),0) -> 0.18200289 | K11: =IF(E11=0,"",I11-J11) -> 0.31799711 | L11: =IF(B11="","",(E11*I11)-(E11*J11)) -> 16.217853 | M11: =IFERROR(IF(E11=0,"",K11/J11),"") -> 1.7472091 | N11: =F11*J11 -> 36.218575 | O11: =F11*I11 -> 99.5
B12: DETERGENTE ALIVE 500GR | C12: {=IF(B12="","",XLOOKUP(B12,DATOS!D13:D1000,DATOS!C13:C1000,0,0,1))} -> 00098 | D12: =IF(B12="","", SUMIFS(COMPRAS!$G$5:$G1000,COMPRAS!$E$5:$E1000,B12)) -> 48 | E12: =IF(C12="","", SUMIFS(VENTAS!$F$5:$F1000,VENTAS!$D$5:$D1000,B12)) -> 4 | F12: =IF(B12="","",D12-E12) -> 44 | G12: =IF(B12="","",COUNTIFS(COMPRAS!$E$5:$E1000,B12)) -> 1 | H12: =IF(B12="","",G12/$G$3) -> 0.0625 | I12: =IFERROR(IF(B12="","",AVERAGEIFS(VENTAS!$G$5:$G1000,VENTAS!$D$5:$D1000,B12)),0) -> 2.5 | J12: =IFERROR(IF(C12="","",AVERAGEIFS(COMPRAS!$T$5:$T1000,COMPRAS!$E$5:$E1000,B12)),0) -> 1.4083563 | K12: =IF(E12=0,"",I12-J12) -> 1.0916437 | L12: =IF(B12="","",(E12*I12)-(E12*J12)) -> 4.3665747 | M12: =IFERROR(IF(E12=0,"",K12/J12),"") -> 0.77511896 | N12: =F12*J12 -> 61.967678 | O12: =F12*I12 -> 110
B13: Huevo | C13: {=IF(B13="","",XLOOKUP(B13,DATOS!D14:D1000,DATOS!C14:C1000,0,0,1))} -> HUEVO | D13: =IF(B13="","", SUMIFS(COMPRAS!$G$5:$G1000,COMPRAS!$E$5:$E1000,B13)) -> 720 | E13: =IF(C13="","", SUMIFS(VENTAS!$F$5:$F1000,VENTAS!$D$5:$D1000,B13)) -> 699 | F13: =IF(B13="","",D13-E13) -> 21 | G13: =IF(B13="","",COUNTIFS(COMPRAS!$E$5:$E1000,B13)) -> 1 | H13: =IF(B13="","",G13/$G$3) -> 0.0625 | I13: =IFERROR(IF(B13="","",AVERAGEIFS(VENTAS!$G$5:$G1000,VENTAS!$D$5:$D1000,B13)),0) -> 0.33331101 | J13: =IFERROR(IF(C13="","",AVERAGEIFS(COMPRAS!$T$5:$T1000,COMPRAS!$E$5:$E1000,B13)),0) -> 0.0625 | K13: =IF(E13=0,"",I13-J13) -> 0.27081101 | L13: =IF(B13="","",(E13*I13)-(E13*J13)) -> 189.2969 | M13: =IFERROR(IF(E13=0,"",K13/J13),"") -> 4.3329762 | N13: =F13*J13 -> 1.3125 | O13: =F13*I13 -> 6.9995312
B14: MARGARINA MAVESA 250GR | C14: {=IF(B14="","",XLOOKUP(B14,DATOS!D15:D1000,DATOS!C15:C1000,0,0,1))} -> MARG1 | D14: =IF(B14="","", SUMIFS(COMPRAS!$G$5:$G1000,COMPRAS!$E$5:$E1000,B14)) -> 24 | E14: =IF(C14="","", SUMIFS(VENTAS!$F$5:$F1000,VENTAS!$D$5:$D1000,B14)) -> 15 | F14: =IF(B14="","",D14-E14) -> 9 | G14: =IF(B14="","",COUNTIFS(COMPRAS!$E$5:$E1000,B14)) -> 1 | H14: =IF(B14="","",G14/$G$3) -> 0.0625 | I14: =IFERROR(IF(B14="","",AVERAGEIFS(VENTAS!$G$5:$G1000,VENTAS!$D$5:$D1000,B14)),0) -> 3 | J14: =IFERROR(IF(C14="","",AVERAGEIFS(COMPRAS!$T$5:$T1000,COMPRAS!$E$5:$E1000,B14)),0) -> 8.3575234 | K14: =IF(E14=0,"",I14-J14) -> -5.3575234 | L14: =IF(B14="","",(E14*I14)-(E14*J14)) -> -80.362851 | M14: =IFERROR(IF(E14=0,"",K14/J14),"") -> -0.64104199 | N14: =F14*J14 -> 75.217711 | O14: =F14*I14 -> 27
B15: MARGARINA MAVESA 500GR | C15: {=IF(B15="","",XLOOKUP(B15,DATOS!D16:D1000,DATOS!C16:C1000,0,0,1))} -> MARG2 | D15: =IF(B15="","", SUMIFS(COMPRAS!$G$5:$G1000,COMPRAS!$E$5:$E1000,B15)) -> 12 | E15: =IF(C15="","", SUMIFS(VENTAS!$F$5:$F1000,VENTAS!$D$5:$D1000,B15)) -> 20 | F15: =IF(B15="","",D15-E15) -> -8 | G15: =IF(B15="","",COUNTIFS(COMPRAS!$E$5:$E1000,B15)) -> 1 | H15: =IF(B15="","",G15/$G$3) -> 0.0625 | I15: =IFERROR(IF(B15="","",AVERAGEIFS(VENTAS!$G$5:$G1000,VENTAS!$D$5:$D1000,B15)),0) -> 4 | J15: =IFERROR(IF(C15="","",AVERAGEIFS(COMPRAS!$T$5:$T1000,COMPRAS!$E$5:$E1000,B15)),0) -> 9.2575423 | K15: =IF(E15=0,"",I15-J15) -> -5.2575423 | L15: =IF(B15="","",(E15*I15)-(E15*J15)) -> -105.15085 | M15: =IFERROR(IF(E15=0,"",K15/J15),"") -> -0.56791988 | N15: =F15*J15 -> -74.060339 | O15: =F15*I15 -> -32
B16: Mayonesa Mavesa 445gr | C16: {=IF(B16="","",XLOOKUP(B16,DATOS!D17:D1000,DATOS!C17:C1000,0,0,1))} -> MAYO2 | D16: =IF(B16="","", SUMIFS(COMPRAS!$G$5:$G1000,COMPRAS!$E$5:$E1000,B16)) -> 12 | E16: =IF(C16="","", SUMIFS(VENTAS!$F$5:$F1000,VENTAS!$D$5:$D1000,B16)) -> 8 | F16: =IF(B16="","",D16-E16) -> 4 | G16: =IF(B16="","",COUNTIFS(COMPRAS!$E$5:$E1000,B16)) -> 1 | H16: =IF(B16="","",G16/$G$3) -> 0.0625 | I16: =IFERROR(IF(B16="","",AVERAGEIFS(VENTAS!$G$5:$G1000,VENTAS!$D$5:$D1000,B16)),0) -> 5.5 | J16: =IFERROR(IF(C16="","",AVERAGEIFS(COMPRAS!$T$5:$T1000,COMPRAS!$E$5:$E1000,B16)),0) -> 11.648386 | K16: =IF(E16=0,"",I16-J16) -> -6.1483855 | L16: =IF(B16="","",(E16*I16)-(E16*J16)) -> -49.187084 | M16: =IFERROR(IF(E16=0,"",K16/J16),"") -> -0.52783156 | N16: =F16*J16 -> 46.593542 | O16: =F16*I16 -> 22
B17: MAYONESA MAVESA 900GR | C17: {=IF(B17="","",XLOOKUP(B17,DATOS!D18:D1000,DATOS!C18:C1000,0,0,1))} -> 00118 | D17: =IF(B17="","", SUMIFS(COMPRAS!$G$5:$G1000,COMPRAS!$E$5:$E1000,B17)) -> 2 | E17: =IF(C17="","", SUMIFS(VENTAS!$F$5:$F1000,VENTAS!$D$5:$D1000,B17)) -> 2 | F17: =IF(B17="","",D17-E17) -> 0 | G17: =IF(B17="","",COUNTIFS(COMPRAS!$E$5:$E1000,B17)) -> 1 | H17: =IF(B17="","",G17/$G$3) -> 0.0625 | I17: =IFERROR(IF(B17="","",AVERAGEIFS(VENTAS!$G$5:$G1000,VENTAS!$D$5:$D1000,B17)),0) -> 10 | J17: =IFERROR(IF(C17="","",AVERAGEIFS(COMPRAS!$T$5:$T1000,COMPRAS!$E$5:$E1000,B17)),0) -> 6.9001136 | K17: =IF(E17=0,"",I17-J17) -> 3.0998864 | L17: =IF(B17="","",(E17*I17)-(E17*J17)) -> 6.1997728 | M17: =IFERROR(IF(E17=0,"",K17/J17),"") -> 0.44925151 | N17: =F17*J17 -> 0 | O17: =F17*I17 -> 0
B18: MORTADELA ALIBAL 500GR | C18: {=IF(B18="","",XLOOKUP(B18,DATOS!D19:D1000,DATOS!C19:C1000,0,0,1))} -> MOR04 | D18: =IF(B18="","", SUMIFS(COMPRAS!$G$5:$G1000,COMPRAS!$E$5:$E1000,B18)) -> 20 | E18: =IF(C18="","", SUMIFS(VENTAS!$F$5:$F1000,VENTAS!$D$5:$D1000,B18)) -> 14 | F18: =IF(B18="","",D18-E18) -> 6 | G18: =IF(B18="","",COUNTIFS(COMPRAS!$E$5:$E1000,B18)) -> 1 | H18: =IF(B18="","",G18/$G$3) -> 0.0625 | I18: =IFERROR(IF(B18="","",AVERAGEIFS(VENTAS!$G$5:$G1000,VENTAS!$D$5:$D1000,B18)),0) -> 3 | J18: =IFERROR(IF(C18="","",AVERAGEIFS(COMPRAS!$T$5:$T1000,COMPRAS!$E$5:$E1000,B18)),0) -> 2.1965001 | K18: =IF(E18=0,"",I18-J18) -> 0.80349992 | L18: =IF(B18="","",(E18*I18)-(E18*J18)) -> 11.248999 | M18: =IFERROR(IF(E18=0,"",K18/J18),"") -> 0.36580919 | N18: =F18*J18 -> 13.179 | O18: =F18*I18 -> 18
B19: Pañal Baby finger XG | C19: {=IF(B19="","",XLOOKUP(B19,DATOS!D20:D1000,DATOS!C20:C1000,0,0,1))} -> PAÑL1 | D19: =IF(B19="","", SUMIFS(COMPRAS!$G$5:$G1000,COMPRAS!$E$5:$E1000,B19)) -> 192 | E19: =IF(C19="","", SUMIFS(VENTAS!$F$5:$F1000,VENTAS!$D$5:$D1000,B19)) -> 26 | F19: =IF(B19="","",D19-E19) -> 166 | G19: =IF(B19="","",COUNTIFS(COMPRAS!$E$5:$E1000,B19)) -> 1 | H19: =IF(B19="","",G19/$G$3) -> 0.0625 | I19: =IFERROR(IF(B19="","",AVERAGEIFS(VENTAS!$G$5:$G1000,VENTAS!$D$5:$D1000,B19)),0) -> 0.5 | J19: =IFERROR(IF(C19="","",AVERAGEIFS(COMPRAS!$T$5:$T1000,COMPRAS!$E$5:$E1000,B19)),0) -> 0.29993307 | K19: =IF(E19=0,"",I19-J19) -> 0.20006693 | L19: =IF(B19="","",(E19*I19)-(E19*J19)) -> 5.2017402 | M19: =IFERROR(IF(E19=0,"",K19/J19),"") -> 0.66703859 | N19: =F19*J19 -> 49.788889 | O19: =F19*I19 -> 83
B20: Sardina Omega | C20: {=IF(B20="","",XLOOKUP(B20,DATOS!D21:D1000,DATOS!C21:C1000,0,0,1))} -> SAR3 | D20: =IF(B20="","", SUMIFS(COMPRAS!$G$5:$G1000,COMPRAS!$E$5:$E1000,B20)) -> 96 | E20: =IF(C20="","", SUMIFS(VENTAS!$F$5:$F1000,VENTAS!$D$5:$D1000,B20)) -> 80 | F20: =IF(B20="","",D20-E20) -> 16 | G20: =IF(B20="","",COUNTIFS(COMPRAS!$E$5:$E1000,B20)) -> 1 | H20: =IF(B20="","",G20/$G$3) -> 0.0625 | I20: =IFERROR(IF(B20="","",AVERAGEIFS(VENTAS!$G$5:$G1000,VENTAS!$D$5:$D1000,B20)),0) -> 1.5 | J20: =IFERROR(IF(C20="","",AVERAGEIFS(COMPRAS!$T$5:$T1000,COMPRAS!$E$5:$E1000,B20)),0) -> 0.66626068 | K20: =IF(E20=0,"",I20-J20) -> 0.83373932 | L20: =IF(B20="","",(E20*I20)-(E20*J20)) -> 66.699145 | M20: =IFERROR(IF(E20=0,"",K20/J20),"") -> 1.251371 | N20: =F20*J20 -> 10.660171 | O20: =F20*I20 -> 24
C21: {=IF(B21="","",XLOOKUP(B21,DATOS!D22:D1000,DATOS!C22:C1000,0,0,1))} | D21: =IF(B21="","", SUMIFS(COMPRAS!$G$5:$G1000,COMPRAS!$E$5:$E1000,B21)) | E21: =IF(C21="","", SUMIFS(VENTAS!$F$5:$F1000,VENTAS!$D$5:$D1000,B21)) | F21: =IF(B21="","",D21-E21) | G21: =IF(B21="","",COUNTIFS(COMPRAS!$E$5:$E1000,B21)) | H21: =IF(B21="","",G21/$G$3) | I21: =IFERROR(IF(B21="","",AVERAGEIFS(VENTAS!$G$5:$G1000,VENTAS!$D$5:$D1000,B21)),0) | J21: =IFERROR(IF(C21="","",AVERAGEIFS(COMPRAS!$T$5:$T1000,COMPRAS!$E$5:$E1000,B21)),0) | K21: =IF(E21=0,"",I21-J21) -> 0 | L21: =IF(B21="","",(E21*I21)-(E21*J21)) | M21: =IFERROR(IF(E21=0,"",K21/J21),"") | N21: =F21*J21 -> 0 | O21: =F21*I21 -> 0
C22: {=IF(B22="","",XLOOKUP(B22,DATOS!D23:D1000,DATOS!C23:C1000,0,0,1))} | D22: =IF(B22="","", SUMIFS(COMPRAS!$G$5:$G1000,COMPRAS!$E$5:$E1000,B22)) | E22: =IF(C22="","", SUMIFS(VENTAS!$F$5:$F1000,VENTAS!$D$5:$D1000,B22)) | F22: =IF(B22="","",D22-E22) | G22: =IF(B22="","",COUNTIFS(COMPRAS!$E$5:$E1000,B22)) | H22: =IF(B22="","",G22/$G$3) | I22: =IFERROR(IF(B22="","",AVERAGEIFS(VENTAS!$G$5:$G1000,VENTAS!$D$5:$D1000,B22)),0) | J22: =IFERROR(IF(C22="","",AVERAGEIFS(COMPRAS!$T$5:$T1000,COMPRAS!$E$5:$E1000,B22)),0) | K22: =IF(E22=0,"",I22-J22) -> 0 | L22: =IF(B22="","",(E22*I22)-(E22*J22)) | M22: =IFERROR(IF(E22=0,"",K22/J22),"") | N22: =F22*J22 -> 0 | O22: =F22*I22 -> 0
C23: {=IF(B23="","",XLOOKUP(B23,DATOS!D24:D1000,DATOS!C24:C1000,0,0,1))} | D23: =IF(B23="","", SUMIFS(COMPRAS!$G$5:$G1000,COMPRAS!$E$5:$E1000,B23)) | E23: =IF(C23="","", SUMIFS(VENTAS!$F$5:$F1000,VENTAS!$D$5:$D1000,B23)) | F23: =IF(B23="","",D23-E23) | G23: =IF(B23="","",COUNTIFS(COMPRAS!$E$5:$E1000,B23)) | H23: =IF(B23="","",G23/$G$3) | I23: =IFERROR(IF(B23="","",AVERAGEIFS(VENTAS!$G$5:$G1000,VENTAS!$D$5:$D1000,B23)),0) | J23: =IFERROR(IF(C23="","",AVERAGEIFS(COMPRAS!$T$5:$T1000,COMPRAS!$E$5:$E1000,B23)),0) | K23: =IF(E23=0,"",I23-J23) -> 0 | L23: =IF(B23="","",(E23*I23)-(E23*J23)) | M23: =IFERROR(IF(E23=0,"",K23/J23),"") | N23: =F23*J23 -> 0 | O23: =F23*I23 -> 0
C24: {=IF(B24="","",XLOOKUP(B24,DATOS!D25:D1000,DATOS!C25:C1000,0,0,1))} | D24: =IF(B24="","", SUMIFS(COMPRAS!$G$5:$G1000,COMPRAS!$E$5:$E1000,B24)) | E24: =IF(C24="","", SUMIFS(VENTAS!$F$5:$F1000,VENTAS!$D$5:$D1000,B24)) | F24: =IF(B24="","",D24-E24) | G24: =IF(B24="","",COUNTIFS(COMPRAS!$E$5:$E1000,B24)) | H24: =IF(B24="","",G24/$G$3) | I24: =IFERROR(IF(B24="","",AVERAGEIFS(VENTAS!$G$5:$G1000,VENTAS!$D$5:$D1000,B24)),0) | J24: =IFERROR(IF(C24="","",AVERAGEIFS(COMPRAS!$T$5:$T1000,COMPRAS!$E$5:$E1000,B24)),0) | K24: =IF(E24=0,"",I24-J24) -> 0 | L24: =IF(B24="","",(E24*I24)-(E24*J24)) | M24: =IFERROR(IF(E24=0,"",K24/J24),"") | N24: =F24*J24 -> 0 | O24: =F24*I24 -> 0
C25: {=IF(B25="","",XLOOKUP(B25,DATOS!D26:D1000,DATOS!C26:C1000,0,0,1))} | D25: =IF(B25="","", SUMIFS(COMPRAS!$G$5:$G1000,COMPRAS!$E$5:$E1000,B25)) | E25: =IF(C25="","", SUMIFS(VENTAS!$F$5:$F1000,VENTAS!$D$5:$D1000,B25)) | F25: =IF(B25="","",D25-E25) | G25: =IF(B25="","",COUNTIFS(COMPRAS!$E$5:$E1000,B25)) | H25: =IF(B25="","",G25/$G$3) | I25: =IFERROR(IF(B25="","",AVERAGEIFS(VENTAS!$G$5:$G1000,VENTAS!$D$5:$D1000,B25)),0) | J25: =IFERROR(IF(C25="","",AVERAGEIFS(COMPRAS!$T$5:$T1000,COMPRAS!$E$5:$E1000,B25)),0) | K25: =IF(E25=0,"",I25-J25) -> 0 | L25: =IF(B25="","",(E25*I25)-(E25*J25)) | M25: =IFERROR(IF(E25=0,"",K25/J25),"") | N25: =F25*J25 -> 0 | O25: =F25*I25 -> 0
C26: {=IF(B26="","",XLOOKUP(B26,DATOS!D27:D1000,DATOS!C27:C1000,0,0,1))} | D26: =IF(B26="","", SUMIFS(COMPRAS!$G$5:$G1000,COMPRAS!$E$5:$E1000,B26)) | E26: =IF(C26="","", SUMIFS(VENTAS!$F$5:$F1000,VENTAS!$D$5:$D1000,B26)) | F26: =IF(B26="","",D26-E26) | G26: =IF(B26="","",COUNTIFS(COMPRAS!$E$5:$E1000,B26)) | H26: =IF(B26="","",G26/$G$3) | I26: =IFERROR(IF(B26="","",AVERAGEIFS(VENTAS!$G$5:$G1000,VENTAS!$D$5:$D1000,B26)),0) | J26: =IFERROR(IF(C26="","",AVERAGEIFS(COMPRAS!$T$5:$T1000,COMPRAS!$E$5:$E1000,B26)),0) | K26: =IF(E26=0,"",I26-J26) -> 0 | L26: =IF(B26="","",(E26*I26)-(E26*J26)) | M26: =IFERROR(IF(E26=0,"",K26/J26),"") | N26: =F26*J26 -> 0 | O26: =F26*I26 -> 0
C27: {=IF(B27="","",XLOOKUP(B27,DATOS!D28:D1000,DATOS!C28:C1000,0,0,1))} | D27: =IF(B27="","", SUMIFS(COMPRAS!$G$5:$G1000,COMPRAS!$E$5:$E1000,B27)) | E27: =IF(C27="","", SUMIFS(VENTAS!$F$5:$F1000,VENTAS!$D$5:$D1000,B27)) | F27: =IF(B27="","",D27-E27) | G27: =IF(B27="","",COUNTIFS(COMPRAS!$E$5:$E1000,B27)) | H27: =IF(B27="","",G27/$G$3) | I27: =IFERROR(IF(B27="","",AVERAGEIFS(VENTAS!$G$5:$G1000,VENTAS!$D$5:$D1000,B27)),0) | J27: =IFERROR(IF(C27="","",AVERAGEIFS(COMPRAS!$T$5:$T1000,COMPRAS!$E$5:$E1000,B27)),0) | K27: =IF(E27=0,"",I27-J27) -> 0 | L27: =IF(B27="","",(E27*I27)-(E27*J27)) | M27: =IFERROR(IF(E27=0,"",K27/J27),"") | N27: =F27*J27 -> 0 | O27: =F27*I27 -> 0
C28: {=IF(B28="","",XLOOKUP(B28,DATOS!D29:D1000,DATOS!C29:C1000,0,0,1))} | D28: =IF(B28="","", SUMIFS(COMPRAS!$G$5:$G1000,COMPRAS!$E$5:$E1000,B28)) | E28: =IF(C28="","", SUMIFS(VENTAS!$F$5:$F1000,VENTAS!$D$5:$D1000,B28)) | F28: =IF(B28="","",D28-E28) | G28: =IF(B28="","",COUNTIFS(COMPRAS!$E$5:$E1000,B28)) | H28: =IF(B28="","",G28/$G$3) | I28: =IFERROR(IF(B28="","",AVERAGEIFS(VENTAS!$G$5:$G1000,VENTAS!$D$5:$D1000,B28)),0) | J28: =IFERROR(IF(C28="","",AVERAGEIFS(COMPRAS!$T$5:$T1000,COMPRAS!$E$5:$E1000,B28)),0) | K28: =IF(E28=0,"",I28-J28) -> 0 | L28: =IF(B28="","",(E28*I28)-(E28*J28)) | M28: =IFERROR(IF(E28=0,"",K28/J28),"") | N28: =F28*J28 -> 0 | O28: =F28*I28 -> 0
C29: {=IF(B29="","",XLOOKUP(B29,DATOS!D30:D1000,DATOS!C30:C1000,0,0,1))} | D29: =IF(B29="","", SUMIFS(COMPRAS!$G$5:$G1000,COMPRAS!$E$5:$E1000,B29)) | E29: =IF(C29="","", SUMIFS(VENTAS!$F$5:$F1000,VENTAS!$D$5:$D1000,B29)) | F29: =IF(B29="","",D29-E29) | G29: =IF(B29="","",COUNTIFS(COMPRAS!$E$5:$E1000,B29)) | H29: =IF(B29="","",G29/$G$3) | I29: =IFERROR(IF(B29="","",AVERAGEIFS(VENTAS!$G$5:$G1000,VENTAS!$D$5:$D1000,B29)),0) | J29: =IFERROR(IF(C29="","",AVERAGEIFS(COMPRAS!$T$5:$T1000,COMPRAS!$E$5:$E1000,B29)),0) | K29: =IF(E29=0,"",I29-J29) -> 0 | L29: =IF(B29="","",(E29*I29)-(E29*J29)) | M29: =IFERROR(IF(E29=0,"",K29/J29),"") | N29: =F29*J29 -> 0 | O29: =F29*I29 -> 0
C30: {=IF(B30="","",XLOOKUP(B30,DATOS!D31:D1000,DATOS!C31:C1000,0,0,1))} | D30: =IF(B30="","", SUMIFS(COMPRAS!$G$5:$G1000,COMPRAS!$E$5:$E1000,B30)) | E30: =IF(C30="","", SUMIFS(VENTAS!$F$5:$F1000,VENTAS!$D$5:$D1000,B30)) | F30: =IF(B30="","",D30-E30) | G30: =IF(B30="","",COUNTIFS(COMPRAS!$E$5:$E1000,B30)) | H30: =IF(B30="","",G30/$G$3) | I30: =IFERROR(IF(B30="","",AVERAGEIFS(VENTAS!$G$5:$G1000,VENTAS!$D$5:$D1000,B30)),0) | J30: =IFERROR(IF(C30="","",AVERAGEIFS(COMPRAS!$T$5:$T1000,COMPRAS!$E$5:$E1000,B30)),0) | K30: =IF(E30=0,"",I30-J30) -> 0 | L30: =IF(B30="","",(E30*I30)-(E30*J30)) | M30: =IFERROR(IF(E30=0,"",K30/J30),"") | N30: =F30*J30 -> 0 | O30: =F30*I30 -> 0
C31: {=IF(B31="","",XLOOKUP(B31,DATOS!D32:D1000,DATOS!C32:C1000,0,0,1))} | D31: =IF(B31="","", SUMIFS(COMPRAS!$G$5:$G1000,COMPRAS!$E$5:$E1000,B31)) | E31: =IF(C31="","", SUMIFS(VENTAS!$F$5:$F1000,VENTAS!$D$5:$D1000,B31)) | F31: =IF(B31="","",D31-E31) | G31: =IF(B31="","",COUNTIFS(COMPRAS!$E$5:$E1000,B31)) | H31: =IF(B31="","",G31/$G$3) | I31: =IFERROR(IF(B31="","",AVERAGEIFS(VENTAS!$G$5:$G1000,VENTAS!$D$5:$D1000,B31)),0) | J31: =IFERROR(IF(C31="","",AVERAGEIFS(COMPRAS!$T$5:$T1000,COMPRAS!$E$5:$E1000,B31)),0) | K31: =IF(E31=0,"",I31-J31) -> 0 | L31: =IF(B31="","",(E31*I31)-(E31*J31)) | M31: =IFERROR(IF(E31=0,"",K31/J31),"") | N31: =F31*J31 -> 0 | O31: =F31*I31 -> 0
C32: {=IF(B32="","",XLOOKUP(B32,DATOS!D33:D1000,DATOS!C33:C1000,0,0,1))} | D32: =IF(B32="","", SUMIFS(COMPRAS!$G$5:$G1000,COMPRAS!$E$5:$E1000,B32)) | E32: =IF(C32="","", SUMIFS(VENTAS!$F$5:$F1000,VENTAS!$D$5:$D1000,B32)) | F32: =IF(B32="","",D32-E32) | G32: =IF(B32="","",COUNTIFS(COMPRAS!$E$5:$E1000,B32)) | H32: =IF(B32="","",G32/$G$3) | I32: =IFERROR(IF(B32="","",AVERAGEIFS(VENTAS!$G$5:$G1000,VENTAS!$D$5:$D1000,B32)),0) | J32: =IFERROR(IF(C32="","",AVERAGEIFS(COMPRAS!$T$5:$T1000,COMPRAS!$E$5:$E1000,B32)),0) | K32: =IF(E32=0,"",I32-J32) -> 0 | L32: =IF(B32="","",(E32*I32)-(E32*J32)) | M32: =IFERROR(IF(E32=0,"",K32/J32),"") | N32: =F32*J32 -> 0 | O32: =F32*I32 -> 0
C33: {=IF(B33="","",XLOOKUP(B33,DATOS!D34:D1000,DATOS!C34:C1000,0,0,1))} | D33: =IF(B33="","", SUMIFS(COMPRAS!$G$5:$G1000,COMPRAS!$E$5:$E1000,B33)) | E33: =IF(C33="","", SUMIFS(VENTAS!$F$5:$F1000,VENTAS!$D$5:$D1000,B33)) | F33: =IF(B33="","",D33-E33) | G33: =IF(B33="","",COUNTIFS(COMPRAS!$E$5:$E1000,B33)) | H33: =IF(B33="","",G33/$G$3) | I33: =IFERROR(IF(B33="","",AVERAGEIFS(VENTAS!$G$5:$G1000,VENTAS!$D$5:$D1000,B33)),0) | J33: =IFERROR(IF(C33="","",AVERAGEIFS(COMPRAS!$T$5:$T1000,COMPRAS!$E$5:$E1000,B33)),0) | K33: =IF(E33=0,"",I33-J33) -> 0 | L33: =IF(B33="","",(E33*I33)-(E33*J33)) | M33: =IFERROR(IF(E33=0,"",K33/J33),"") | N33: =F33*J33 -> 0 | O33: =F33*I33 -> 0
C34: {=IF(B34="","",XLOOKUP(B34,DATOS!D35:D1000,DATOS!C35:C1000,0,0,1))} | D34: =IF(B34="","", SUMIFS(COMPRAS!$G$5:$G1000,COMPRAS!$E$5:$E1000,B34)) | E34: =IF(C34="","", SUMIFS(VENTAS!$F$5:$F1000,VENTAS!$D$5:$D1000,B34)) | F34: =IF(B34="","",D34-E34) | G34: =IF(B34="","",COUNTIFS(COMPRAS!$E$5:$E1000,B34)) | H34: =IF(B34="","",G34/$G$3) | I34: =IFERROR(IF(B34="","",AVERAGEIFS(VENTAS!$G$5:$G1000,VENTAS!$D$5:$D1000,B34)),0) | J34: =IFERROR(IF(C34="","",AVERAGEIFS(COMPRAS!$T$5:$T1000,COMPRAS!$E$5:$E1000,B34)),0) | K34: =IF(E34=0,"",I34-J34) -> 0 | L34: =IF(B34="","",(E34*I34)-(E34*J34)) | M34: =IFERROR(IF(E34=0,"",K34/J34),"") | N34: =F34*J34 -> 0 | O34: =F34*I34 -> 0
C35: {=IF(B35="","",XLOOKUP(B35,DATOS!D36:D1000,DATOS!C36:C1000,0,0,1))} | D35: =IF(B35="","", SUMIFS(COMPRAS!$G$5:$G1000,COMPRAS!$E$5:$E1000,B35)) | E35: =IF(C35="","", SUMIFS(VENTAS!$F$5:$F1000,VENTAS!$D$5:$D1000,B35)) | F35: =IF(B35="","",D35-E35) | G35: =IF(B35="","",COUNTIFS(COMPRAS!$E$5:$E1000,B35)) | H35: =IF(B35="","",G35/$G$3) | I35: =IFERROR(IF(B35="","",AVERAGEIFS(VENTAS!$G$5:$G1000,VENTAS!$D$5:$D1000,B35)),0) | J35: =IFERROR(IF(C35="","",AVERAGEIFS(COMPRAS!$T$5:$T1000,COMPRAS!$E$5:$E1000,B35)),0) | K35: =IF(E35=0,"",I35-J35) -> 0 | L35: =IF(B35="","",(E35*I35)-(E35*J35)) | M35: =IFERROR(IF(E35=0,"",K35/J35),"") | N35: =F35*J35 -> 0 | O35: =F35*I35 -> 0
C36: {=IF(B36="","",XLOOKUP(B36,DATOS!D37:D1000,DATOS!C37:C1000,0,0,1))} | D36: =IF(B36="","", SUMIFS(COMPRAS!$G$5:$G1000,COMPRAS!$E$5:$E1000,B36)) | E36: =IF(C36="","", SUMIFS(VENTAS!$F$5:$F1000,VENTAS!$D$5:$D1000,B36)) | F36: =IF(B36="","",D36-E36) | G36: =IF(B36="","",COUNTIFS(COMPRAS!$E$5:$E1000,B36)) | H36: =IF(B36="","",G36/$G$3) | I36: =IFERROR(IF(B36="","",AVERAGEIFS(VENTAS!$G$5:$G1000,VENTAS!$D$5:$D1000,B36)),0) | J36: =IFERROR(IF(C36="","",AVERAGEIFS(COMPRAS!$T$5:$T1000,COMPRAS!$E$5:$E1000,B36)),0) | K36: =IF(E36=0,"",I36-J36) -> 0 | L36: =IF(B36="","",(E36*I36)-(E36*J36)) | M36: =IFERROR(IF(E36=0,"",K36/J36),"") | N36: =F36*J36 -> 0 | O36: =F36*I36 -> 0
C37: {=IF(B37="","",XLOOKUP(B37,DATOS!D38:D1000,DATOS!C38:C1000,0,0,1))} | D37: =IF(B37="","", SUMIFS(COMPRAS!$G$5:$G1000,COMPRAS!$E$5:$E1000,B37)) | E37: =IF(C37="","", SUMIFS(VENTAS!$F$5:$F1000,VENTAS!$D$5:$D1000,B37)) | F37: =IF(B37="","",D37-E37) | G37: =IF(B37="","",COUNTIFS(COMPRAS!$E$5:$E1000,B37)) | H37: =IF(B37="","",G37/$G$3) | I37: =IFERROR(IF(B37="","",AVERAGEIFS(VENTAS!$G$5:$G1000,VENTAS!$D$5:$D1000,B37)),0) | J37: =IFERROR(IF(C37="","",AVERAGEIFS(COMPRAS!$T$5:$T1000,COMPRAS!$E$5:$E1000,B37)),0) | K37: =IF(E37=0,"",I37-J37) -> 0 | L37: =IF(B37="","",(E37*I37)-(E37*J37)) | M37: =IFERROR(IF(E37=0,"",K37/J37),"") | N37: =F37*J37 -> 0 | O37: =F37*I37 -> 0
C38: {=IF(B38="","",XLOOKUP(B38,DATOS!D39:D1000,DATOS!C39:C1000,0,0,1))} | D38: =IF(B38="","", SUMIFS(COMPRAS!$G$5:$G1000,COMPRAS!$E$5:$E1000,B38)) | E38: =IF(C38="","", SUMIFS(VENTAS!$F$5:$F1000,VENTAS!$D$5:$D1000,B38)) | F38: =IF(B38="","",D38-E38) | G38: =IF(B38="","",COUNTIFS(COMPRAS!$E$5:$E1000,B38)) | H38: =IF(B38="","",G38/$G$3) | I38: =IFERROR(IF(B38="","",AVERAGEIFS(VENTAS!$G$5:$G1000,VENTAS!$D$5:$D1000,B38)),0) | J38: =IFERROR(IF(C38="","",AVERAGEIFS(COMPRAS!$T$5:$T1000,COMPRAS!$E$5:$E1000,B38)),0) | K38: =IF(E38=0,"",I38-J38) -> 0 | L38: =IF(B38="","",(E38*I38)-(E38*J38)) | M38: =IFERROR(IF(E38=0,"",K38/J38),"") | N38: =F38*J38 -> 0 | O38: =F38*I38 -> 0
C39: {=IF(B39="","",XLOOKUP(B39,DATOS!D40:D1000,DATOS!C40:C1000,0,0,1))} | D39: =IF(B39="","", SUMIFS(COMPRAS!$G$5:$G1000,COMPRAS!$E$5:$E1000,B39)) | E39: =IF(C39="","", SUMIFS(VENTAS!$F$5:$F1000,VENTAS!$D$5:$D1000,B39)) | F39: =IF(B39="","",D39-E39) | G39: =IF(B39="","",COUNTIFS(COMPRAS!$E$5:$E1000,B39)) | H39: =IF(B39="","",G39/$G$3) | I39: =IFERROR(IF(B39="","",AVERAGEIFS(VENTAS!$G$5:$G1000,VENTAS!$D$5:$D1000,B39)),0) | J39: =IFERROR(IF(C39="","",AVERAGEIFS(COMPRAS!$T$5:$T1000,COMPRAS!$E$5:$E1000,B39)),0) | K39: =IF(E39=0,"",I39-J39) -> 0 | L39: =IF(B39="","",(E39*I39)-(E39*J39)) | M39: =IFERROR(IF(E39=0,"",K39/J39),"") | N39: =F39*J39 -> 0 | O39: =F39*I39 -> 0
C40: {=IF(B40="","",XLOOKUP(B40,DATOS!D41:D1000,DATOS!C41:C1000,0,0,1))} | D40: =IF(B40="","", SUMIFS(COMPRAS!$G$5:$G1000,COMPRAS!$E$5:$E1000,B40)) | E40: =IF(C40="","", SUMIFS(VENTAS!$F$5:$F1000,VENTAS!$D$5:$D1000,B40)) | F40: =IF(B40="","",D40-E40) | G40: =IF(B40="","",COUNTIFS(COMPRAS!$E$5:$E1000,B40)) | H40: =IF(B40="","",G40/$G$3) | I40: =IFERROR(IF(B40="","",AVERAGEIFS(VENTAS!$G$5:$G1000,VENTAS!$D$5:$D1000,B40)),0) | J40: =IFERROR(IF(C40="","",AVERAGEIFS(COMPRAS!$T$5:$T1000,COMPRAS!$E$5:$E1000,B40)),0) | K40: =IF(E40=0,"",I40-J40) -> 0 | L40: =IF(B40="","",(E40*I40)-(E40*J40)) | M40: =IFERROR(IF(E40=0,"",K40/J40),"") | N40: =F40*J40 -> 0 | O40: =F40*I40 -> 0
C41: {=IF(B41="","",XLOOKUP(B41,DATOS!D42:D1000,DATOS!C42:C1000,0,0,1))} | D41: =IF(B41="","", SUMIFS(COMPRAS!$G$5:$G1000,COMPRAS!$E$5:$E1000,B41)) | E41: =IF(C41="","", SUMIFS(VENTAS!$F$5:$F1000,VENTAS!$D$5:$D1000,B41)) | F41: =IF(B41="","",D41-E41) | G41: =IF(B41="","",COUNTIFS(COMPRAS!$E$5:$E1000,B41)) | H41: =IF(B41="","",G41/$G$3) | I41: =IFERROR(IF(B41="","",AVERAGEIFS(VENTAS!$G$5:$G1000,VENTAS!$D$5:$D1000,B41)),0) | J41: =IFERROR(IF(C41="","",AVERAGEIFS(COMPRAS!$T$5:$T1000,COMPRAS!$E$5:$E1000,B41)),0) | K41: =IF(E41=0,"",I41-J41) -> 0 | L41: =IF(B41="","",(E41*I41)-(E41*J41)) | M41: =IFERROR(IF(E41=0,"",K41/J41),"") | N41: =F41*J41 -> 0 | O41: =F41*I41 -> 0
C42: {=IF(B42="","",XLOOKUP(B42,DATOS!D43:D1000,DATOS!C43:C1000,0,0,1))} | D42: =IF(B42="","", SUMIFS(COMPRAS!$G$5:$G1000,COMPRAS!$E$5:$E1000,B42)) | E42: =IF(C42="","", SUMIFS(VENTAS!$F$5:$F1000,VENTAS!$D$5:$D1000,B42)) | F42: =IF(B42="","",D42-E42) | G42: =IF(B42="","",COUNTIFS(COMPRAS!$E$5:$E1000,B42)) | H42: =IF(B42="","",G42/$G$3) | I42: =IFERROR(IF(B42="","",AVERAGEIFS(VENTAS!$G$5:$G1000,VENTAS!$D$5:$D1000,B42)),0) | J42: =IFERROR(IF(C42="","",AVERAGEIFS(COMPRAS!$T$5:$T1000,COMPRAS!$E$5:$E1000,B42)),0) | K42: =IF(E42=0,"",I42-J42) -> 0 | L42: =IF(B42="","",(E42*I42)-(E42*J42)) | M42: =IFERROR(IF(E42=0,"",K42/J42),"") | N42: =F42*J42 -> 0 | O42: =F42*I42 -> 0
C43: {=IF(B43="","",XLOOKUP(B43,DATOS!D44:D1000,DATOS!C44:C1000,0,0,1))} | D43: =IF(B43="","", SUMIFS(COMPRAS!$G$5:$G1000,COMPRAS!$E$5:$E1000,B43)) | E43: =IF(C43="","", SUMIFS(VENTAS!$F$5:$F1000,VENTAS!$D$5:$D1000,B43)) | F43: =IF(B43="","",D43-E43) | G43: =IF(B43="","",COUNTIFS(COMPRAS!$E$5:$E1000,B43)) | H43: =IF(B43="","",G43/$G$3) | I43: =IFERROR(IF(B43="","",AVERAGEIFS(VENTAS!$G$5:$G1000,VENTAS!$D$5:$D1000,B43)),0) | J43: =IFERROR(IF(C43="","",AVERAGEIFS(COMPRAS!$T$5:$T1000,COMPRAS!$E$5:$E1000,B43)),0) | K43: =IF(E43=0,"",I43-J43) -> 0 | L43: =IF(B43="","",(E43*I43)-(E43*J43)) | M43: =IFERROR(IF(E43=0,"",K43/J43),"") | N43: =F43*J43 -> 0 | O43: =F43*I43 -> 0
C44: {=IF(B44="","",XLOOKUP(B44,DATOS!D45:D1000,DATOS!C45:C1000,0,0,1))} | D44: =IF(B44="","", SUMIFS(COMPRAS!$G$5:$G1000,COMPRAS!$E$5:$E1000,B44)) | E44: =IF(C44="","", SUMIFS(VENTAS!$F$5:$F1000,VENTAS!$D$5:$D1000,B44)) | F44: =IF(B44="","",D44-E44) | G44: =IF(B44="","",COUNTIFS(COMPRAS!$E$5:$E1000,B44)) | H44: =IF(B44="","",G44/$G$3) | I44: =IFERROR(IF(B44="","",AVERAGEIFS(VENTAS!$G$5:$G1000,VENTAS!$D$5:$D1000,B44)),0) | J44: =IFERROR(IF(C44="","",AVERAGEIFS(COMPRAS!$T$5:$T1000,COMPRAS!$E$5:$E1000,B44)),0) | K44: =IF(E44=0,"",I44-J44) -> 0 | L44: =IF(B44="","",(E44*I44)-(E44*J44)) | M44: =IFERROR(IF(E44=0,"",K44/J44),"") | N44: =F44*J44 -> 0 | O44: =F44*I44 -> 0
C45: {=IF(B45="","",XLOOKUP(B45,DATOS!D46:D1000,DATOS!C46:C1000,0,0,1))} | D45: =IF(B45="","", SUMIFS(COMPRAS!$G$5:$G1000,COMPRAS!$E$5:$E1000,B45)) | E45: =IF(C45="","", SUMIFS(VENTAS!$F$5:$F1000,VENTAS!$D$5:$D1000,B45)) | F45: =IF(B45="","",D45-E45) | G45: =IF(B45="","",COUNTIFS(COMPRAS!$E$5:$E1000,B45)) | H45: =IF(B45="","",G45/$G$3) | I45: =IFERROR(IF(B45="","",AVERAGEIFS(VENTAS!$G$5:$G1000,VENTAS!$D$5:$D1000,B45)),0) | J45: =IFERROR(IF(C45="","",AVERAGEIFS(COMPRAS!$T$5:$T1000,COMPRAS!$E$5:$E1000,B45)),0) | K45: =IF(E45=0,"",I45-J45) -> 0 | L45: =IF(B45="","",(E45*I45)-(E45*J45)) | M45: =IFERROR(IF(E45=0,"",K45/J45),"") | N45: =F45*J45 -> 0 | O45: =F45*I45 -> 0
C46: {=IF(B46="","",XLOOKUP(B46,DATOS!D47:D1000,DATOS!C47:C1000,0,0,1))} | D46: =IF(B46="","", SUMIFS(COMPRAS!$G$5:$G1000,COMPRAS!$E$5:$E1000,B46)) | E46: =IF(C46="","", SUMIFS(VENTAS!$F$5:$F1000,VENTAS!$D$5:$D1000,B46)) | F46: =IF(B46="","",D46-E46) | G46: =IF(B46="","",COUNTIFS(COMPRAS!$E$5:$E1000,B46)) | H46: =IF(B46="","",G46/$G$3) | I46: =IFERROR(IF(B46="","",AVERAGEIFS(VENTAS!$G$5:$G1000,VENTAS!$D$5:$D1000,B46)),0) | J46: =IFERROR(IF(C46="","",AVERAGEIFS(COMPRAS!$T$5:$T1000,COMPRAS!$E$5:$E1000,B46)),0) | K46: =IF(E46=0,"",I46-J46) -> 0 | L46: =IF(B46="","",(E46*I46)-(E46*J46)) | M46: =IFERROR(IF(E46=0,"",K46/J46),"") | N46: =F46*J46 -> 0 | O46: =F46*I46 -> 0
C47: {=IF(B47="","",XLOOKUP(B47,DATOS!D48:D1000,DATOS!C48:C1000,0,0,1))} | D47: =IF(B47="","", SUMIFS(COMPRAS!$G$5:$G1000,COMPRAS!$E$5:$E1000,B47)) | E47: =IF(C47="","", SUMIFS(VENTAS!$F$5:$F1000,VENTAS!$D$5:$D1000,B47)) | F47: =IF(B47="","",D47-E47) | G47: =IF(B47="","",COUNTIFS(COMPRAS!$E$5:$E1000,B47)) | H47: =IF(B47="","",G47/$G$3) | I47: =IFERROR(IF(B47="","",AVERAGEIFS(VENTAS!$G$5:$G1000,VENTAS!$D$5:$D1000,B47)),0) | J47: =IFERROR(IF(C47="","",AVERAGEIFS(COMPRAS!$T$5:$T1000,COMPRAS!$E$5:$E1000,B47)),0) | K47: =IF(E47=0,"",I47-J47) -> 0 | L47: =IF(B47="","",(E47*I47)-(E47*J47)) | M47: =IFERROR(IF(E47=0,"",K47/J47),"") | N47: =F47*J47 -> 0 | O47: =F47*I47 -> 0
C48: {=IF(B48="","",XLOOKUP(B48,DATOS!D49:D1000,DATOS!C49:C1000,0,0,1))} | D48: =IF(B48="","", SUMIFS(COMPRAS!$G$5:$G1000,COMPRAS!$E$5:$E1000,B48)) | E48: =IF(C48="","", SUMIFS(VENTAS!$F$5:$F1000,VENTAS!$D$5:$D1000,B48)) | F48: =IF(B48="","",D48-E48) | G48: =IF(B48="","",COUNTIFS(COMPRAS!$E$5:$E1000,B48)) | H48: =IF(B48="","",G48/$G$3) | I48: =IFERROR(IF(B48="","",AVERAGEIFS(VENTAS!$G$5:$G1000,VENTAS!$D$5:$D1000,B48)),0) | J48: =IFERROR(IF(C48="","",AVERAGEIFS(COMPRAS!$T$5:$T1000,COMPRAS!$E$5:$E1000,B48)),0) | K48: =IF(E48=0,"",I48-J48) -> 0 | L48: =IF(B48="","",(E48*I48)-(E48*J48)) | M48: =IFERROR(IF(E48=0,"",K48/J48),"") | N48: =F48*J48 -> 0 | O48: =F48*I48 -> 0
C49: {=IF(B49="","",XLOOKUP(B49,DATOS!D50:D1000,DATOS!C50:C1000,0,0,1))} | D49: =IF(B49="","", SUMIFS(COMPRAS!$G$5:$G1000,COMPRAS!$E$5:$E1000,B49)) | E49: =IF(C49="","", SUMIFS(VENTAS!$F$5:$F1000,VENTAS!$D$5:$D1000,B49)) | F49: =IF(B49="","",D49-E49) | G49: =IF(B49="","",COUNTIFS(COMPRAS!$E$5:$E1000,B49)) | H49: =IF(B49="","",G49/$G$3) | I49: =IFERROR(IF(B49="","",AVERAGEIFS(VENTAS!$G$5:$G1000,VENTAS!$D$5:$D1000,B49)),0) | J49: =IFERROR(IF(C49="","",AVERAGEIFS(COMPRAS!$T$5:$T1000,COMPRAS!$E$5:$E1000,B49)),0) | K49: =IF(E49=0,"",I49-J49) -> 0 | L49: =IF(B49="","",(E49*I49)-(E49*J49)) | M49: =IFERROR(IF(E49=0,"",K49/J49),"") | N49: =F49*J49 -> 0 | O49: =F49*I49 -> 0
C50: {=IF(B50="","",XLOOKUP(B50,DATOS!D51:D1000,DATOS!C51:C1000,0,0,1))} | D50: =IF(B50="","", SUMIFS(COMPRAS!$G$5:$G1000,COMPRAS!$E$5:$E1000,B50)) | E50: =IF(C50="","", SUMIFS(VENTAS!$F$5:$F1000,VENTAS!$D$5:$D1000,B50)) | F50: =IF(B50="","",D50-E50) | G50: =IF(B50="","",COUNTIFS(COMPRAS!$E$5:$E1000,B50)) | H50: =IF(B50="","",G50/$G$3) | I50: =IFERROR(IF(B50="","",AVERAGEIFS(VENTAS!$G$5:$G1000,VENTAS!$D$5:$D1000,B50)),0) | J50: =IFERROR(IF(C50="","",AVERAGEIFS(COMPRAS!$T$5:$T1000,COMPRAS!$E$5:$E1000,B50)),0) | K50: =IF(E50=0,"",I50-J50) -> 0 | L50: =IF(B50="","",(E50*I50)-(E50*J50)) | M50: =IFERROR(IF(E50=0,"",K50/J50),"") | N50: =F50*J50 -> 0 | O50: =F50*I50 -> 0
C51: {=IF(B51="","",XLOOKUP(B51,DATOS!D52:D1000,DATOS!C52:C1000,0,0,1))} | D51: =IF(B51="","", SUMIFS(COMPRAS!$G$5:$G1000,COMPRAS!$E$5:$E1000,B51)) | E51: =IF(C51="","", SUMIFS(VENTAS!$F$5:$F1000,VENTAS!$D$5:$D1000,B51)) | F51: =IF(B51="","",D51-E51) | G51: =IF(B51="","",COUNTIFS(COMPRAS!$E$5:$E1000,B51)) | H51: =IF(B51="","",G51/$G$3) | I51: =IFERROR(IF(B51="","",AVERAGEIFS(VENTAS!$G$5:$G1000,VENTAS!$D$5:$D1000,B51)),0) | J51: =IFERROR(IF(C51="","",AVERAGEIFS(COMPRAS!$T$5:$T1000,COMPRAS!$E$5:$E1000,B51)),0) | K51: =IF(E51=0,"",I51-J51) -> 0 | L51: =IF(B51="","",(E51*I51)-(E51*J51)) | M51: =IFERROR(IF(E51=0,"",K51/J51),"") | N51: =F51*J51 -> 0 | O51: =F51*I51 -> 0
C52: {=IF(B52="","",XLOOKUP(B52,DATOS!D53:D1000,DATOS!C53:C1000,0,0,1))} | D52: =IF(B52="","", SUMIFS(COMPRAS!$G$5:$G1000,COMPRAS!$E$5:$E1000,B52)) | E52: =IF(C52="","", SUMIFS(VENTAS!$F$5:$F1000,VENTAS!$D$5:$D1000,B52)) | F52: =IF(B52="","",D52-E52) | G52: =IF(B52="","",COUNTIFS(COMPRAS!$E$5:$E1000,B52)) | H52: =IF(B52="","",G52/$G$3) | I52: =IFERROR(IF(B52="","",AVERAGEIFS(VENTAS!$G$5:$G1000,VENTAS!$D$5:$D1000,B52)),0) | J52: =IFERROR(IF(C52="","",AVERAGEIFS(COMPRAS!$T$5:$T1000,COMPRAS!$E$5:$E1000,B52)),0) | K52: =IF(E52=0,"",I52-J52) -> 0 | L52: =IF(B52="","",(E52*I52)-(E52*J52)) | M52: =IFERROR(IF(E52=0,"",K52/J52),"") | N52: =F52*J52 -> 0 | O52: =F52*I52 -> 0
C53: {=IF(B53="","",XLOOKUP(B53,DATOS!D54:D1000,DATOS!C54:C1000,0,0,1))} | D53: =IF(B53="","", SUMIFS(COMPRAS!$G$5:$G1000,COMPRAS!$E$5:$E1000,B53)) | E53: =IF(C53="","", SUMIFS(VENTAS!$F$5:$F1000,VENTAS!$D$5:$D1000,B53)) | F53: =IF(B53="","",D53-E53) | G53: =IF(B53="","",COUNTIFS(COMPRAS!$E$5:$E1000,B53)) | H53: =IF(B53="","",G53/$G$3) | I53: =IFERROR(IF(B53="","",AVERAGEIFS(VENTAS!$G$5:$G1000,VENTAS!$D$5:$D1000,B53)),0) | J53: =IFERROR(IF(C53="","",AVERAGEIFS(COMPRAS!$T$5:$T1000,COMPRAS!$E$5:$E1000,B53)),0) | K53: =IF(E53=0,"",I53-J53) -> 0 | L53: =IF(B53="","",(E53*I53)-(E53*J53)) | M53: =IFERROR(IF(E53=0,"",K53/J53),"") | N53: =F53*J53 -> 0 | O53: =F53*I53 -> 0
C54: {=IF(B54="","",XLOOKUP(B54,DATOS!D55:D1000,DATOS!C55:C1000,0,0,1))} | D54: =IF(B54="","", SUMIFS(COMPRAS!$G$5:$G1000,COMPRAS!$E$5:$E1000,B54)) | E54: =IF(C54="","", SUMIFS(VENTAS!$F$5:$F1000,VENTAS!$D$5:$D1000,B54)) | F54: =IF(B54="","",D54-E54) | G54: =IF(B54="","",COUNTIFS(COMPRAS!$E$5:$E1000,B54)) | H54: =IF(B54="","",G54/$G$3) | I54: =IFERROR(IF(B54="","",AVERAGEIFS(VENTAS!$G$5:$G1000,VENTAS!$D$5:$D1000,B54)),0) | J54: =IFERROR(IF(C54="","",AVERAGEIFS(COMPRAS!$T$5:$T1000,COMPRAS!$E$5:$E1000,B54)),0) | K54: =IF(E54=0,"",I54-J54) -> 0 | L54: =IF(B54="","",(E54*I54)-(E54*J54)) | M54: =IFERROR(IF(E54=0,"",K54/J54),"") | N54: =F54*J54 -> 0 | O54: =F54*I54 -> 0
C55: {=IF(B55="","",XLOOKUP(B55,DATOS!D56:D1000,DATOS!C56:C1000,0,0,1))} | D55: =IF(B55="","", SUMIFS(COMPRAS!$G$5:$G1000,COMPRAS!$E$5:$E1000,B55)) | E55: =IF(C55="","", SUMIFS(VENTAS!$F$5:$F1000,VENTAS!$D$5:$D1000,B55)) | F55: =IF(B55="","",D55-E55) | G55: =IF(B55="","",COUNTIFS(COMPRAS!$E$5:$E1000,B55)) | H55: =IF(B55="","",G55/$G$3) | I55: =IFERROR(IF(B55="","",AVERAGEIFS(VENTAS!$G$5:$G1000,VENTAS!$D$5:$D1000,B55)),0) | J55: =IFERROR(IF(C55="","",AVERAGEIFS(COMPRAS!$T$5:$T1000,COMPRAS!$E$5:$E1000,B55)),0) | K55: =IF(E55=0,"",I55-J55) -> 0 | L55: =IF(B55="","",(E55*I55)-(E55*J55)) | M55: =IFERROR(IF(E55=0,"",K55/J55),"") | N55: =F55*J55 -> 0 | O55: =F55*I55 -> 0
C56: {=IF(B56="","",XLOOKUP(B56,DATOS!D57:D1000,DATOS!C57:C1000,0,0,1))} | D56: =IF(B56="","", SUMIFS(COMPRAS!$G$5:$G1000,COMPRAS!$E$5:$E1000,B56)) | E56: =IF(C56="","", SUMIFS(VENTAS!$F$5:$F1000,VENTAS!$D$5:$D1000,B56)) | F56: =IF(B56="","",D56-E56) | G56: =IF(B56="","",COUNTIFS(COMPRAS!$E$5:$E1000,B56)) | H56: =IF(B56="","",G56/$G$3) | I56: =IFERROR(IF(B56="","",AVERAGEIFS(VENTAS!$G$5:$G1000,VENTAS!$D$5:$D1000,B56)),0) | J56: =IFERROR(IF(C56="","",AVERAGEIFS(COMPRAS!$T$5:$T1000,COMPRAS!$E$5:$E1000,B56)),0) | K56: =IF(E56=0,"",I56-J56) -> 0 | L56: =IF(B56="","",(E56*I56)-(E56*J56)) | M56: =IFERROR(IF(E56=0,"",K56/J56),"") | N56: =F56*J56 -> 0 | O56: =F56*I56 -> 0
C57: {=IF(B57="","",XLOOKUP(B57,DATOS!D58:D1000,DATOS!C58:C1000,0,0,1))} | D57: =IF(B57="","", SUMIFS(COMPRAS!$G$5:$G1000,COMPRAS!$E$5:$E1000,B57)) | E57: =IF(C57="","", SUMIFS(VENTAS!$F$5:$F1000,VENTAS!$D$5:$D1000,B57)) | F57: =IF(B57="","",D57-E57) | G57: =IF(B57="","",COUNTIFS(COMPRAS!$E$5:$E1000,B57)) | H57: =IF(B57="","",G57/$G$3) | I57: =IFERROR(IF(B57="","",AVERAGEIFS(VENTAS!$G$5:$G1000,VENTAS!$D$5:$D1000,B57)),0) | J57: =IFERROR(IF(C57="","",AVERAGEIFS(COMPRAS!$T$5:$T1000,COMPRAS!$E$5:$E1000,B57)),0) | K57: =IF(E57=0,"",I57-J57) -> 0 | L57: =IF(B57="","",(E57*I57)-(E57*J57)) | M57: =IFERROR(IF(E57=0,"",K57/J57),"") | N57: =F57*J57 -> 0 | O57: =F57*I57 -> 0
C58: {=IF(B58="","",XLOOKUP(B58,DATOS!D59:D1000,DATOS!C59:C1000,0,0,1))} | D58: =IF(B58="","", SUMIFS(COMPRAS!$G$5:$G1000,COMPRAS!$E$5:$E1000,B58)) | E58: =IF(C58="","", SUMIFS(VENTAS!$F$5:$F1000,VENTAS!$D$5:$D1000,B58)) | F58: =IF(B58="","",D58-E58) | G58: =IF(B58="","",COUNTIFS(COMPRAS!$E$5:$E1000,B58)) | H58: =IF(B58="","",G58/$G$3) | I58: =IFERROR(IF(B58="","",AVERAGEIFS(VENTAS!$G$5:$G1000,VENTAS!$D$5:$D1000,B58)),0) | J58: =IFERROR(IF(C58="","",AVERAGEIFS(COMPRAS!$T$5:$T1000,COMPRAS!$E$5:$E1000,B58)),0) | K58: =IF(E58=0,"",I58-J58) -> 0 | L58: =IF(B58="","",(E58*I58)-(E58*J58)) | M58: =IFERROR(IF(E58=0,"",K58/J58),"") | N58: =F58*J58 -> 0 | O58: =F58*I58 -> 0
C59: {=IF(B59="","",XLOOKUP(B59,DATOS!D60:D1000,DATOS!C60:C1000,0,0,1))} | D59: =IF(B59="","", SUMIFS(COMPRAS!$G$5:$G1000,COMPRAS!$E$5:$E1000,B59)) | E59: =IF(C59="","", SUMIFS(VENTAS!$F$5:$F1000,VENTAS!$D$5:$D1000,B59)) | F59: =IF(B59="","",D59-E59) | G59: =IF(B59="","",COUNTIFS(COMPRAS!$E$5:$E1000,B59)) | H59: =IF(B59="","",G59/$G$3) | I59: =IFERROR(IF(B59="","",AVERAGEIFS(VENTAS!$G$5:$G1000,VENTAS!$D$5:$D1000,B59)),0) | J59: =IFERROR(IF(C59="","",AVERAGEIFS(COMPRAS!$T$5:$T1000,COMPRAS!$E$5:$E1000,B59)),0) | K59: =IF(E59=0,"",I59-J59) -> 0 | L59: =IF(B59="","",(E59*I59)-(E59*J59)) | M59: =IFERROR(IF(E59=0,"",K59/J59),"") | N59: =F59*J59 -> 0 | O59: =F59*I59 -> 0
C60: {=IF(B60="","",XLOOKUP(B60,DATOS!D61:D1000,DATOS!C61:C1000,0,0,1))} | D60: =IF(B60="","", SUMIFS(COMPRAS!$G$5:$G1000,COMPRAS!$E$5:$E1000,B60)) | E60: =IF(C60="","", SUMIFS(VENTAS!$F$5:$F1000,VENTAS!$D$5:$D1000,B60)) | F60: =IF(B60="","",D60-E60) | G60: =IF(B60="","",COUNTIFS(COMPRAS!$E$5:$E1000,B60)) | H60: =IF(B60="","",G60/$G$3) | I60: =IFERROR(IF(B60="","",AVERAGEIFS(VENTAS!$G$5:$G1000,VENTAS!$D$5:$D1000,B60)),0) | J60: =IFERROR(IF(C60="","",AVERAGEIFS(COMPRAS!$T$5:$T1000,COMPRAS!$E$5:$E1000,B60)),0) | K60: =IF(E60=0,"",I60-J60) -> 0 | L60: =IF(B60="","",(E60*I60)-(E60*J60)) | M60: =IFERROR(IF(E60=0,"",K60/J60),"") | N60: =F60*J60 -> 0 | O60: =F60*I60 -> 0
C61: {=IF(B61="","",XLOOKUP(B61,DATOS!D62:D1000,DATOS!C62:C1000,0,0,1))} | D61: =IF(B61="","", SUMIFS(COMPRAS!$G$5:$G1000,COMPRAS!$E$5:$E1000,B61)) | E61: =IF(C61="","", SUMIFS(VENTAS!$F$5:$F1000,VENTAS!$D$5:$D1000,B61)) | F61: =IF(B61="","",D61-E61) | G61: =IF(B61="","",COUNTIFS(COMPRAS!$E$5:$E1000,B61)) | H61: =IF(B61="","",G61/$G$3) | I61: =IFERROR(IF(B61="","",AVERAGEIFS(VENTAS!$G$5:$G1000,VENTAS!$D$5:$D1000,B61)),0) | J61: =IFERROR(IF(C61="","",AVERAGEIFS(COMPRAS!$T$5:$T1000,COMPRAS!$E$5:$E1000,B61)),0) | K61: =IF(E61=0,"",I61-J61) -> 0 | L61: =IF(B61="","",(E61*I61)-(E61*J61)) | M61: =IFERROR(IF(E61=0,"",K61/J61),"") | N61: =F61*J61 -> 0 | O61: =F61*I61 -> 0
C62: {=IF(B62="","",XLOOKUP(B62,DATOS!D63:D1000,DATOS!C63:C1000,0,0,1))} | D62: =IF(B62="","", SUMIFS(COMPRAS!$G$5:$G1000,COMPRAS!$E$5:$E1000,B62)) | E62: =IF(C62="","", SUMIFS(VENTAS!$F$5:$F1000,VENTAS!$D$5:$D1000,B62)) | F62: =IF(B62="","",D62-E62) | G62: =IF(B62="","",COUNTIFS(COMPRAS!$E$5:$E1000,B62)) | H62: =IF(B62="","",G62/$G$3) | I62: =IFERROR(IF(B62="","",AVERAGEIFS(VENTAS!$G$5:$G1000,VENTAS!$D$5:$D1000,B62)),0) | J62: =IFERROR(IF(C62="","",AVERAGEIFS(COMPRAS!$T$5:$T1000,COMPRAS!$E$5:$E1000,B62)),0) | K62: =IF(E62=0,"",I62-J62) -> 0 | L62: =IF(B62="","",(E62*I62)-(E62*J62)) | M62: =IFERROR(IF(E62=0,"",K62/J62),"") | N62: =F62*J62 -> 0 | O62: =F62*I62 -> 0
C63: {=IF(B63="","",XLOOKUP(B63,DATOS!D64:D1000,DATOS!C64:C1000,0,0,1))} | D63: =IF(B63="","", SUMIFS(COMPRAS!$G$5:$G1000,COMPRAS!$E$5:$E1000,B63)) | E63: =IF(C63="","", SUMIFS(VENTAS!$F$5:$F1000,VENTAS!$D$5:$D1000,B63)) | F63: =IF(B63="","",D63-E63) | G63: =IF(B63="","",COUNTIFS(COMPRAS!$E$5:$E1000,B63)) | H63: =IF(B63="","",G63/$G$3) | I63: =IFERROR(IF(B63="","",AVERAGEIFS(VENTAS!$G$5:$G1000,VENTAS!$D$5:$D1000,B63)),0) | J63: =IFERROR(IF(C63="","",AVERAGEIFS(COMPRAS!$T$5:$T1000,COMPRAS!$E$5:$E1000,B63)),0) | K63: =IF(E63=0,"",I63-J63) -> 0 | L63: =IF(B63="","",(E63*I63)-(E63*J63)) | M63: =IFERROR(IF(E63=0,"",K63/J63),"") | N63: =F63*J63 -> 0 | O63: =F63*I63 -> 0
C64: {=IF(B64="","",XLOOKUP(B64,DATOS!D65:D1000,DATOS!C65:C1000,0,0,1))} | D64: =IF(B64="","", SUMIFS(COMPRAS!$G$5:$G1000,COMPRAS!$E$5:$E1000,B64)) | E64: =IF(C64="","", SUMIFS(VENTAS!$F$5:$F1000,VENTAS!$D$5:$D1000,B64)) | F64: =IF(B64="","",D64-E64) | G64: =IF(B64="","",COUNTIFS(COMPRAS!$E$5:$E1000,B64)) | H64: =IF(B64="","",G64/$G$3) | I64: =IFERROR(IF(B64="","",AVERAGEIFS(VENTAS!$G$5:$G1000,VENTAS!$D$5:$D1000,B64)),0) | J64: =IFERROR(IF(C64="","",AVERAGEIFS(COMPRAS!$T$5:$T1000,COMPRAS!$E$5:$E1000,B64)),0) | K64: =IF(E64=0,"",I64-J64) -> 0 | L64: =IF(B64="","",(E64*I64)-(E64*J64)) | M64: =IFERROR(IF(E64=0,"",K64/J64),"") | N64: =F64*J64 -> 0 | O64: =F64*I64 -> 0
C65: {=IF(B65="","",XLOOKUP(B65,DATOS!D66:D1000,DATOS!C66:C1000,0,0,1))} | D65: =IF(B65="","", SUMIFS(COMPRAS!$G$5:$G1000,COMPRAS!$E$5:$E1000,B65)) | E65: =IF(C65="","", SUMIFS(VENTAS!$F$5:$F1000,VENTAS!$D$5:$D1000,B65)) | F65: =IF(B65="","",D65-E65) | G65: =IF(B65="","",COUNTIFS(COMPRAS!$E$5:$E1000,B65)) | H65: =IF(B65="","",G65/$G$3) | I65: =IFERROR(IF(B65="","",AVERAGEIFS(VENTAS!$G$5:$G1000,VENTAS!$D$5:$D1000,B65)),0) | J65: =IFERROR(IF(C65="","",AVERAGEIFS(COMPRAS!$T$5:$T1000,COMPRAS!$E$5:$E1000,B65)),0) | K65: =IF(E65=0,"",I65-J65) -> 0 | L65: =IF(B65="","",(E65*I65)-(E65*J65)) | M65: =IFERROR(IF(E65=0,"",K65/J65),"") | N65: =F65*J65 -> 0 | O65: =F65*I65 -> 0
C66: {=IF(B66="","",XLOOKUP(B66,DATOS!D67:D1000,DATOS!C67:C1000,0,0,1))} | D66: =IF(B66="","", SUMIFS(COMPRAS!$G$5:$G1000,COMPRAS!$E$5:$E1000,B66)) | E66: =IF(C66="","", SUMIFS(VENTAS!$F$5:$F1000,VENTAS!$D$5:$D1000,B66)) | F66: =IF(B66="","",D66-E66) | G66: =IF(B66="","",COUNTIFS(COMPRAS!$E$5:$E1000,B66)) | H66: =IF(B66="","",G66/$G$3) | I66: =IFERROR(IF(B66="","",AVERAGEIFS(VENTAS!$G$5:$G1000,VENTAS!$D$5:$D1000,B66)),0) | J66: =IFERROR(IF(C66="","",AVERAGEIFS(COMPRAS!$T$5:$T1000,COMPRAS!$E$5:$E1000,B66)),0) | K66: =IF(E66=0,"",I66-J66) -> 0 | L66: =IF(B66="","",(E66*I66)-(E66*J66)) | M66: =IFERROR(IF(E66=0,"",K66/J66),"") | N66: =F66*J66 -> 0 | O66: =F66*I66 -> 0
C67: {=IF(B67="","",XLOOKUP(B67,DATOS!D68:D1000,DATOS!C68:C1000,0,0,1))} | D67: =IF(B67="","", SUMIFS(COMPRAS!$G$5:$G1000,COMPRAS!$E$5:$E1000,B67)) | E67: =IF(C67="","", SUMIFS(VENTAS!$F$5:$F1000,VENTAS!$D$5:$D1000,B67)) | F67: =IF(B67="","",D67-E67) | G67: =IF(B67="","",COUNTIFS(COMPRAS!$E$5:$E1000,B67)) | H67: =IF(B67="","",G67/$G$3) | I67: =IFERROR(IF(B67="","",AVERAGEIFS(VENTAS!$G$5:$G1000,VENTAS!$D$5:$D1000,B67)),0) | J67: =IFERROR(IF(C67="","",AVERAGEIFS(COMPRAS!$T$5:$T1000,COMPRAS!$E$5:$E1000,B67)),0) | K67: =IF(E67=0,"",I67-J67) -> 0 | L67: =IF(B67="","",(E67*I67)-(E67*J67)) | M67: =IFERROR(IF(E67=0,"",K67/J67),"") | N67: =F67*J67 -> 0 | O67: =F67*I67 -> 0
C68: {=IF(B68="","",XLOOKUP(B68,DATOS!D69:D1000,DATOS!C69:C1000,0,0,1))} | D68: =IF(B68="","", SUMIFS(COMPRAS!$G$5:$G1000,COMPRAS!$E$5:$E1000,B68)) | E68: =IF(C68="","", SUMIFS(VENTAS!$F$5:$F1000,VENTAS!$D$5:$D1000,B68)) | F68: =IF(B68="","",D68-E68) | G68: =IF(B68="","",COUNTIFS(COMPRAS!$E$5:$E1000,B68)) | H68: =IF(B68="","",G68/$G$3) | I68: =IFERROR(IF(B68="","",AVERAGEIFS(VENTAS!$G$5:$G1000,VENTAS!$D$5:$D1000,B68)),0) | J68: =IFERROR(IF(C68="","",AVERAGEIFS(COMPRAS!$T$5:$T1000,COMPRAS!$E$5:$E1000,B68)),0) | K68: =IF(E68=0,"",I68-J68) -> 0 | L68: =IF(B68="","",(E68*I68)-(E68*J68)) | M68: =IFERROR(IF(E68=0,"",K68/J68),"") | N68: =F68*J68 -> 0 | O68: =F68*I68 -> 0
C69: {=IF(B69="","",XLOOKUP(B69,DATOS!D70:D1000,DATOS!C70:C1000,0,0,1))} | D69: =IF(B69="","", SUMIFS(COMPRAS!$G$5:$G1000,COMPRAS!$E$5:$E1000,B69)) | E69: =IF(C69="","", SUMIFS(VENTAS!$F$5:$F1000,VENTAS!$D$5:$D1000,B69)) | F69: =IF(B69="","",D69-E69) | G69: =IF(B69="","",COUNTIFS(COMPRAS!$E$5:$E1000,B69)) | H69: =IF(B69="","",G69/$G$3) | I69: =IFERROR(IF(B69="","",AVERAGEIFS(VENTAS!$G$5:$G1000,VENTAS!$D$5:$D1000,B69)),0) | J69: =IFERROR(IF(C69="","",AVERAGEIFS(COMPRAS!$T$5:$T1000,COMPRAS!$E$5:$E1000,B69)),0) | K69: =IF(E69=0,"",I69-J69) -> 0 | L69: =IF(B69="","",(E69*I69)-(E69*J69)) | M69: =IFERROR(IF(E69=0,"",K69/J69),"") | N69: =F69*J69 -> 0 | O69: =F69*I69 -> 0
C70: {=IF(B70="","",XLOOKUP(B70,DATOS!D71:D1000,DATOS!C71:C1000,0,0,1))} | D70: =IF(B70="","", SUMIFS(COMPRAS!$G$5:$G1000,COMPRAS!$E$5:$E1000,B70)) | E70: =IF(C70="","", SUMIFS(VENTAS!$F$5:$F1000,VENTAS!$D$5:$D1000,B70)) | F70: =IF(B70="","",D70-E70) | G70: =IF(B70="","",COUNTIFS(COMPRAS!$E$5:$E1000,B70)) | H70: =IF(B70="","",G70/$G$3) | I70: =IFERROR(IF(B70="","",AVERAGEIFS(VENTAS!$G$5:$G1000,VENTAS!$D$5:$D1000,B70)),0) | J70: =IFERROR(IF(C70="","",AVERAGEIFS(COMPRAS!$T$5:$T1000,COMPRAS!$E$5:$E1000,B70)),0) | K70: =IF(E70=0,"",I70-J70) -> 0 | L70: =IF(B70="","",(E70*I70)-(E70*J70)) | M70: =IFERROR(IF(E70=0,"",K70/J70),"") | N70: =F70*J70 -> 0 | O70: =F70*I70 -> 0
C71: {=IF(B71="","",XLOOKUP(B71,DATOS!D72:D1000,DATOS!C72:C1000,0,0,1))} | D71: =IF(B71="","", SUMIFS(COMPRAS!$G$5:$G1000,COMPRAS!$E$5:$E1000,B71)) | E71: =IF(C71="","", SUMIFS(VENTAS!$F$5:$F1000,VENTAS!$D$5:$D1000,B71)) | F71: =IF(B71="","",D71-E71) | G71: =IF(B71="","",COUNTIFS(COMPRAS!$E$5:$E1000,B71)) | H71: =IF(B71="","",G71/$G$3) | I71: =IFERROR(IF(B71="","",AVERAGEIFS(VENTAS!$G$5:$G1000,VENTAS!$D$5:$D1000,B71)),0) | J71: =IFERROR(IF(C71="","",AVERAGEIFS(COMPRAS!$T$5:$T1000,COMPRAS!$E$5:$E1000,B71)),0) | K71: =IF(E71=0,"",I71-J71) -> 0 | L71: =IF(B71="","",(E71*I71)-(E71*J71)) | M71: =IFERROR(IF(E71=0,"",K71/J71),"") | N71: =F71*J71 -> 0 | O71: =F71*I71 -> 0
C72: {=IF(B72="","",XLOOKUP(B72,DATOS!D73:D1000,DATOS!C73:C1000,0,0,1))} | D72: =IF(B72="","", SUMIFS(COMPRAS!$G$5:$G1000,COMPRAS!$E$5:$E1000,B72)) | E72: =IF(C72="","", SUMIFS(VENTAS!$F$5:$F1000,VENTAS!$D$5:$D1000,B72)) | F72: =IF(B72="","",D72-E72) | G72: =IF(B72="","",COUNTIFS(COMPRAS!$E$5:$E1000,B72)) | H72: =IF(B72="","",G72/$G$3) | I72: =IFERROR(IF(B72="","",AVERAGEIFS(VENTAS!$G$5:$G1000,VENTAS!$D$5:$D1000,B72)),0) | J72: =IFERROR(IF(C72="","",AVERAGEIFS(COMPRAS!$T$5:$T1000,COMPRAS!$E$5:$E1000,B72)),0) | K72: =IF(E72=0,"",I72-J72) -> 0 | L72: =IF(B72="","",(E72*I72)-(E72*J72)) | M72: =IFERROR(IF(E72=0,"",K72/J72),"") | N72: =F72*J72 -> 0 | O72: =F72*I72 -> 0
C73: {=IF(B73="","",XLOOKUP(B73,DATOS!D74:D1000,DATOS!C74:C1000,0,0,1))} | D73: =IF(B73="","", SUMIFS(COMPRAS!$G$5:$G1000,COMPRAS!$E$5:$E1000,B73)) | E73: =IF(C73="","", SUMIFS(VENTAS!$F$5:$F1000,VENTAS!$D$5:$D1000,B73)) | F73: =IF(B73="","",D73-E73) | G73: =IF(B73="","",COUNTIFS(COMPRAS!$E$5:$E1000,B73)) | H73: =IF(B73="","",G73/$G$3) | I73: =IFERROR(IF(B73="","",AVERAGEIFS(VENTAS!$G$5:$G1000,VENTAS!$D$5:$D1000,B73)),0) | J73: =IFERROR(IF(C73="","",AVERAGEIFS(COMPRAS!$T$5:$T1000,COMPRAS!$E$5:$E1000,B73)),0) | K73: =IF(E73=0,"",I73-J73) -> 0 | L73: =IF(B73="","",(E73*I73)-(E73*J73)) | M73: =IFERROR(IF(E73=0,"",K73/J73),"") | N73: =F73*J73 -> 0 | O73: =F73*I73 -> 0
C74: {=IF(B74="","",XLOOKUP(B74,DATOS!D75:D1000,DATOS!C75:C1000,0,0,1))} | D74: =IF(B74="","", SUMIFS(COMPRAS!$G$5:$G1000,COMPRAS!$E$5:$E1000,B74)) | E74: =IF(C74="","", SUMIFS(VENTAS!$F$5:$F1000,VENTAS!$D$5:$D1000,B74)) | F74: =IF(B74="","",D74-E74) | G74: =IF(B74="","",COUNTIFS(COMPRAS!$E$5:$E1000,B74)) | H74: =IF(B74="","",G74/$G$3) | I74: =IFERROR(IF(B74="","",AVERAGEIFS(VENTAS!$G$5:$G1000,VENTAS!$D$5:$D1000,B74)),0) | J74: =IFERROR(IF(C74="","",AVERAGEIFS(COMPRAS!$T$5:$T1000,COMPRAS!$E$5:$E1000,B74)),0) | K74: =IF(E74=0,"",I74-J74) -> 0 | L74: =IF(B74="","",(E74*I74)-(E74*J74)) | M74: =IFERROR(IF(E74=0,"",K74/J74),"") | N74: =F74*J74 -> 0 | O74: =F74*I74 -> 0
C75: {=IF(B75="","",XLOOKUP(B75,DATOS!D76:D1000,DATOS!C76:C1000,0,0,1))} | D75: =IF(B75="","", SUMIFS(COMPRAS!$G$5:$G1000,COMPRAS!$E$5:$E1000,B75)) | E75: =IF(C75="","", SUMIFS(VENTAS!$F$5:$F1000,VENTAS!$D$5:$D1000,B75)) | F75: =IF(B75="","",D75-E75) | G75: =IF(B75="","",COUNTIFS(COMPRAS!$E$5:$E1000,B75)) | H75: =IF(B75="","",G75/$G$3) | I75: =IFERROR(IF(B75="","",AVERAGEIFS(VENTAS!$G$5:$G1000,VENTAS!$D$5:$D1000,B75)),0) | J75: =IFERROR(IF(C75="","",AVERAGEIFS(COMPRAS!$T$5:$T1000,COMPRAS!$E$5:$E1000,B75)),0) | K75: =IF(E75=0,"",I75-J75) -> 0 | L75: =IF(B75="","",(E75*I75)-(E75*J75)) | M75: =IFERROR(IF(E75=0,"",K75/J75),"") | N75: =F75*J75 -> 0 | O75: =F75*I75 -> 0
C76: {=IF(B76="","",XLOOKUP(B76,DATOS!D77:D1000,DATOS!C77:C1000,0,0,1))} | D76: =IF(B76="","", SUMIFS(COMPRAS!$G$5:$G1000,COMPRAS!$E$5:$E1000,B76)) | E76: =IF(C76="","", SUMIFS(VENTAS!$F$5:$F1000,VENTAS!$D$5:$D1000,B76)) | F76: =IF(B76="","",D76-E76) | G76: =IF(B76="","",COUNTIFS(COMPRAS!$E$5:$E1000,B76)) | H76: =IF(B76="","",G76/$G$3) | I76: =IFERROR(IF(B76="","",AVERAGEIFS(VENTAS!$G$5:$G1000,VENTAS!$D$5:$D1000,B76)),0) | J76: =IFERROR(IF(C76="","",AVERAGEIFS(COMPRAS!$T$5:$T1000,COMPRAS!$E$5:$E1000,B76)),0) | K76: =IF(E76=0,"",I76-J76) -> 0 | L76: =IF(B76="","",(E76*I76)-(E76*J76)) | M76: =IFERROR(IF(E76=0,"",K76/J76),"") | N76: =F76*J76 -> 0 | O76: =F76*I76 -> 0
C77: {=IF(B77="","",XLOOKUP(B77,DATOS!D78:D1000,DATOS!C78:C1000,0,0,1))} | D77: =IF(B77="","", SUMIFS(COMPRAS!$G$5:$G1000,COMPRAS!$E$5:$E1000,B77)) | E77: =IF(C77="","", SUMIFS(VENTAS!$F$5:$F1000,VENTAS!$D$5:$D1000,B77)) | F77: =IF(B77="","",D77-E77) | G77: =IF(B77="","",COUNTIFS(COMPRAS!$E$5:$E1000,B77)) | H77: =IF(B77="","",G77/$G$3) | I77: =IFERROR(IF(B77="","",AVERAGEIFS(VENTAS!$G$5:$G1000,VENTAS!$D$5:$D1000,B77)),0) | J77: =IFERROR(IF(C77="","",AVERAGEIFS(COMPRAS!$T$5:$T1000,COMPRAS!$E$5:$E1000,B77)),0) | K77: =IF(E77=0,"",I77-J77) -> 0 | L77: =IF(B77="","",(E77*I77)-(E77*J77)) | M77: =IFERROR(IF(E77=0,"",K77/J77),"") | N77: =F77*J77 -> 0 | O77: =F77*I77 -> 0
C78: {=IF(B78="","",XLOOKUP(B78,DATOS!D79:D1000,DATOS!C79:C1000,0,0,1))} | D78: =IF(B78="","", SUMIFS(COMPRAS!$G$5:$G1000,COMPRAS!$E$5:$E1000,B78)) | E78: =IF(C78="","", SUMIFS(VENTAS!$F$5:$F1000,VENTAS!$D$5:$D1000,B78)) | F78: =IF(B78="","",D78-E78) | G78: =IF(B78="","",COUNTIFS(COMPRAS!$E$5:$E1000,B78)) | H78: =IF(B78="","",G78/$G$3) | I78: =IFERROR(IF(B78="","",AVERAGEIFS(VENTAS!$G$5:$G1000,VENTAS!$D$5:$D1000,B78)),0) | J78: =IFERROR(IF(C78="","",AVERAGEIFS(COMPRAS!$T$5:$T1000,COMPRAS!$E$5:$E1000,B78)),0) | K78: =IF(E78=0,"",I78-J78) -> 0 | L78: =IF(B78="","",(E78*I78)-(E78*J78)) | M78: =IFERROR(IF(E78=0,"",K78/J78),"") | N78: =F78*J78 -> 0 | O78: =F78*I78 -> 0
C79: {=IF(B79="","",XLOOKUP(B79,DATOS!D80:D1000,DATOS!C80:C1000,0,0,1))} | D79: =IF(B79="","", SUMIFS(COMPRAS!$G$5:$G1000,COMPRAS!$E$5:$E1000,B79)) | E79: =IF(C79="","", SUMIFS(VENTAS!$F$5:$F1000,VENTAS!$D$5:$D1000,B79)) | F79: =IF(B79="","",D79-E79) | G79: =IF(B79="","",COUNTIFS(COMPRAS!$E$5:$E1000,B79)) | H79: =IF(B79="","",G79/$G$3) | I79: =IFERROR(IF(B79="","",AVERAGEIFS(VENTAS!$G$5:$G1000,VENTAS!$D$5:$D1000,B79)),0) | J79: =IFERROR(IF(C79="","",AVERAGEIFS(COMPRAS!$T$5:$T1000,COMPRAS!$E$5:$E1000,B79)),0) | K79: =IF(E79=0,"",I79-J79) -> 0 | L79: =IF(B79="","",(E79*I79)-(E79*J79)) | M79: =IFERROR(IF(E79=0,"",K79/J79),"") | N79: =F79*J79 -> 0 | O79: =F79*I79 -> 0
